Workbook

Sheet README
A1: 6-Month Cluster Revenue & COE Demand-Supply Forecast
A2: Built from: Pipeline Details, Skill Data, Employee Details, Project Allocation Details
A4: HOW THIS MODEL WORKS
A5: 1. Revenue_Trend tab: Total company revenue for Jan-Jun 2026 (given) is trended forward with FORECAST.LINEAR to get a top-down TOTAL revenue estimate for Jul-Dec 2026.
A6: 2. Pipeline_Data tab: Every open pipeline deal/role line (Pipeline Details > Forecast tab) is cleaned, mapped to a rate-card role, and its revenue is spread across the months it runs using day-count proration.
A7: 3. Cluster_Forecast tab: The bottom-up pipeline revenue is used only to work out each Cluster's % SHARE of business each month (since Cluster is only tagged in the pipeline, not in historical actuals). That % share is then applied to the top-down TOTAL revenue trend from step 1. This is the blend the user requested: 'get the forecasted revenue from previous data and spread that revenue based on the cluster achievable %s in the pipeline'.
A8: 4. COE_Supply_Demand tab: Pipeline role requests are mapped to a Centre of Excellence (COE) to estimate DEMAND headcount by COE by month. SUPPLY is active headcount by COE (from Skill Data + Employee Details) minus employees already billable on confirmed projects (from Project Allocation Details).
A10: KEY ASSUMPTIONS - PLEASE REVIEW & EDIT (blue cells)
A11: - Rate_Card and Role_Mapping tabs are editable assumption tables (blue font = input). Pipeline role codes (e.g. 'SC', 'PA', 'Sr DS SME') are mapped to a standard role/location/COE using best-fit judgement - please correct any mapping that looks wrong.
A12: - Deal duration/allocation values with unusual formats in the source (e.g. '75/100', '25-50') were averaged. Rows missing a duration were defaulted to the pipeline's median duration.
A13: - Cluster is not tagged anywhere in the 3-years-of-actuals data provided, only in the future pipeline. This is why the model blends top-down total trend x bottom-up cluster mix, rather than trending each cluster's history directly. If a project-level table with Cluster + Project Type (Internal/BAU/Sales) + monthly revenue becomes available, that should replace this workaround with a direct per-cluster trend/FORECAST.ETS.
A14: - 'Internal / BAU / Sales' project exclusion could not be applied because no project-type field exists in any of the 5 source files - the pipeline tab used here only contains client opportunities, so no explicit exclusion was needed for the bottom-up piece.
... A16: - Only 286 of 665 active employees have a recorded Skill/COE tag in Skill Data; Supply figures reflect only that mapped population - flagged in the COE tab.

Sheet Rate_Card
A1: Role Rate Card (USD Day Rate) - Source: Client Rate Card screenshot
A2: Blue cells = editable inputs. Used by Pipeline_Data to price each pipeline role request.
A4: Role | B4: Location | C4: Day Rate (USD)
A5: Associate Partner | B5: UK | C5: 3526
A6: Principal | B6: UK | C6: 3234
A7: Manager | B7: UK | C7: 2984
A8: Senior Consultant | B8: UK | C8: 2798
A9: Consultant | B9: UK | C9: 2457
A10: Senior Associate Consultant | B10: UK | C10: 1979
A11: Associate Consultant | B11: UK | C11: 1866
A12: Intern | B12: UK | C12: 1866
A13: Senior Solutions Consultant | B13: UK | C13: 2798
A14: Solutions Consultant | B14: UK | C14: 2457
A15: Principal Technology Architect | B15: IN | C15: 845
A16: Technical Solutions Architect | B16: IN | C16: 748
... A34: Technical Solutions Architect | B34: USA | C34: 3234

Sheet Role_Mapping
A1: Pipeline Role-Code Mapping (ASSUMPTION - please review/correct)
A2: Maps each 'Resources Requested' code from Pipeline Details > Forecast to a Rate_Card role, a default location, and a Skill-Data COE.
A4: Pipeline Role Code | B4: Mapped Role (Rate_Card) | C4: Default Location | D4: Mapped COE | E4: Confidence
A5: AC | B5: Associate Consultant | C5: IN | D5: Consulting | E5: High
A6: AC (UK) | B6: Associate Consultant | C6: UK | D6: Consulting | E6: High
A7: AP | B7: Associate Partner | C7: UK | D7: GTM | E7: Medium
A8: AP/P | B8: Associate Partner | C8: UK | D8: GTM | E8: Medium
A9: C | B9: Consultant | C9: IN | D9: Consulting | E9: High
A10: C/SAC/AC | B10: Consultant | C10: IN | D10: Consulting | E10: Low - multi-role code, picked mid-point
A11: EM | B11: Manager | C11: UK | D11: Consulting | E11: Medium - Engagement Manager proxy
A12: Enabler | B12: Solutions Enabler | C12: IN | D12: Data Engineering | E12: Medium
A13: GTM Architect | B13: Principal Technology Architect | C13: IN | D13: GTM | E13: Medium
A14: M | B14: Manager | C14: UK | D14: Consulting | E14: High
A15: P | B15: Associate Partner | C15: UK | D15: GTM | E15: Medium - 'Partner' not separately rate-carded
... A31: Sr Sol Con | B31: Senior Solutions Consultant | C31: IN | D31: Power BI & Consulting | E31: High

Sheet Pipeline_Data
A1: Pipeline Deal-Role Lines (cleaned from Pipeline Details > Forecast) with Revenue Calculation
A2: Revenue per line = Day Rate x Working Days x Allocation% , then spread across the 6 forecast months by day-overlap proration.
A4: DealID | B4: Cluster | C4: Client | D4: RoleCode | E4: Start Date | F4: Weeks | G4: End Date | H4: Alloc % | I4: Status | J4: Mapped Role | K4: Location | L4: Day Rate (USD) | M4: Working Days | N4: Total Deal Revenue (USD) | O4: Total Days | P4: Mapped COE | Q4: Jul-2026 (Revenue) | R4: Aug-2026 (Revenue) | S4: Sep-2026 (Revenue) | T4: Oct-2026 (Revenue) | U4: Nov-2026 (Revenue) | V4: Dec-2026 (Revenue) | W4: Jul-2026 (Demand FTE) | X4: Aug-2026 (Demand FTE) | Y4: Sep-2026 (Demand FTE) | Z4: Oct-2026 (Demand FTE) | AA4: Nov-2026 (Demand FTE) | AB4: Dec-2026 (Demand FTE)
A5: 1 | B5: 3 | C5: Sigma | D5: P | E5: 46209 | F5: 11 | G5: 46286 | H5: 0.25 | I5: Not Resourced | J5: =IFERROR(VLOOKUP(D5,Role_Mapping!$A$5:$D$31,2,FALSE()),"UNMAPPED") -> Associate Partner | K5: =IFERROR(VLOOKUP(D5,Role_Mapping!$A$5:$D$31,3,FALSE()),"IN") -> UK | L5: =IFERROR(SUMPRODUCT((Rate_Card!$A$5:$A$34=J5)*(Rate_Card!$B$5:$B$34=K5)*Rate_Card!$C$5:$C$34),0) -> 3526 | M5: =F5*5 -> 55 | N5: =L5*M5*H5 -> 48482.5 | O5: =(G5-E5)+1 -> 78 | P5: =IFERROR(VLOOKUP(D5,Role_Mapping!$A$5:$D$31,4,FALSE()),"UNMAPPED") -> GTM | Q5: =$N5*MAX(0,(MIN($G5,DATE(2026,7,31))-MAX($E5,DATE(2026,7,1))+1))/$O5 -> 16160.833 | R5: =$N5*MAX(0,(MIN($G5,DATE(2026,8,31))-MAX($E5,DATE(2026,8,1))+1))/$O5 -> 19268.686 | S5: =$N5*MAX(0,(MIN($G5,DATE(2026,9,30))-MAX($E5,DATE(2026,9,1))+1))/$O5 -> 13052.981 | T5: =$N5*MAX(0,(MIN($G5,DATE(2026,10,31))-MAX($E5,DATE(2026,10,1))+1))/$O5 -> 0 | U5: =$N5*MAX(0,(MIN($G5,DATE(2026,11,30))-MAX($E5,DATE(2026,11,1))+1))/$O5 -> 0 | V5: =$N5*MAX(0,(MIN($G5,DATE(2026,12,31))-MAX($E5,DATE(2026,12,1))+1))/$O5 -> 0 | W5: =$H5*MAX(0,(MIN($G5,DATE(2026,7,31))-MAX($E5,DATE(2026,7,1))+1))/30.4 -> 0.21381579 | X5: =$H5*MAX(0,(MIN($G5,DATE(2026,8,31))-MAX($E5,DATE(2026,8,1))+1))/30.4 -> 0.25493421 | Y5: =$H5*MAX(0,(MIN($G5,DATE(2026,9,30))-MAX($E5,DATE(2026,9,1))+1))/30.4 -> 0.17269737 | Z5: =$H5*MAX(0,(MIN($G5,DATE(2026,10,31))-MAX($E5,DATE(2026,10,1))+1))/30.4 -> 0 | AA5: =$H5*MAX(0,(MIN($G5,DATE(2026,11,30))-MAX($E5,DATE(2026,11,1))+1))/30.4 -> 0 | AB5: =$H5*MAX(0,(MIN($G5,DATE(2026,12,31))-MAX($E5,DATE(2026,12,1))+1))/30.4 -> 0
A6: 1 | B6: 3 | C6: Sigma | D6: SC | E6: 46209 | F6: 11 | G6: 46286 | H6: 0.5 | I6: Not Resourced | J6: =IFERROR(VLOOKUP(D6,Role_Mapping!$A$5:$D$31,2,FALSE()),"UNMAPPED") -> Senior Consultant | K6: =IFERROR(VLOOKUP(D6,Role_Mapping!$A$5:$D$31,3,FALSE()),"IN") -> UK | L6: =IFERROR(SUMPRODUCT((Rate_Card!$A$5:$A$34=J6)*(Rate_Card!$B$5:$B$34=K6)*Rate_Card!$C$5:$C$34),0) -> 2798 | M6: =F6*5 -> 55 | N6: =L6*M6*H6 -> 76945 | O6: =(G6-E6)+1 -> 78 | P6: =IFERROR(VLOOKUP(D6,Role_Mapping!$A$5:$D$31,4,FALSE()),"UNMAPPED") -> Consulting | Q6: =$N6*MAX(0,(MIN($G6,DATE(2026,7,31))-MAX($E6,DATE(2026,7,1))+1))/$O6 -> 25648.333 | R6: =$N6*MAX(0,(MIN($G6,DATE(2026,8,31))-MAX($E6,DATE(2026,8,1))+1))/$O6 -> 30580.705 | S6: =$N6*MAX(0,(MIN($G6,DATE(2026,9,30))-MAX($E6,DATE(2026,9,1))+1))/$O6 -> 20715.962 | T6: =$N6*MAX(0,(MIN($G6,DATE(2026,10,31))-MAX($E6,DATE(2026,10,1))+1))/$O6 -> 0 | U6: =$N6*MAX(0,(MIN($G6,DATE(2026,11,30))-MAX($E6,DATE(2026,11,1))+1))/$O6 -> 0 | V6: =$N6*MAX(0,(MIN($G6,DATE(2026,12,31))-MAX($E6,DATE(2026,12,1))+1))/$O6 -> 0 | W6: =$H6*MAX(0,(MIN($G6,DATE(2026,7,31))-MAX($E6,DATE(2026,7,1))+1))/30.4 -> 0.42763158 | X6: =$H6*MAX(0,(MIN($G6,DATE(2026,8,31))-MAX($E6,DATE(2026,8,1))+1))/30.4 -> 0.50986842 | Y6: =$H6*MAX(0,(MIN($G6,DATE(2026,9,30))-MAX($E6,DATE(2026,9,1))+1))/30.4 -> 0.34539474 | Z6: =$H6*MAX(0,(MIN($G6,DATE(2026,10,31))-MAX($E6,DATE(2026,10,1))+1))/30.4 -> 0 | AA6: =$H6*MAX(0,(MIN($G6,DATE(2026,11,30))-MAX($E6,DATE(2026,11,1))+1))/30.4 -> 0 | AB6: =$H6*MAX(0,(MIN($G6,DATE(2026,12,31))-MAX($E6,DATE(2026,12,1))+1))/30.4 -> 0
A7: 1 | B7: 3 | C7: Sigma | D7: C | E7: 46209 | F7: 11 | G7: 46286 | H7: 1 | I7: Not Resourced | J7: =IFERROR(VLOOKUP(D7,Role_Mapping!$A$5:$D$31,2,FALSE()),"UNMAPPED") -> Consultant | K7: =IFERROR(VLOOKUP(D7,Role_Mapping!$A$5:$D$31,3,FALSE()),"IN") -> IN | L7: =IFERROR(SUMPRODUCT((Rate_Card!$A$5:$A$34=J7)*(Rate_Card!$B$5:$B$34=K7)*Rate_Card!$C$5:$C$34),0) -> 683 | M7: =F7*5 -> 55 | N7: =L7*M7*H7 -> 37565 | O7: =(G7-E7)+1 -> 78 | P7: =IFERROR(VLOOKUP(D7,Role_Mapping!$A$5:$D$31,4,FALSE()),"UNMAPPED") -> Consulting | Q7: =$N7*MAX(0,(MIN($G7,DATE(2026,7,31))-MAX($E7,DATE(2026,7,1))+1))/$O7 -> 12521.667 | R7: =$N7*MAX(0,(MIN($G7,DATE(2026,8,31))-MAX($E7,DATE(2026,8,1))+1))/$O7 -> 14929.679 | S7: =$N7*MAX(0,(MIN($G7,DATE(2026,9,30))-MAX($E7,DATE(2026,9,1))+1))/$O7 -> 10113.654 | T7: =$N7*MAX(0,(MIN($G7,DATE(2026,10,31))-MAX($E7,DATE(2026,10,1))+1))/$O7 -> 0 | U7: =$N7*MAX(0,(MIN($G7,DATE(2026,11,30))-MAX($E7,DATE(2026,11,1))+1))/$O7 -> 0 | V7: =$N7*MAX(0,(MIN($G7,DATE(2026,12,31))-MAX($E7,DATE(2026,12,1))+1))/$O7 -> 0 | W7: =$H7*MAX(0,(MIN($G7,DATE(2026,7,31))-MAX($E7,DATE(2026,7,1))+1))/30.4 -> 0.85526316 | X7: =$H7*MAX(0,(MIN($G7,DATE(2026,8,31))-MAX($E7,DATE(2026,8,1))+1))/30.4 -> 1.0197368 | Y7: =$H7*MAX(0,(MIN($G7,DATE(2026,9,30))-MAX($E7,DATE(2026,9,1))+1))/30.4 -> 0.69078947 | Z7: =$H7*MAX(0,(MIN($G7,DATE(2026,10,31))-MAX($E7,DATE(2026,10,1))+1))/30.4 -> 0 | AA7: =$H7*MAX(0,(MIN($G7,DATE(2026,11,30))-MAX($E7,DATE(2026,11,1))+1))/30.4 -> 0 | AB7: =$H7*MAX(0,(MIN($G7,DATE(2026,12,31))-MAX($E7,DATE(2026,12,1))+1))/30.4 -> 0
A8: 1 | B8: 3 | C8: Sigma | D8: Sr Sol Con | E8: 46209 | F8: 11 | G8: 46286 | H8: 0.875 | I8: Not Resourced | J8: =IFERROR(VLOOKUP(D8,Role_Mapping!$A$5:$D$31,2,FALSE()),"UNMAPPED") -> Senior Solutions Consultant | K8: =IFERROR(VLOOKUP(D8,Role_Mapping!$A$5:$D$31,3,FALSE()),"IN") -> IN | L8: =IFERROR(SUMPRODUCT((Rate_Card!$A$5:$A$34=J8)*(Rate_Card!$B$5:$B$34=K8)*Rate_Card!$C$5:$C$34),0) -> 715 | M8: =F8*5 -> 55 | N8: =L8*M8*H8 -> 34409.375 | O8: =(G8-E8)+1 -> 78 | P8: =IFERROR(VLOOKUP(D8,Role_Mapping!$A$5:$D$31,4,FALSE()),"UNMAPPED") -> Power BI & Consulting | Q8: =$N8*MAX(0,(MIN($G8,DATE(2026,7,31))-MAX($E8,DATE(2026,7,1))+1))/$O8 -> 11469.792 | R8: =$N8*MAX(0,(MIN($G8,DATE(2026,8,31))-MAX($E8,DATE(2026,8,1))+1))/$O8 -> 13675.521 | S8: =$N8*MAX(0,(MIN($G8,DATE(2026,9,30))-MAX($E8,DATE(2026,9,1))+1))/$O8 -> 9264.0625 | T8: =$N8*MAX(0,(MIN($G8,DATE(2026,10,31))-MAX($E8,DATE(2026,10,1))+1))/$O8 -> 0 | U8: =$N8*MAX(0,(MIN($G8,DATE(2026,11,30))-MAX($E8,DATE(2026,11,1))+1))/$O8 -> 0 | V8: =$N8*MAX(0,(MIN($G8,DATE(2026,12,31))-MAX($E8,DATE(2026,12,1))+1))/$O8 -> 0 | W8: =$H8*MAX(0,(MIN($G8,DATE(2026,7,31))-MAX($E8,DATE(2026,7,1))+1))/30.4 -> 0.74835526 | X8: =$H8*MAX(0,(MIN($G8,DATE(2026,8,31))-MAX($E8,DATE(2026,8,1))+1))/30.4 -> 0.89226974 | Y8: =$H8*MAX(0,(MIN($G8,DATE(2026,9,30))-MAX($E8,DATE(2026,9,1))+1))/30.4 -> 0.60444079 | Z8: =$H8*MAX(0,(MIN($G8,DATE(2026,10,31))-MAX($E8,DATE(2026,10,1))+1))/30.4 -> 0 | AA8: =$H8*MAX(0,(MIN($G8,DATE(2026,11,30))-MAX($E8,DATE(2026,11,1))+1))/30.4 -> 0 | AB8: =$H8*MAX(0,(MIN($G8,DATE(2026,12,31))-MAX($E8,DATE(2026,12,1))+1))/30.4 -> 0
A9: 1 | B9: 3 | C9: Sigma | D9: SSE | E9: 46209 | F9: 11 | G9: 46286 | H9: 1 | I9: Not Resourced | J9: =IFERROR(VLOOKUP(D9,Role_Mapping!$A$5:$D$31,2,FALSE()),"UNMAPPED") -> Senior Software Engineer | K9: =IFERROR(VLOOKUP(D9,Role_Mapping!$A$5:$D$31,3,FALSE()),"IN") -> IN | L9: =IFERROR(SUMPRODUCT((Rate_Card!$A$5:$A$34=J9)*(Rate_Card!$B$5:$B$34=K9)*Rate_Card!$C$5:$C$34),0) -> 585 | M9: =F9*5 -> 55 | N9: =L9*M9*H9 -> 32175 | O9: =(G9-E9)+1 -> 78 | P9: =IFERROR(VLOOKUP(D9,Role_Mapping!$A$5:$D$31,4,FALSE()),"UNMAPPED") -> Full Stack | Q9: =$N9*MAX(0,(MIN($G9,DATE(2026,7,31))-MAX($E9,DATE(2026,7,1))+1))/$O9 -> 10725 | R9: =$N9*MAX(0,(MIN($G9,DATE(2026,8,31))-MAX($E9,DATE(2026,8,1))+1))/$O9 -> 12787.5 | S9: =$N9*MAX(0,(MIN($G9,DATE(2026,9,30))-MAX($E9,DATE(2026,9,1))+1))/$O9 -> 8662.5 | T9: =$N9*MAX(0,(MIN($G9,DATE(2026,10,31))-MAX($E9,DATE(2026,10,1))+1))/$O9 -> 0 | U9: =$N9*MAX(0,(MIN($G9,DATE(2026,11,30))-MAX($E9,DATE(2026,11,1))+1))/$O9 -> 0 | V9: =$N9*MAX(0,(MIN($G9,DATE(2026,12,31))-MAX($E9,DATE(2026,12,1))+1))/$O9 -> 0 | W9: =$H9*MAX(0,(MIN($G9,DATE(2026,7,31))-MAX($E9,DATE(2026,7,1))+1))/30.4 -> 0.85526316 | X9: =$H9*MAX(0,(MIN($G9,DATE(2026,8,31))-MAX($E9,DATE(2026,8,1))+1))/30.4 -> 1.0197368 | Y9: =$H9*MAX(0,(MIN($G9,DATE(2026,9,30))-MAX($E9,DATE(2026,9,1))+1))/30.4 -> 0.69078947 | Z9: =$H9*MAX(0,(MIN($G9,DATE(2026,10,31))-MAX($E9,DATE(2026,10,1))+1))/30.4 -> 0 | AA9: =$H9*MAX(0,(MIN($G9,DATE(2026,11,30))-MAX($E9,DATE(2026,11,1))+1))/30.4 -> 0 | AB9: =$H9*MAX(0,(MIN($G9,DATE(2026,12,31))-MAX($E9,DATE(2026,12,1))+1))/30.4 -> 0
A10: 1 | B10: 3 | C10: Sigma | D10: SE | E10: 46209 | F10: 11 | G10: 46286 | H10: 1 | I10: Not Resourced | J10: =IFERROR(VLOOKUP(D10,Role_Mapping!$A$5:$D$31,2,FALSE()),"UNMAPPED") -> Software Engineer | K10: =IFERROR(VLOOKUP(D10,Role_Mapping!$A$5:$D$31,3,FALSE()),"IN") -> IN | L10: =IFERROR(SUMPRODUCT((Rate_Card!$A$5:$A$34=J10)*(Rate_Card!$B$5:$B$34=K10)*Rate_Card!$C$5:$C$34),0) -> 455 | M10: =F10*5 -> 55 | N10: =L10*M10*H10 -> 25025 | O10: =(G10-E10)+1 -> 78 | P10: =IFERROR(VLOOKUP(D10,Role_Mapping!$A$5:$D$31,4,FALSE()),"UNMAPPED") -> Full Stack | Q10: =$N10*MAX(0,(MIN($G10,DATE(2026,7,31))-MAX($E10,DATE(2026,7,1))+1))/$O10 -> 8341.6667 | R10: =$N10*MAX(0,(MIN($G10,DATE(2026,8,31))-MAX($E10,DATE(2026,8,1))+1))/$O10 -> 9945.8333 | S10: =$N10*MAX(0,(MIN($G10,DATE(2026,9,30))-MAX($E10,DATE(2026,9,1))+1))/$O10 -> 6737.5 | T10: =$N10*MAX(0,(MIN($G10,DATE(2026,10,31))-MAX($E10,DATE(2026,10,1))+1))/$O10 -> 0 | U10: =$N10*MAX(0,(MIN($G10,DATE(2026,11,30))-MAX($E10,DATE(2026,11,1))+1))/$O10 -> 0 | V10: =$N10*MAX(0,(MIN($G10,DATE(2026,12,31))-MAX($E10,DATE(2026,12,1))+1))/$O10 -> 0 | W10: =$H10*MAX(0,(MIN($G10,DATE(2026,7,31))-MAX($E10,DATE(2026,7,1))+1))/30.4 -> 0.85526316 | X10: =$H10*MAX(0,(MIN($G10,DATE(2026,8,31))-MAX($E10,DATE(2026,8,1))+1))/30.4 -> 1.0197368 | Y10: =$H10*MAX(0,(MIN($G10,DATE(2026,9,30))-MAX($E10,DATE(2026,9,1))+1))/30.4 -> 0.69078947 | Z10: =$H10*MAX(0,(MIN($G10,DATE(2026,10,31))-MAX($E10,DATE(2026,10,1))+1))/30.4 -> 0 | AA10: =$H10*MAX(0,(MIN($G10,DATE(2026,11,30))-MAX($E10,DATE(2026,11,1))+1))/30.4 -> 0 | AB10: =$H10*MAX(0,(MIN($G10,DATE(2026,12,31))-MAX($E10,DATE(2026,12,1))+1))/30.4 -> 0
A11: 2 | B11: 5 | C11: Spidy | D11: Enabler | E11: 46209 | F11: 4 | G11: 46237 | H11: 0.125 | I11: Not Resourced | J11: =IFERROR(VLOOKUP(D11,Role_Mapping!$A$5:$D$31,2,FALSE()),"UNMAPPED") -> Solutions Enabler | K11: =IFERROR(VLOOKUP(D11,Role_Mapping!$A$5:$D$31,3,FALSE()),"IN") -> IN | L11: =IFERROR(SUMPRODUCT((Rate_Card!$A$5:$A$34=J11)*(Rate_Card!$B$5:$B$34=K11)*Rate_Card!$C$5:$C$34),0) -> 683 | M11: =F11*5 -> 20 | N11: =L11*M11*H11 -> 1707.5 | O11: =(G11-E11)+1 -> 29 | P11: =IFERROR(VLOOKUP(D11,Role_Mapping!$A$5:$D$31,4,FALSE()),"UNMAPPED") -> Data Engineering | Q11: =$N11*MAX(0,(MIN($G11,DATE(2026,7,31))-MAX($E11,DATE(2026,7,1))+1))/$O11 -> 1530.8621 | R11: =$N11*MAX(0,(MIN($G11,DATE(2026,8,31))-MAX($E11,DATE(2026,8,1))+1))/$O11 -> 176.63793 | S11: =$N11*MAX(0,(MIN($G11,DATE(2026,9,30))-MAX($E11,DATE(2026,9,1))+1))/$O11 -> 0 | T11: =$N11*MAX(0,(MIN($G11,DATE(2026,10,31))-MAX($E11,DATE(2026,10,1))+1))/$O11 -> 0 | U11: =$N11*MAX(0,(MIN($G11,DATE(2026,11,30))-MAX($E11,DATE(2026,11,1))+1))/$O11 -> 0 | V11: =$N11*MAX(0,(MIN($G11,DATE(2026,12,31))-MAX($E11,DATE(2026,12,1))+1))/$O11 -> 0 | W11: =$H11*MAX(0,(MIN($G11,DATE(2026,7,31))-MAX($E11,DATE(2026,7,1))+1))/30.4 -> 0.10690789 | X11: =$H11*MAX(0,(MIN($G11,DATE(2026,8,31))-MAX($E11,DATE(2026,8,1))+1))/30.4 -> 0.012335526 | Y11: =$H11*MAX(0,(MIN($G11,DATE(2026,9,30))-MAX($E11,DATE(2026,9,1))+1))/30.4 -> 0 | Z11: =$H11*MAX(0,(MIN($G11,DATE(2026,10,31))-MAX($E11,DATE(2026,10,1))+1))/30.4 -> 0 | AA11: =$H11*MAX(0,(MIN($G11,DATE(2026,11,30))-MAX($E11,DATE(2026,11,1))+1))/30.4 -> 0 | AB11: =$H11*MAX(0,(MIN($G11,DATE(2026,12,31))-MAX($E11,DATE(2026,12,1))+1))/30.4 -> 0
A12: 2 | B12: 5 | C12: Spidy | D12: Sol Con | E12: 46209 | F12: 4 | G12: 46237 | H12: 0.5 | I12: Not Resourced | J12: =IFERROR(VLOOKUP(D12,Role_Mapping!$A$5:$D$31,2,FALSE()),"UNMAPPED") -> Solutions Consultant | K12: =IFERROR(VLOOKUP(D12,Role_Mapping!$A$5:$D$31,3,FALSE()),"IN") -> IN | L12: =IFERROR(SUMPRODUCT((Rate_Card!$A$5:$A$34=J12)*(Rate_Card!$B$5:$B$34=K12)*Rate_Card!$C$5:$C$34),0) -> 683 | M12: =F12*5 -> 20 | N12: =L12*M12*H12 -> 6830 | O12: =(G12-E12)+1 -> 29 | P12: =IFERROR(VLOOKUP(D12,Role_Mapping!$A$5:$D$31,4,FALSE()),"UNMAPPED") -> Power BI & Consulting | Q12: =$N12*MAX(0,(MIN($G12,DATE(2026,7,31))-MAX($E12,DATE(2026,7,1))+1))/$O12 -> 6123.4483 | R12: =$N12*MAX(0,(MIN($G12,DATE(2026,8,31))-MAX($E12,DATE(2026,8,1))+1))/$O12 -> 706.55172 | S12: =$N12*MAX(0,(MIN($G12,DATE(2026,9,30))-MAX($E12,DATE(2026,9,1))+1))/$O12 -> 0 | T12: =$N12*MAX(0,(MIN($G12,DATE(2026,10,31))-MAX($E12,DATE(2026,10,1))+1))/$O12 -> 0 | U12: =$N12*MAX(0,(MIN($G12,DATE(2026,11,30))-MAX($E12,DATE(2026,11,1))+1))/$O12 -> 0 | V12: =$N12*MAX(0,(MIN($G12,DATE(2026,12,31))-MAX($E12,DATE(2026,12,1))+1))/$O12 -> 0 | W12: =$H12*MAX(0,(MIN($G12,DATE(2026,7,31))-MAX($E12,DATE(2026,7,1))+1))/30.4 -> 0.42763158 | X12: =$H12*MAX(0,(MIN($G12,DATE(2026,8,31))-MAX($E12,DATE(2026,8,1))+1))/30.4 -> 0.049342105 | Y12: =$H12*MAX(0,(MIN($G12,DATE(2026,9,30))-MAX($E12,DATE(2026,9,1))+1))/30.4 -> 0 | Z12: =$H12*MAX(0,(MIN($G12,DATE(2026,10,31))-MAX($E12,DATE(2026,10,1))+1))/30.4 -> 0 | AA12: =$H12*MAX(0,(MIN($G12,DATE(2026,11,30))-MAX($E12,DATE(2026,11,1))+1))/30.4 -> 0 | AB12: =$H12*MAX(0,(MIN($G12,DATE(2026,12,31))-MAX($E12,DATE(2026,12,1))+1))/30.4 -> 0
A13: 2 | B13: 5 | C13: Spidy | D13: SE | E13: 46209 | F13: 4 | G13: 46237 | H13: 1 | I13: Not Resourced | J13: =IFERROR(VLOOKUP(D13,Role_Mapping!$A$5:$D$31,2,FALSE()),"UNMAPPED") -> Software Engineer | K13: =IFERROR(VLOOKUP(D13,Role_Mapping!$A$5:$D$31,3,FALSE()),"IN") -> IN | L13: =IFERROR(SUMPRODUCT((Rate_Card!$A$5:$A$34=J13)*(Rate_Card!$B$5:$B$34=K13)*Rate_Card!$C$5:$C$34),0) -> 455 | M13: =F13*5 -> 20 | N13: =L13*M13*H13 -> 9100 | O13: =(G13-E13)+1 -> 29 | P13: =IFERROR(VLOOKUP(D13,Role_Mapping!$A$5:$D$31,4,FALSE()),"UNMAPPED") -> Full Stack | Q13: =$N13*MAX(0,(MIN($G13,DATE(2026,7,31))-MAX($E13,DATE(2026,7,1))+1))/$O13 -> 8158.6207 | R13: =$N13*MAX(0,(MIN($G13,DATE(2026,8,31))-MAX($E13,DATE(2026,8,1))+1))/$O13 -> 941.37931 | S13: =$N13*MAX(0,(MIN($G13,DATE(2026,9,30))-MAX($E13,DATE(2026,9,1))+1))/$O13 -> 0 | T13: =$N13*MAX(0,(MIN($G13,DATE(2026,10,31))-MAX($E13,DATE(2026,10,1))+1))/$O13 -> 0 | U13: =$N13*MAX(0,(MIN($G13,DATE(2026,11,30))-MAX($E13,DATE(2026,11,1))+1))/$O13 -> 0 | V13: =$N13*MAX(0,(MIN($G13,DATE(2026,12,31))-MAX($E13,DATE(2026,12,1))+1))/$O13 -> 0 | W13: =$H13*MAX(0,(MIN($G13,DATE(2026,7,31))-MAX($E13,DATE(2026,7,1))+1))/30.4 -> 0.85526316 | X13: =$H13*MAX(0,(MIN($G13,DATE(2026,8,31))-MAX($E13,DATE(2026,8,1))+1))/30.4 -> 0.098684211 | Y13: =$H13*MAX(0,(MIN($G13,DATE(2026,9,30))-MAX($E13,DATE(2026,9,1))+1))/30.4 -> 0 | Z13: =$H13*MAX(0,(MIN($G13,DATE(2026,10,31))-MAX($E13,DATE(2026,10,1))+1))/30.4 -> 0 | AA13: =$H13*MAX(0,(MIN($G13,DATE(2026,11,30))-MAX($E13,DATE(2026,11,1))+1))/30.4 -> 0 | AB13: =$H13*MAX(0,(MIN($G13,DATE(2026,12,31))-MAX($E13,DATE(2026,12,1))+1))/30.4 -> 0
A14: 3 | B14: 4 | C14: FD | D14: AP/P | E14: 46209 | F14: 5 | G14: 46244 | H14: 0.375 | I14: Not Resourced | J14: =IFERROR(VLOOKUP(D14,Role_Mapping!$A$5:$D$31,2,FALSE()),"UNMAPPED") -> Associate Partner | K14: =IFERROR(VLOOKUP(D14,Role_Mapping!$A$5:$D$31,3,FALSE()),"IN") -> UK | L14: =IFERROR(SUMPRODUCT((Rate_Card!$A$5:$A$34=J14)*(Rate_Card!$B$5:$B$34=K14)*Rate_Card!$C$5:$C$34),0) -> 3526 | M14: =F14*5 -> 25 | N14: =L14*M14*H14 -> 33056.25 | O14: =(G14-E14)+1 -> 36 | P14: =IFERROR(VLOOKUP(D14,Role_Mapping!$A$5:$D$31,4,FALSE()),"UNMAPPED") -> GTM | Q14: =$N14*MAX(0,(MIN($G14,DATE(2026,7,31))-MAX($E14,DATE(2026,7,1))+1))/$O14 -> 23873.958 | R14: =$N14*MAX(0,(MIN($G14,DATE(2026,8,31))-MAX($E14,DATE(2026,8,1))+1))/$O14 -> 9182.2917 | S14: =$N14*MAX(0,(MIN($G14,DATE(2026,9,30))-MAX($E14,DATE(2026,9,1))+1))/$O14 -> 0 | T14: =$N14*MAX(0,(MIN($G14,DATE(2026,10,31))-MAX($E14,DATE(2026,10,1))+1))/$O14 -> 0 | U14: =$N14*MAX(0,(MIN($G14,DATE(2026,11,30))-MAX($E14,DATE(2026,11,1))+1))/$O14 -> 0 | V14: =$N14*MAX(0,(MIN($G14,DATE(2026,12,31))-MAX($E14,DATE(2026,12,1))+1))/$O14 -> 0 | W14: =$H14*MAX(0,(MIN($G14,DATE(2026,7,31))-MAX($E14,DATE(2026,7,1))+1))/30.4 -> 0.32072368 | X14: =$H14*MAX(0,(MIN($G14,DATE(2026,8,31))-MAX($E14,DATE(2026,8,1))+1))/30.4 -> 0.12335526 | Y14: =$H14*MAX(0,(MIN($G14,DATE(2026,9,30))-MAX($E14,DATE(2026,9,1))+1))/30.4 -> 0 | Z14: =$H14*MAX(0,(MIN($G14,DATE(2026,10,31))-MAX($E14,DATE(2026,10,1))+1))/30.4 -> 0 | AA14: =$H14*MAX(0,(MIN($G14,DATE(2026,11,30))-MAX($E14,DATE(2026,11,1))+1))/30.4 -> 0 | AB14: =$H14*MAX(0,(MIN($G14,DATE(2026,12,31))-MAX($E14,DATE(2026,12,1))+1))/30.4 -> 0
A15: 3 | B15: 4 | C15: FD | D15: PA | E15: 46209 | F15: 5 | G15: 46244 | H15: 0.25 | I15: Not Resourced | J15: =IFERROR(VLOOKUP(D15,Role_Mapping!$A$5:$D$31,2,FALSE()),"UNMAPPED") -> Principal Technology Architect | K15: =IFERROR(VLOOKUP(D15,Role_Mapping!$A$5:$D$31,3,FALSE()),"IN") -> IN | L15: =IFERROR(SUMPRODUCT((Rate_Card!$A$5:$A$34=J15)*(Rate_Card!$B$5:$B$34=K15)*Rate_Card!$C$5:$C$34),0) -> 845 | M15: =F15*5 -> 25 | N15: =L15*M15*H15 -> 5281.25 | O15: =(G15-E15)+1 -> 36 | P15: =IFERROR(VLOOKUP(D15,Role_Mapping!$A$5:$D$31,4,FALSE()),"UNMAPPED") -> Full Stack | Q15: =$N15*MAX(0,(MIN($G15,DATE(2026,7,31))-MAX($E15,DATE(2026,7,1))+1))/$O15 -> 3814.2361 | R15: =$N15*MAX(0,(MIN($G15,DATE(2026,8,31))-MAX($E15,DATE(2026,8,1))+1))/$O15 -> 1467.0139 | S15: =$N15*MAX(0,(MIN($G15,DATE(2026,9,30))-MAX($E15,DATE(2026,9,1))+1))/$O15 -> 0 | T15: =$N15*MAX(0,(MIN($G15,DATE(2026,10,31))-MAX($E15,DATE(2026,10,1))+1))/$O15 -> 0 | U15: =$N15*MAX(0,(MIN($G15,DATE(2026,11,30))-MAX($E15,DATE(2026,11,1))+1))/$O15 -> 0 | V15: =$N15*MAX(0,(MIN($G15,DATE(2026,12,31))-MAX($E15,DATE(2026,12,1))+1))/$O15 -> 0 | W15: =$H15*MAX(0,(MIN($G15,DATE(2026,7,31))-MAX($E15,DATE(2026,7,1))+1))/30.4 -> 0.21381579 | X15: =$H15*MAX(0,(MIN($G15,DATE(2026,8,31))-MAX($E15,DATE(2026,8,1))+1))/30.4 -> 0.082236842 | Y15: =$H15*MAX(0,(MIN($G15,DATE(2026,9,30))-MAX($E15,DATE(2026,9,1))+1))/30.4 -> 0 | Z15: =$H15*MAX(0,(MIN($G15,DATE(2026,10,31))-MAX($E15,DATE(2026,10,1))+1))/30.4 -> 0 | AA15: =$H15*MAX(0,(MIN($G15,DATE(2026,11,30))-MAX($E15,DATE(2026,11,1))+1))/30.4 -> 0 | AB15: =$H15*MAX(0,(MIN($G15,DATE(2026,12,31))-MAX($E15,DATE(2026,12,1))+1))/30.4 -> 0
A16: 3 | B16: 4 | C16: FD | D16: SC (EM) | E16: 46209 | F16: 5 | G16: 46244 | H16: 0.5 | I16: Not Resourced | J16: =IFERROR(VLOOKUP(D16,Role_Mapping!$A$5:$D$31,2,FALSE()),"UNMAPPED") -> Senior Consultant | K16: =IFERROR(VLOOKUP(D16,Role_Mapping!$A$5:$D$31,3,FALSE()),"IN") -> UK | L16: =IFERROR(SUMPRODUCT((Rate_Card!$A$5:$A$34=J16)*(Rate_Card!$B$5:$B$34=K16)*Rate_Card!$C$5:$C$34),0) -> 2798 | M16: =F16*5 -> 25 | N16: =L16*M16*H16 -> 34975 | O16: =(G16-E16)+1 -> 36 | P16: =IFERROR(VLOOKUP(D16,Role_Mapping!$A$5:$D$31,4,FALSE()),"UNMAPPED") -> Consulting | Q16: =$N16*MAX(0,(MIN($G16,DATE(2026,7,31))-MAX($E16,DATE(2026,7,1))+1))/$O16 -> 25259.722 | R16: =$N16*MAX(0,(MIN($G16,DATE(2026,8,31))-MAX($E16,DATE(2026,8,1))+1))/$O16 -> 9715.2778 | S16: =$N16*MAX(0,(MIN($G16,DATE(2026,9,30))-MAX($E16,DATE(2026,9,1))+1))/$O16 -> 0 | T16: =$N16*MAX(0,(MIN($G16,DATE(2026,10,31))-MAX($E16,DATE(2026,10,1))+1))/$O16 -> 0 | U16: =$N16*MAX(0,(MIN($G16,DATE(2026,11,30))-MAX($E16,DATE(2026,11,1))+1))/$O16 -> 0 | V16: =$N16*MAX(0,(MIN($G16,DATE(2026,12,31))-MAX($E16,DATE(2026,12,1))+1))/$O16 -> 0 | W16: =$H16*MAX(0,(MIN($G16,DATE(2026,7,31))-MAX($E16,DATE(2026,7,1))+1))/30.4 -> 0.42763158 | X16: =$H16*MAX(0,(MIN($G16,DATE(2026,8,31))-MAX($E16,DATE(2026,8,1))+1))/30.4 -> 0.16447368 | Y16: =$H16*MAX(0,(MIN($G16,DATE(2026,9,30))-MAX($E16,DATE(2026,9,1))+1))/30.4 -> 0 | Z16: =$H16*MAX(0,(MIN($G16,DATE(2026,10,31))-MAX($E16,DATE(2026,10,1))+1))/30.4 -> 0 | AA16: =$H16*MAX(0,(MIN($G16,DATE(2026,11,30))-MAX($E16,DATE(2026,11,1))+1))/30.4 -> 0 | AB16: =$H16*MAX(0,(MIN($G16,DATE(2026,12,31))-MAX($E16,DATE(2026,12,1))+1))/30.4 -> 0
... A61: 11 | B61: 5 | C61: Kawasaki | D61: P | E61: 46195 | F61: 8 | G61: 46251 | H61: 0.125 | I61: Resourced | J61: =IFERROR(VLOOKUP(D61,Role_Mapping!$A$5:$D$31,2,FALSE()),"UNMAPPED") -> Associate Partner | K61: =IFERROR(VLOOKUP(D61,Role_Mapping!$A$5:$D$31,3,FALSE()),"IN") -> UK | L61: =IFERROR(SUMPRODUCT((Rate_Card!$A$5:$A$34=J61)*(Rate_Card!$B$5:$B$34=K61)*Rate_Card!$C$5:$C$34),0) -> 3526 | M61: =F61*5 -> 40 | N61: =L61*M61*H61 -> 17630 | O61: =(G61-E61)+1 -> 57 | P61: =IFERROR(VLOOKUP(D61,Role_Mapping!$A$5:$D$31,4,FALSE()),"UNMAPPED") -> GTM | Q61: =$N61*MAX(0,(MIN($G61,DATE(2026,7,31))-MAX($E61,DATE(2026,7,1))+1))/$O61 -> 9588.2456 | R61: =$N61*MAX(0,(MIN($G61,DATE(2026,8,31))-MAX($E61,DATE(2026,8,1))+1))/$O61 -> 5258.0702 | S61: =$N61*MAX(0,(MIN($G61,DATE(2026,9,30))-MAX($E61,DATE(2026,9,1))+1))/$O61 -> 0 | T61: =$N61*MAX(0,(MIN($G61,DATE(2026,10,31))-MAX($E61,DATE(2026,10,1))+1))/$O61 -> 0 | U61: =$N61*MAX(0,(MIN($G61,DATE(2026,11,30))-MAX($E61,DATE(2026,11,1))+1))/$O61 -> 0 | V61: =$N61*MAX(0,(MIN($G61,DATE(2026,12,31))-MAX($E61,DATE(2026,12,1))+1))/$O61 -> 0 | W61: =$H61*MAX(0,(MIN($G61,DATE(2026,7,31))-MAX($E61,DATE(2026,7,1))+1))/30.4 -> 0.12746711 | X61: =$H61*MAX(0,(MIN($G61,DATE(2026,8,31))-MAX($E61,DATE(2026,8,1))+1))/30.4 -> 0.069901316 | Y61: =$H61*MAX(0,(MIN($G61,DATE(2026,9,30))-MAX($E61,DATE(2026,9,1))+1))/30.4 -> 0 | Z61: =$H61*MAX(0,(MIN($G61,DATE(2026,10,31))-MAX($E61,DATE(2026,10,1))+1))/30.4 -> 0 | AA61: =$H61*MAX(0,(MIN($G61,DATE(2026,11,30))-MAX($E61,DATE(2026,11,1))+1))/30.4 -> 0 | AB61: =$H61*MAX(0,(MIN($G61,DATE(2026,12,31))-MAX($E61,DATE(2026,12,1))+1))/30.4 -> 0
A62: 12 | B62: 5 | D62: PA | E62: 46195 | F62: 5 | G62: 46230 | H62: 0.125 | I62: Resourced | J62: =IFERROR(VLOOKUP(D62,Role_Mapping!$A$5:$D$31,2,FALSE()),"UNMAPPED") -> Principal Technology Architect | K62: =IFERROR(VLOOKUP(D62,Role_Mapping!$A$5:$D$31,3,FALSE()),"IN") -> IN | L62: =IFERROR(SUMPRODUCT((Rate_Card!$A$5:$A$34=J62)*(Rate_Card!$B$5:$B$34=K62)*Rate_Card!$C$5:$C$34),0) -> 845 | M62: =F62*5 -> 25 | N62: =L62*M62*H62 -> 2640.625 | O62: =(G62-E62)+1 -> 36 | P62: =IFERROR(VLOOKUP(D62,Role_Mapping!$A$5:$D$31,4,FALSE()),"UNMAPPED") -> Full Stack | Q62: =$N62*MAX(0,(MIN($G62,DATE(2026,7,31))-MAX($E62,DATE(2026,7,1))+1))/$O62 -> 1980.4688 | R62: =$N62*MAX(0,(MIN($G62,DATE(2026,8,31))-MAX($E62,DATE(2026,8,1))+1))/$O62 -> 0 | S62: =$N62*MAX(0,(MIN($G62,DATE(2026,9,30))-MAX($E62,DATE(2026,9,1))+1))/$O62 -> 0 | T62: =$N62*MAX(0,(MIN($G62,DATE(2026,10,31))-MAX($E62,DATE(2026,10,1))+1))/$O62 -> 0 | U62: =$N62*MAX(0,(MIN($G62,DATE(2026,11,30))-MAX($E62,DATE(2026,11,1))+1))/$O62 -> 0 | V62: =$N62*MAX(0,(MIN($G62,DATE(2026,12,31))-MAX($E62,DATE(2026,12,1))+1))/$O62 -> 0 | W62: =$H62*MAX(0,(MIN($G62,DATE(2026,7,31))-MAX($E62,DATE(2026,7,1))+1))/30.4 -> 0.11101974 | X62: =$H62*MAX(0,(MIN($G62,DATE(2026,8,31))-MAX($E62,DATE(2026,8,1))+1))/30.4 -> 0 | Y62: =$H62*MAX(0,(MIN($G62,DATE(2026,9,30))-MAX($E62,DATE(2026,9,1))+1))/30.4 -> 0 | Z62: =$H62*MAX(0,(MIN($G62,DATE(2026,10,31))-MAX($E62,DATE(2026,10,1))+1))/30.4 -> 0 | AA62: =$H62*MAX(0,(MIN($G62,DATE(2026,11,30))-MAX($E62,DATE(2026,11,1))+1))/30.4 -> 0 | AB62: =$H62*MAX(0,(MIN($G62,DATE(2026,12,31))-MAX($E62,DATE(2026,12,1))+1))/30.4 -> 0
A63: 13 | B63: 5 | D63: SC | E63: 46195 | F63: 5 | G63: 46230 | H63: 0.5 | I63: Not Resourced | J63: =IFERROR(VLOOKUP(D63,Role_Mapping!$A$5:$D$31,2,FALSE()),"UNMAPPED") -> Senior Consultant | K63: =IFERROR(VLOOKUP(D63,Role_Mapping!$A$5:$D$31,3,FALSE()),"IN") -> UK | L63: =IFERROR(SUMPRODUCT((Rate_Card!$A$5:$A$34=J63)*(Rate_Card!$B$5:$B$34=K63)*Rate_Card!$C$5:$C$34),0) -> 2798 | M63: =F63*5 -> 25 | N63: =L63*M63*H63 -> 34975 | O63: =(G63-E63)+1 -> 36 | P63: =IFERROR(VLOOKUP(D63,Role_Mapping!$A$5:$D$31,4,FALSE()),"UNMAPPED") -> Consulting | Q63: =$N63*MAX(0,(MIN($G63,DATE(2026,7,31))-MAX($E63,DATE(2026,7,1))+1))/$O63 -> 26231.25 | R63: =$N63*MAX(0,(MIN($G63,DATE(2026,8,31))-MAX($E63,DATE(2026,8,1))+1))/$O63 -> 0 | S63: =$N63*MAX(0,(MIN($G63,DATE(2026,9,30))-MAX($E63,DATE(2026,9,1))+1))/$O63 -> 0 | T63: =$N63*MAX(0,(MIN($G63,DATE(2026,10,31))-MAX($E63,DATE(2026,10,1))+1))/$O63 -> 0 | U63: =$N63*MAX(0,(MIN($G63,DATE(2026,11,30))-MAX($E63,DATE(2026,11,1))+1))/$O63 -> 0 | V63: =$N63*MAX(0,(MIN($G63,DATE(2026,12,31))-MAX($E63,DATE(2026,12,1))+1))/$O63 -> 0 | W63: =$H63*MAX(0,(MIN($G63,DATE(2026,7,31))-MAX($E63,DATE(2026,7,1))+1))/30.4 -> 0.44407895 | X63: =$H63*MAX(0,(MIN($G63,DATE(2026,8,31))-MAX($E63,DATE(2026,8,1))+1))/30.4 -> 0 | Y63: =$H63*MAX(0,(MIN($G63,DATE(2026,9,30))-MAX($E63,DATE(2026,9,1))+1))/30.4 -> 0 | Z63: =$H63*MAX(0,(MIN($G63,DATE(2026,10,31))-MAX($E63,DATE(2026,10,1))+1))/30.4 -> 0 | AA63: =$H63*MAX(0,(MIN($G63,DATE(2026,11,30))-MAX($E63,DATE(2026,11,1))+1))/30.4 -> 0 | AB63: =$H63*MAX(0,(MIN($G63,DATE(2026,12,31))-MAX($E63,DATE(2026,12,1))+1))/30.4 -> 0
A64: 14 | B64: 5 | D64: SAC | E64: 46195 | F64: 5 | G64: 46230 | H64: 1 | I64: Not Resourced | J64: =IFERROR(VLOOKUP(D64,Role_Mapping!$A$5:$D$31,2,FALSE()),"UNMAPPED") -> Senior Associate Consultant | K64: =IFERROR(VLOOKUP(D64,Role_Mapping!$A$5:$D$31,3,FALSE()),"IN") -> IN | L64: =IFERROR(SUMPRODUCT((Rate_Card!$A$5:$A$34=J64)*(Rate_Card!$B$5:$B$34=K64)*Rate_Card!$C$5:$C$34),0) -> 683 | M64: =F64*5 -> 25 | N64: =L64*M64*H64 -> 17075 | O64: =(G64-E64)+1 -> 36 | P64: =IFERROR(VLOOKUP(D64,Role_Mapping!$A$5:$D$31,4,FALSE()),"UNMAPPED") -> Consulting | Q64: =$N64*MAX(0,(MIN($G64,DATE(2026,7,31))-MAX($E64,DATE(2026,7,1))+1))/$O64 -> 12806.25 | R64: =$N64*MAX(0,(MIN($G64,DATE(2026,8,31))-MAX($E64,DATE(2026,8,1))+1))/$O64 -> 0 | S64: =$N64*MAX(0,(MIN($G64,DATE(2026,9,30))-MAX($E64,DATE(2026,9,1))+1))/$O64 -> 0 | T64: =$N64*MAX(0,(MIN($G64,DATE(2026,10,31))-MAX($E64,DATE(2026,10,1))+1))/$O64 -> 0 | U64: =$N64*MAX(0,(MIN($G64,DATE(2026,11,30))-MAX($E64,DATE(2026,11,1))+1))/$O64 -> 0 | V64: =$N64*MAX(0,(MIN($G64,DATE(2026,12,31))-MAX($E64,DATE(2026,12,1))+1))/$O64 -> 0 | W64: =$H64*MAX(0,(MIN($G64,DATE(2026,7,31))-MAX($E64,DATE(2026,7,1))+1))/30.4 -> 0.88815789 | X64: =$H64*MAX(0,(MIN($G64,DATE(2026,8,31))-MAX($E64,DATE(2026,8,1))+1))/30.4 -> 0 | Y64: =$H64*MAX(0,(MIN($G64,DATE(2026,9,30))-MAX($E64,DATE(2026,9,1))+1))/30.4 -> 0 | Z64: =$H64*MAX(0,(MIN($G64,DATE(2026,10,31))-MAX($E64,DATE(2026,10,1))+1))/30.4 -> 0 | AA64: =$H64*MAX(0,(MIN($G64,DATE(2026,11,30))-MAX($E64,DATE(2026,11,1))+1))/30.4 -> 0 | AB64: =$H64*MAX(0,(MIN($G64,DATE(2026,12,31))-MAX($E64,DATE(2026,12,1))+1))/30.4 -> 0
A65: 15 | B65: 5 | D65: Enabler | E65: 46202 | F65: 5 | G65: 46237 | H65: 1 | I65: Not Resourced | J65: =IFERROR(VLOOKUP(D65,Role_Mapping!$A$5:$D$31,2,FALSE()),"UNMAPPED") -> Solutions Enabler | K65: =IFERROR(VLOOKUP(D65,Role_Mapping!$A$5:$D$31,3,FALSE()),"IN") -> IN | L65: =IFERROR(SUMPRODUCT((Rate_Card!$A$5:$A$34=J65)*(Rate_Card!$B$5:$B$34=K65)*Rate_Card!$C$5:$C$34),0) -> 683 | M65: =F65*5 -> 25 | N65: =L65*M65*H65 -> 17075 | O65: =(G65-E65)+1 -> 36 | P65: =IFERROR(VLOOKUP(D65,Role_Mapping!$A$5:$D$31,4,FALSE()),"UNMAPPED") -> Data Engineering | Q65: =$N65*MAX(0,(MIN($G65,DATE(2026,7,31))-MAX($E65,DATE(2026,7,1))+1))/$O65 -> 14703.472 | R65: =$N65*MAX(0,(MIN($G65,DATE(2026,8,31))-MAX($E65,DATE(2026,8,1))+1))/$O65 -> 1422.9167 | S65: =$N65*MAX(0,(MIN($G65,DATE(2026,9,30))-MAX($E65,DATE(2026,9,1))+1))/$O65 -> 0 | T65: =$N65*MAX(0,(MIN($G65,DATE(2026,10,31))-MAX($E65,DATE(2026,10,1))+1))/$O65 -> 0 | U65: =$N65*MAX(0,(MIN($G65,DATE(2026,11,30))-MAX($E65,DATE(2026,11,1))+1))/$O65 -> 0 | V65: =$N65*MAX(0,(MIN($G65,DATE(2026,12,31))-MAX($E65,DATE(2026,12,1))+1))/$O65 -> 0 | W65: =$H65*MAX(0,(MIN($G65,DATE(2026,7,31))-MAX($E65,DATE(2026,7,1))+1))/30.4 -> 1.0197368 | X65: =$H65*MAX(0,(MIN($G65,DATE(2026,8,31))-MAX($E65,DATE(2026,8,1))+1))/30.4 -> 0.098684211 | Y65: =$H65*MAX(0,(MIN($G65,DATE(2026,9,30))-MAX($E65,DATE(2026,9,1))+1))/30.4 -> 0 | Z65: =$H65*MAX(0,(MIN($G65,DATE(2026,10,31))-MAX($E65,DATE(2026,10,1))+1))/30.4 -> 0 | AA65: =$H65*MAX(0,(MIN($G65,DATE(2026,11,30))-MAX($E65,DATE(2026,11,1))+1))/30.4 -> 0 | AB65: =$H65*MAX(0,(MIN($G65,DATE(2026,12,31))-MAX($E65,DATE(2026,12,1))+1))/30.4 -> 0
A66: 16 | B66: 5 | D66: SSE | E66: 46202 | F66: 5 | G66: 46237 | H66: 1 | I66: Not Resourced | J66: =IFERROR(VLOOKUP(D66,Role_Mapping!$A$5:$D$31,2,FALSE()),"UNMAPPED") -> Senior Software Engineer | K66: =IFERROR(VLOOKUP(D66,Role_Mapping!$A$5:$D$31,3,FALSE()),"IN") -> IN | L66: =IFERROR(SUMPRODUCT((Rate_Card!$A$5:$A$34=J66)*(Rate_Card!$B$5:$B$34=K66)*Rate_Card!$C$5:$C$34),0) -> 585 | M66: =F66*5 -> 25 | N66: =L66*M66*H66 -> 14625 | O66: =(G66-E66)+1 -> 36 | P66: =IFERROR(VLOOKUP(D66,Role_Mapping!$A$5:$D$31,4,FALSE()),"UNMAPPED") -> Full Stack | Q66: =$N66*MAX(0,(MIN($G66,DATE(2026,7,31))-MAX($E66,DATE(2026,7,1))+1))/$O66 -> 12593.75 | R66: =$N66*MAX(0,(MIN($G66,DATE(2026,8,31))-MAX($E66,DATE(2026,8,1))+1))/$O66 -> 1218.75 | S66: =$N66*MAX(0,(MIN($G66,DATE(2026,9,30))-MAX($E66,DATE(2026,9,1))+1))/$O66 -> 0 | T66: =$N66*MAX(0,(MIN($G66,DATE(2026,10,31))-MAX($E66,DATE(2026,10,1))+1))/$O66 -> 0 | U66: =$N66*MAX(0,(MIN($G66,DATE(2026,11,30))-MAX($E66,DATE(2026,11,1))+1))/$O66 -> 0 | V66: =$N66*MAX(0,(MIN($G66,DATE(2026,12,31))-MAX($E66,DATE(2026,12,1))+1))/$O66 -> 0 | W66: =$H66*MAX(0,(MIN($G66,DATE(2026,7,31))-MAX($E66,DATE(2026,7,1))+1))/30.4 -> 1.0197368 | X66: =$H66*MAX(0,(MIN($G66,DATE(2026,8,31))-MAX($E66,DATE(2026,8,1))+1))/30.4 -> 0.098684211 | Y66: =$H66*MAX(0,(MIN($G66,DATE(2026,9,30))-MAX($E66,DATE(2026,9,1))+1))/30.4 -> 0 | Z66: =$H66*MAX(0,(MIN($G66,DATE(2026,10,31))-MAX($E66,DATE(2026,10,1))+1))/30.4 -> 0 | AA66: =$H66*MAX(0,(MIN($G66,DATE(2026,11,30))-MAX($E66,DATE(2026,11,1))+1))/30.4 -> 0 | AB66: =$H66*MAX(0,(MIN($G66,DATE(2026,12,31))-MAX($E66,DATE(2026,12,1))+1))/30.4 -> 0
A67: 17 | B67: 5 | D67: SE | E67: 46202 | F67: 5 | G67: 46237 | H67: 1 | I67: Not Resourced | J67: =IFERROR(VLOOKUP(D67,Role_Mapping!$A$5:$D$31,2,FALSE()),"UNMAPPED") -> Software Engineer | K67: =IFERROR(VLOOKUP(D67,Role_Mapping!$A$5:$D$31,3,FALSE()),"IN") -> IN | L67: =IFERROR(SUMPRODUCT((Rate_Card!$A$5:$A$34=J67)*(Rate_Card!$B$5:$B$34=K67)*Rate_Card!$C$5:$C$34),0) -> 455 | M67: =F67*5 -> 25 | N67: =L67*M67*H67 -> 11375 | O67: =(G67-E67)+1 -> 36 | P67: =IFERROR(VLOOKUP(D67,Role_Mapping!$A$5:$D$31,4,FALSE()),"UNMAPPED") -> Full Stack | Q67: =$N67*MAX(0,(MIN($G67,DATE(2026,7,31))-MAX($E67,DATE(2026,7,1))+1))/$O67 -> 9795.1389 | R67: =$N67*MAX(0,(MIN($G67,DATE(2026,8,31))-MAX($E67,DATE(2026,8,1))+1))/$O67 -> 947.91667 | S67: =$N67*MAX(0,(MIN($G67,DATE(2026,9,30))-MAX($E67,DATE(2026,9,1))+1))/$O67 -> 0 | T67: =$N67*MAX(0,(MIN($G67,DATE(2026,10,31))-MAX($E67,DATE(2026,10,1))+1))/$O67 -> 0 | U67: =$N67*MAX(0,(MIN($G67,DATE(2026,11,30))-MAX($E67,DATE(2026,11,1))+1))/$O67 -> 0 | V67: =$N67*MAX(0,(MIN($G67,DATE(2026,12,31))-MAX($E67,DATE(2026,12,1))+1))/$O67 -> 0 | W67: =$H67*MAX(0,(MIN($G67,DATE(2026,7,31))-MAX($E67,DATE(2026,7,1))+1))/30.4 -> 1.0197368 | X67: =$H67*MAX(0,(MIN($G67,DATE(2026,8,31))-MAX($E67,DATE(2026,8,1))+1))/30.4 -> 0.098684211 | Y67: =$H67*MAX(0,(MIN($G67,DATE(2026,9,30))-MAX($E67,DATE(2026,9,1))+1))/30.4 -> 0 | Z67: =$H67*MAX(0,(MIN($G67,DATE(2026,10,31))-MAX($E67,DATE(2026,10,1))+1))/30.4 -> 0 | AA67: =$H67*MAX(0,(MIN($G67,DATE(2026,11,30))-MAX($E67,DATE(2026,11,1))+1))/30.4 -> 0 | AB67: =$H67*MAX(0,(MIN($G67,DATE(2026,12,31))-MAX($E67,DATE(2026,12,1))+1))/30.4 -> 0
A68: 18 | B68: 2 | C68: Honda | D68: SSE | E68: 46202 | F68: 5 | G68: 46237 | H68: 1 | I68: Not Resourced | J68: =IFERROR(VLOOKUP(D68,Role_Mapping!$A$5:$D$31,2,FALSE()),"UNMAPPED") -> Senior Software Engineer | K68: =IFERROR(VLOOKUP(D68,Role_Mapping!$A$5:$D$31,3,FALSE()),"IN") -> IN | L68: =IFERROR(SUMPRODUCT((Rate_Card!$A$5:$A$34=J68)*(Rate_Card!$B$5:$B$34=K68)*Rate_Card!$C$5:$C$34),0) -> 585 | M68: =F68*5 -> 25 | N68: =L68*M68*H68 -> 14625 | O68: =(G68-E68)+1 -> 36 | P68: =IFERROR(VLOOKUP(D68,Role_Mapping!$A$5:$D$31,4,FALSE()),"UNMAPPED") -> Full Stack | Q68: =$N68*MAX(0,(MIN($G68,DATE(2026,7,31))-MAX($E68,DATE(2026,7,1))+1))/$O68 -> 12593.75 | R68: =$N68*MAX(0,(MIN($G68,DATE(2026,8,31))-MAX($E68,DATE(2026,8,1))+1))/$O68 -> 1218.75 | S68: =$N68*MAX(0,(MIN($G68,DATE(2026,9,30))-MAX($E68,DATE(2026,9,1))+1))/$O68 -> 0 | T68: =$N68*MAX(0,(MIN($G68,DATE(2026,10,31))-MAX($E68,DATE(2026,10,1))+1))/$O68 -> 0 | U68: =$N68*MAX(0,(MIN($G68,DATE(2026,11,30))-MAX($E68,DATE(2026,11,1))+1))/$O68 -> 0 | V68: =$N68*MAX(0,(MIN($G68,DATE(2026,12,31))-MAX($E68,DATE(2026,12,1))+1))/$O68 -> 0 | W68: =$H68*MAX(0,(MIN($G68,DATE(2026,7,31))-MAX($E68,DATE(2026,7,1))+1))/30.4 -> 1.0197368 | X68: =$H68*MAX(0,(MIN($G68,DATE(2026,8,31))-MAX($E68,DATE(2026,8,1))+1))/30.4 -> 0.098684211 | Y68: =$H68*MAX(0,(MIN($G68,DATE(2026,9,30))-MAX($E68,DATE(2026,9,1))+1))/30.4 -> 0 | Z68: =$H68*MAX(0,(MIN($G68,DATE(2026,10,31))-MAX($E68,DATE(2026,10,1))+1))/30.4 -> 0 | AA68: =$H68*MAX(0,(MIN($G68,DATE(2026,11,30))-MAX($E68,DATE(2026,11,1))+1))/30.4 -> 0 | AB68: =$H68*MAX(0,(MIN($G68,DATE(2026,12,31))-MAX($E68,DATE(2026,12,1))+1))/30.4 -> 0
A69: 19 | B69: 5 | C69: KTM | D69: P | E69: 46195 | F69: 12 | G69: 46279 | H69: 0.5 | I69: Part Resourced | J69: =IFERROR(VLOOKUP(D69,Role_Mapping!$A$5:$D$31,2,FALSE()),"UNMAPPED") -> Associate Partner | K69: =IFERROR(VLOOKUP(D69,Role_Mapping!$A$5:$D$31,3,FALSE()),"IN") -> UK | L69: =IFERROR(SUMPRODUCT((Rate_Card!$A$5:$A$34=J69)*(Rate_Card!$B$5:$B$34=K69)*Rate_Card!$C$5:$C$34),0) -> 3526 | M69: =F69*5 -> 60 | N69: =L69*M69*H69 -> 105780 | O69: =(G69-E69)+1 -> 85 | P69: =IFERROR(VLOOKUP(D69,Role_Mapping!$A$5:$D$31,4,FALSE()),"UNMAPPED") -> GTM | Q69: =$N69*MAX(0,(MIN($G69,DATE(2026,7,31))-MAX($E69,DATE(2026,7,1))+1))/$O69 -> 38578.588 | R69: =$N69*MAX(0,(MIN($G69,DATE(2026,8,31))-MAX($E69,DATE(2026,8,1))+1))/$O69 -> 38578.588 | S69: =$N69*MAX(0,(MIN($G69,DATE(2026,9,30))-MAX($E69,DATE(2026,9,1))+1))/$O69 -> 17422.588 | T69: =$N69*MAX(0,(MIN($G69,DATE(2026,10,31))-MAX($E69,DATE(2026,10,1))+1))/$O69 -> 0 | U69: =$N69*MAX(0,(MIN($G69,DATE(2026,11,30))-MAX($E69,DATE(2026,11,1))+1))/$O69 -> 0 | V69: =$N69*MAX(0,(MIN($G69,DATE(2026,12,31))-MAX($E69,DATE(2026,12,1))+1))/$O69 -> 0 | W69: =$H69*MAX(0,(MIN($G69,DATE(2026,7,31))-MAX($E69,DATE(2026,7,1))+1))/30.4 -> 0.50986842 | X69: =$H69*MAX(0,(MIN($G69,DATE(2026,8,31))-MAX($E69,DATE(2026,8,1))+1))/30.4 -> 0.50986842 | Y69: =$H69*MAX(0,(MIN($G69,DATE(2026,9,30))-MAX($E69,DATE(2026,9,1))+1))/30.4 -> 0.23026316 | Z69: =$H69*MAX(0,(MIN($G69,DATE(2026,10,31))-MAX($E69,DATE(2026,10,1))+1))/30.4 -> 0 | AA69: =$H69*MAX(0,(MIN($G69,DATE(2026,11,30))-MAX($E69,DATE(2026,11,1))+1))/30.4 -> 0 | AB69: =$H69*MAX(0,(MIN($G69,DATE(2026,12,31))-MAX($E69,DATE(2026,12,1))+1))/30.4 -> 0
A70: 20 | B70: 5 | D70: C | E70: 46195 | F70: 5 | G70: 46230 | H70: 0.5 | I70: Not Resourced | J70: =IFERROR(VLOOKUP(D70,Role_Mapping!$A$5:$D$31,2,FALSE()),"UNMAPPED") -> Consultant | K70: =IFERROR(VLOOKUP(D70,Role_Mapping!$A$5:$D$31,3,FALSE()),"IN") -> IN | L70: =IFERROR(SUMPRODUCT((Rate_Card!$A$5:$A$34=J70)*(Rate_Card!$B$5:$B$34=K70)*Rate_Card!$C$5:$C$34),0) -> 683 | M70: =F70*5 -> 25 | N70: =L70*M70*H70 -> 8537.5 | O70: =(G70-E70)+1 -> 36 | P70: =IFERROR(VLOOKUP(D70,Role_Mapping!$A$5:$D$31,4,FALSE()),"UNMAPPED") -> Consulting | Q70: =$N70*MAX(0,(MIN($G70,DATE(2026,7,31))-MAX($E70,DATE(2026,7,1))+1))/$O70 -> 6403.125 | R70: =$N70*MAX(0,(MIN($G70,DATE(2026,8,31))-MAX($E70,DATE(2026,8,1))+1))/$O70 -> 0 | S70: =$N70*MAX(0,(MIN($G70,DATE(2026,9,30))-MAX($E70,DATE(2026,9,1))+1))/$O70 -> 0 | T70: =$N70*MAX(0,(MIN($G70,DATE(2026,10,31))-MAX($E70,DATE(2026,10,1))+1))/$O70 -> 0 | U70: =$N70*MAX(0,(MIN($G70,DATE(2026,11,30))-MAX($E70,DATE(2026,11,1))+1))/$O70 -> 0 | V70: =$N70*MAX(0,(MIN($G70,DATE(2026,12,31))-MAX($E70,DATE(2026,12,1))+1))/$O70 -> 0 | W70: =$H70*MAX(0,(MIN($G70,DATE(2026,7,31))-MAX($E70,DATE(2026,7,1))+1))/30.4 -> 0.44407895 | X70: =$H70*MAX(0,(MIN($G70,DATE(2026,8,31))-MAX($E70,DATE(2026,8,1))+1))/30.4 -> 0 | Y70: =$H70*MAX(0,(MIN($G70,DATE(2026,9,30))-MAX($E70,DATE(2026,9,1))+1))/30.4 -> 0 | Z70: =$H70*MAX(0,(MIN($G70,DATE(2026,10,31))-MAX($E70,DATE(2026,10,1))+1))/30.4 -> 0 | AA70: =$H70*MAX(0,(MIN($G70,DATE(2026,11,30))-MAX($E70,DATE(2026,11,1))+1))/30.4 -> 0 | AB70: =$H70*MAX(0,(MIN($G70,DATE(2026,12,31))-MAX($E70,DATE(2026,12,1))+1))/30.4 -> 0
A71: 21 | B71: 5 | D71: PA | E71: 46195 | F71: 5 | G71: 46230 | H71: 0.25 | I71: Not Resourced | J71: =IFERROR(VLOOKUP(D71,Role_Mapping!$A$5:$D$31,2,FALSE()),"UNMAPPED") -> Principal Technology Architect | K71: =IFERROR(VLOOKUP(D71,Role_Mapping!$A$5:$D$31,3,FALSE()),"IN") -> IN | L71: =IFERROR(SUMPRODUCT((Rate_Card!$A$5:$A$34=J71)*(Rate_Card!$B$5:$B$34=K71)*Rate_Card!$C$5:$C$34),0) -> 845 | M71: =F71*5 -> 25 | N71: =L71*M71*H71 -> 5281.25 | O71: =(G71-E71)+1 -> 36 | P71: =IFERROR(VLOOKUP(D71,Role_Mapping!$A$5:$D$31,4,FALSE()),"UNMAPPED") -> Full Stack | Q71: =$N71*MAX(0,(MIN($G71,DATE(2026,7,31))-MAX($E71,DATE(2026,7,1))+1))/$O71 -> 3960.9375 | R71: =$N71*MAX(0,(MIN($G71,DATE(2026,8,31))-MAX($E71,DATE(2026,8,1))+1))/$O71 -> 0 | S71: =$N71*MAX(0,(MIN($G71,DATE(2026,9,30))-MAX($E71,DATE(2026,9,1))+1))/$O71 -> 0 | T71: =$N71*MAX(0,(MIN($G71,DATE(2026,10,31))-MAX($E71,DATE(2026,10,1))+1))/$O71 -> 0 | U71: =$N71*MAX(0,(MIN($G71,DATE(2026,11,30))-MAX($E71,DATE(2026,11,1))+1))/$O71 -> 0 | V71: =$N71*MAX(0,(MIN($G71,DATE(2026,12,31))-MAX($E71,DATE(2026,12,1))+1))/$O71 -> 0 | W71: =$H71*MAX(0,(MIN($G71,DATE(2026,7,31))-MAX($E71,DATE(2026,7,1))+1))/30.4 -> 0.22203947 | X71: =$H71*MAX(0,(MIN($G71,DATE(2026,8,31))-MAX($E71,DATE(2026,8,1))+1))/30.4 -> 0 | Y71: =$H71*MAX(0,(MIN($G71,DATE(2026,9,30))-MAX($E71,DATE(2026,9,1))+1))/30.4 -> 0 | Z71: =$H71*MAX(0,(MIN($G71,DATE(2026,10,31))-MAX($E71,DATE(2026,10,1))+1))/30.4 -> 0 | AA71: =$H71*MAX(0,(MIN($G71,DATE(2026,11,30))-MAX($E71,DATE(2026,11,1))+1))/30.4 -> 0 | AB71: =$H71*MAX(0,(MIN($G71,DATE(2026,12,31))-MAX($E71,DATE(2026,12,1))+1))/30.4 -> 0
A72: 22 | B72: 5 | D72: SAC or AC | E72: 46195 | F72: 5 | G72: 46230 | H72: 1 | I72: Not Resourced | J72: =IFERROR(VLOOKUP(D72,Role_Mapping!$A$5:$D$31,2,FALSE()),"UNMAPPED") -> Senior Associate Consultant | K72: =IFERROR(VLOOKUP(D72,Role_Mapping!$A$5:$D$31,3,FALSE()),"IN") -> IN | L72: =IFERROR(SUMPRODUCT((Rate_Card!$A$5:$A$34=J72)*(Rate_Card!$B$5:$B$34=K72)*Rate_Card!$C$5:$C$34),0) -> 683 | M72: =F72*5 -> 25 | N72: =L72*M72*H72 -> 17075 | O72: =(G72-E72)+1 -> 36 | P72: =IFERROR(VLOOKUP(D72,Role_Mapping!$A$5:$D$31,4,FALSE()),"UNMAPPED") -> Consulting | Q72: =$N72*MAX(0,(MIN($G72,DATE(2026,7,31))-MAX($E72,DATE(2026,7,1))+1))/$O72 -> 12806.25 | R72: =$N72*MAX(0,(MIN($G72,DATE(2026,8,31))-MAX($E72,DATE(2026,8,1))+1))/$O72 -> 0 | S72: =$N72*MAX(0,(MIN($G72,DATE(2026,9,30))-MAX($E72,DATE(2026,9,1))+1))/$O72 -> 0 | T72: =$N72*MAX(0,(MIN($G72,DATE(2026,10,31))-MAX($E72,DATE(2026,10,1))+1))/$O72 -> 0 | U72: =$N72*MAX(0,(MIN($G72,DATE(2026,11,30))-MAX($E72,DATE(2026,11,1))+1))/$O72 -> 0 | V72: =$N72*MAX(0,(MIN($G72,DATE(2026,12,31))-MAX($E72,DATE(2026,12,1))+1))/$O72 -> 0 | W72: =$H72*MAX(0,(MIN($G72,DATE(2026,7,31))-MAX($E72,DATE(2026,7,1))+1))/30.4 -> 0.88815789 | X72: =$H72*MAX(0,(MIN($G72,DATE(2026,8,31))-MAX($E72,DATE(2026,8,1))+1))/30.4 -> 0 | Y72: =$H72*MAX(0,(MIN($G72,DATE(2026,9,30))-MAX($E72,DATE(2026,9,1))+1))/30.4 -> 0 | Z72: =$H72*MAX(0,(MIN($G72,DATE(2026,10,31))-MAX($E72,DATE(2026,10,1))+1))/30.4 -> 0 | AA72: =$H72*MAX(0,(MIN($G72,DATE(2026,11,30))-MAX($E72,DATE(2026,11,1))+1))/30.4 -> 0 | AB72: =$H72*MAX(0,(MIN($G72,DATE(2026,12,31))-MAX($E72,DATE(2026,12,1))+1))/30.4 -> 0
A73: 23 | B73: 5 | D73: Sol Con | E73: 46195 | F73: 5 | G73: 46230 | H73: 1 | I73: Not Resourced | J73: =IFERROR(VLOOKUP(D73,Role_Mapping!$A$5:$D$31,2,FALSE()),"UNMAPPED") -> Solutions Consultant | K73: =IFERROR(VLOOKUP(D73,Role_Mapping!$A$5:$D$31,3,FALSE()),"IN") -> IN | L73: =IFERROR(SUMPRODUCT((Rate_Card!$A$5:$A$34=J73)*(Rate_Card!$B$5:$B$34=K73)*Rate_Card!$C$5:$C$34),0) -> 683 | M73: =F73*5 -> 25 | N73: =L73*M73*H73 -> 17075 | O73: =(G73-E73)+1 -> 36 | P73: =IFERROR(VLOOKUP(D73,Role_Mapping!$A$5:$D$31,4,FALSE()),"UNMAPPED") -> Power BI & Consulting | Q73: =$N73*MAX(0,(MIN($G73,DATE(2026,7,31))-MAX($E73,DATE(2026,7,1))+1))/$O73 -> 12806.25 | R73: =$N73*MAX(0,(MIN($G73,DATE(2026,8,31))-MAX($E73,DATE(2026,8,1))+1))/$O73 -> 0 | S73: =$N73*MAX(0,(MIN($G73,DATE(2026,9,30))-MAX($E73,DATE(2026,9,1))+1))/$O73 -> 0 | T73: =$N73*MAX(0,(MIN($G73,DATE(2026,10,31))-MAX($E73,DATE(2026,10,1))+1))/$O73 -> 0 | U73: =$N73*MAX(0,(MIN($G73,DATE(2026,11,30))-MAX($E73,DATE(2026,11,1))+1))/$O73 -> 0 | V73: =$N73*MAX(0,(MIN($G73,DATE(2026,12,31))-MAX($E73,DATE(2026,12,1))+1))/$O73 -> 0 | W73: =$H73*MAX(0,(MIN($G73,DATE(2026,7,31))-MAX($E73,DATE(2026,7,1))+1))/30.4 -> 0.88815789 | X73: =$H73*MAX(0,(MIN($G73,DATE(2026,8,31))-MAX($E73,DATE(2026,8,1))+1))/30.4 -> 0 | Y73: =$H73*MAX(0,(MIN($G73,DATE(2026,9,30))-MAX($E73,DATE(2026,9,1))+1))/30.4 -> 0 | Z73: =$H73*MAX(0,(MIN($G73,DATE(2026,10,31))-MAX($E73,DATE(2026,10,1))+1))/30.4 -> 0 | AA73: =$H73*MAX(0,(MIN($G73,DATE(2026,11,30))-MAX($E73,DATE(2026,11,1))+1))/30.4 -> 0 | AB73: =$H73*MAX(0,(MIN($G73,DATE(2026,12,31))-MAX($E73,DATE(2026,12,1))+1))/30.4 -> 0
A74: 24 | B74: 5 | D74: SSE | E74: 46195 | F74: 5 | G74: 46230 | H74: 1 | I74: Not Resourced | J74: =IFERROR(VLOOKUP(D74,Role_Mapping!$A$5:$D$31,2,FALSE()),"UNMAPPED") -> Senior Software Engineer | K74: =IFERROR(VLOOKUP(D74,Role_Mapping!$A$5:$D$31,3,FALSE()),"IN") -> IN | L74: =IFERROR(SUMPRODUCT((Rate_Card!$A$5:$A$34=J74)*(Rate_Card!$B$5:$B$34=K74)*Rate_Card!$C$5:$C$34),0) -> 585 | M74: =F74*5 -> 25 | N74: =L74*M74*H74 -> 14625 | O74: =(G74-E74)+1 -> 36 | P74: =IFERROR(VLOOKUP(D74,Role_Mapping!$A$5:$D$31,4,FALSE()),"UNMAPPED") -> Full Stack | Q74: =$N74*MAX(0,(MIN($G74,DATE(2026,7,31))-MAX($E74,DATE(2026,7,1))+1))/$O74 -> 10968.75 | R74: =$N74*MAX(0,(MIN($G74,DATE(2026,8,31))-MAX($E74,DATE(2026,8,1))+1))/$O74 -> 0 | S74: =$N74*MAX(0,(MIN($G74,DATE(2026,9,30))-MAX($E74,DATE(2026,9,1))+1))/$O74 -> 0 | T74: =$N74*MAX(0,(MIN($G74,DATE(2026,10,31))-MAX($E74,DATE(2026,10,1))+1))/$O74 -> 0 | U74: =$N74*MAX(0,(MIN($G74,DATE(2026,11,30))-MAX($E74,DATE(2026,11,1))+1))/$O74 -> 0 | V74: =$N74*MAX(0,(MIN($G74,DATE(2026,12,31))-MAX($E74,DATE(2026,12,1))+1))/$O74 -> 0 | W74: =$H74*MAX(0,(MIN($G74,DATE(2026,7,31))-MAX($E74,DATE(2026,7,1))+1))/30.4 -> 0.88815789 | X74: =$H74*MAX(0,(MIN($G74,DATE(2026,8,31))-MAX($E74,DATE(2026,8,1))+1))/30.4 -> 0 | Y74: =$H74*MAX(0,(MIN($G74,DATE(2026,9,30))-MAX($E74,DATE(2026,9,1))+1))/30.4 -> 0 | Z74: =$H74*MAX(0,(MIN($G74,DATE(2026,10,31))-MAX($E74,DATE(2026,10,1))+1))/30.4 -> 0 | AA74: =$H74*MAX(0,(MIN($G74,DATE(2026,11,30))-MAX($E74,DATE(2026,11,1))+1))/30.4 -> 0 | AB74: =$H74*MAX(0,(MIN($G74,DATE(2026,12,31))-MAX($E74,DATE(2026,12,1))+1))/30.4 -> 0
A75: 25 | B75: 5 | D75: SE | E75: 46195 | F75: 5 | G75: 46230 | H75: 1 | I75: Not Resourced | J75: =IFERROR(VLOOKUP(D75,Role_Mapping!$A$5:$D$31,2,FALSE()),"UNMAPPED") -> Software Engineer | K75: =IFERROR(VLOOKUP(D75,Role_Mapping!$A$5:$D$31,3,FALSE()),"IN") -> IN | L75: =IFERROR(SUMPRODUCT((Rate_Card!$A$5:$A$34=J75)*(Rate_Card!$B$5:$B$34=K75)*Rate_Card!$C$5:$C$34),0) -> 455 | M75: =F75*5 -> 25 | N75: =L75*M75*H75 -> 11375 | O75: =(G75-E75)+1 -> 36 | P75: =IFERROR(VLOOKUP(D75,Role_Mapping!$A$5:$D$31,4,FALSE()),"UNMAPPED") -> Full Stack | Q75: =$N75*MAX(0,(MIN($G75,DATE(2026,7,31))-MAX($E75,DATE(2026,7,1))+1))/$O75 -> 8531.25 | R75: =$N75*MAX(0,(MIN($G75,DATE(2026,8,31))-MAX($E75,DATE(2026,8,1))+1))/$O75 -> 0 | S75: =$N75*MAX(0,(MIN($G75,DATE(2026,9,30))-MAX($E75,DATE(2026,9,1))+1))/$O75 -> 0 | T75: =$N75*MAX(0,(MIN($G75,DATE(2026,10,31))-MAX($E75,DATE(2026,10,1))+1))/$O75 -> 0 | U75: =$N75*MAX(0,(MIN($G75,DATE(2026,11,30))-MAX($E75,DATE(2026,11,1))+1))/$O75 -> 0 | V75: =$N75*MAX(0,(MIN($G75,DATE(2026,12,31))-MAX($E75,DATE(2026,12,1))+1))/$O75 -> 0 | W75: =$H75*MAX(0,(MIN($G75,DATE(2026,7,31))-MAX($E75,DATE(2026,7,1))+1))/30.4 -> 0.88815789 | X75: =$H75*MAX(0,(MIN($G75,DATE(2026,8,31))-MAX($E75,DATE(2026,8,1))+1))/30.4 -> 0 | Y75: =$H75*MAX(0,(MIN($G75,DATE(2026,9,30))-MAX($E75,DATE(2026,9,1))+1))/30.4 -> 0 | Z75: =$H75*MAX(0,(MIN($G75,DATE(2026,10,31))-MAX($E75,DATE(2026,10,1))+1))/30.4 -> 0 | AA75: =$H75*MAX(0,(MIN($G75,DATE(2026,11,30))-MAX($E75,DATE(2026,11,1))+1))/30.4 -> 0 | AB75: =$H75*MAX(0,(MIN($G75,DATE(2026,12,31))-MAX($E75,DATE(2026,12,1))+1))/30.4 -> 0
A76: 26 | B76: 5 | C76: KIA | D76: AP | E76: 46195 | F76: 5 | G76: 46230 | H76: 0.125 | I76: Resourced | J76: =IFERROR(VLOOKUP(D76,Role_Mapping!$A$5:$D$31,2,FALSE()),"UNMAPPED") -> Associate Partner | K76: =IFERROR(VLOOKUP(D76,Role_Mapping!$A$5:$D$31,3,FALSE()),"IN") -> UK | L76: =IFERROR(SUMPRODUCT((Rate_Card!$A$5:$A$34=J76)*(Rate_Card!$B$5:$B$34=K76)*Rate_Card!$C$5:$C$34),0) -> 3526 | M76: =F76*5 -> 25 | N76: =L76*M76*H76 -> 11018.75 | O76: =(G76-E76)+1 -> 36 | P76: =IFERROR(VLOOKUP(D76,Role_Mapping!$A$5:$D$31,4,FALSE()),"UNMAPPED") -> GTM | Q76: =$N76*MAX(0,(MIN($G76,DATE(2026,7,31))-MAX($E76,DATE(2026,7,1))+1))/$O76 -> 8264.0625 | R76: =$N76*MAX(0,(MIN($G76,DATE(2026,8,31))-MAX($E76,DATE(2026,8,1))+1))/$O76 -> 0 | S76: =$N76*MAX(0,(MIN($G76,DATE(2026,9,30))-MAX($E76,DATE(2026,9,1))+1))/$O76 -> 0 | T76: =$N76*MAX(0,(MIN($G76,DATE(2026,10,31))-MAX($E76,DATE(2026,10,1))+1))/$O76 -> 0 | U76: =$N76*MAX(0,(MIN($G76,DATE(2026,11,30))-MAX($E76,DATE(2026,11,1))+1))/$O76 -> 0 | V76: =$N76*MAX(0,(MIN($G76,DATE(2026,12,31))-MAX($E76,DATE(2026,12,1))+1))/$O76 -> 0 | W76: =$H76*MAX(0,(MIN($G76,DATE(2026,7,31))-MAX($E76,DATE(2026,7,1))+1))/30.4 -> 0.11101974 | X76: =$H76*MAX(0,(MIN($G76,DATE(2026,8,31))-MAX($E76,DATE(2026,8,1))+1))/30.4 -> 0 | Y76: =$H76*MAX(0,(MIN($G76,DATE(2026,9,30))-MAX($E76,DATE(2026,9,1))+1))/30.4 -> 0 | Z76: =$H76*MAX(0,(MIN($G76,DATE(2026,10,31))-MAX($E76,DATE(2026,10,1))+1))/30.4 -> 0 | AA76: =$H76*MAX(0,(MIN($G76,DATE(2026,11,30))-MAX($E76,DATE(2026,11,1))+1))/30.4 -> 0 | AB76: =$H76*MAX(0,(MIN($G76,DATE(2026,12,31))-MAX($E76,DATE(2026,12,1))+1))/30.4 -> 0
A77: 27 | B77: 5 | D77: M | E77: 46195 | F77: 5 | G77: 46230 | H77: 0.5 | I77: Resourced | J77: =IFERROR(VLOOKUP(D77,Role_Mapping!$A$5:$D$31,2,FALSE()),"UNMAPPED") -> Manager | K77: =IFERROR(VLOOKUP(D77,Role_Mapping!$A$5:$D$31,3,FALSE()),"IN") -> UK | L77: =IFERROR(SUMPRODUCT((Rate_Card!$A$5:$A$34=J77)*(Rate_Card!$B$5:$B$34=K77)*Rate_Card!$C$5:$C$34),0) -> 2984 | M77: =F77*5 -> 25 | N77: =L77*M77*H77 -> 37300 | O77: =(G77-E77)+1 -> 36 | P77: =IFERROR(VLOOKUP(D77,Role_Mapping!$A$5:$D$31,4,FALSE()),"UNMAPPED") -> Consulting | Q77: =$N77*MAX(0,(MIN($G77,DATE(2026,7,31))-MAX($E77,DATE(2026,7,1))+1))/$O77 -> 27975 | R77: =$N77*MAX(0,(MIN($G77,DATE(2026,8,31))-MAX($E77,DATE(2026,8,1))+1))/$O77 -> 0 | S77: =$N77*MAX(0,(MIN($G77,DATE(2026,9,30))-MAX($E77,DATE(2026,9,1))+1))/$O77 -> 0 | T77: =$N77*MAX(0,(MIN($G77,DATE(2026,10,31))-MAX($E77,DATE(2026,10,1))+1))/$O77 -> 0 | U77: =$N77*MAX(0,(MIN($G77,DATE(2026,11,30))-MAX($E77,DATE(2026,11,1))+1))/$O77 -> 0 | V77: =$N77*MAX(0,(MIN($G77,DATE(2026,12,31))-MAX($E77,DATE(2026,12,1))+1))/$O77 -> 0 | W77: =$H77*MAX(0,(MIN($G77,DATE(2026,7,31))-MAX($E77,DATE(2026,7,1))+1))/30.4 -> 0.44407895 | X77: =$H77*MAX(0,(MIN($G77,DATE(2026,8,31))-MAX($E77,DATE(2026,8,1))+1))/30.4 -> 0 | Y77: =$H77*MAX(0,(MIN($G77,DATE(2026,9,30))-MAX($E77,DATE(2026,9,1))+1))/30.4 -> 0 | Z77: =$H77*MAX(0,(MIN($G77,DATE(2026,10,31))-MAX($E77,DATE(2026,10,1))+1))/30.4 -> 0 | AA77: =$H77*MAX(0,(MIN($G77,DATE(2026,11,30))-MAX($E77,DATE(2026,11,1))+1))/30.4 -> 0 | AB77: =$H77*MAX(0,(MIN($G77,DATE(2026,12,31))-MAX($E77,DATE(2026,12,1))+1))/30.4 -> 0
A78: 28 | B78: 5 | D78: C | E78: 46195 | F78: 5 | G78: 46230 | H78: 1 | I78: Resourced | J78: =IFERROR(VLOOKUP(D78,Role_Mapping!$A$5:$D$31,2,FALSE()),"UNMAPPED") -> Consultant | K78: =IFERROR(VLOOKUP(D78,Role_Mapping!$A$5:$D$31,3,FALSE()),"IN") -> IN | L78: =IFERROR(SUMPRODUCT((Rate_Card!$A$5:$A$34=J78)*(Rate_Card!$B$5:$B$34=K78)*Rate_Card!$C$5:$C$34),0) -> 683 | M78: =F78*5 -> 25 | N78: =L78*M78*H78 -> 17075 | O78: =(G78-E78)+1 -> 36 | P78: =IFERROR(VLOOKUP(D78,Role_Mapping!$A$5:$D$31,4,FALSE()),"UNMAPPED") -> Consulting | Q78: =$N78*MAX(0,(MIN($G78,DATE(2026,7,31))-MAX($E78,DATE(2026,7,1))+1))/$O78 -> 12806.25 | R78: =$N78*MAX(0,(MIN($G78,DATE(2026,8,31))-MAX($E78,DATE(2026,8,1))+1))/$O78 -> 0 | S78: =$N78*MAX(0,(MIN($G78,DATE(2026,9,30))-MAX($E78,DATE(2026,9,1))+1))/$O78 -> 0 | T78: =$N78*MAX(0,(MIN($G78,DATE(2026,10,31))-MAX($E78,DATE(2026,10,1))+1))/$O78 -> 0 | U78: =$N78*MAX(0,(MIN($G78,DATE(2026,11,30))-MAX($E78,DATE(2026,11,1))+1))/$O78 -> 0 | V78: =$N78*MAX(0,(MIN($G78,DATE(2026,12,31))-MAX($E78,DATE(2026,12,1))+1))/$O78 -> 0 | W78: =$H78*MAX(0,(MIN($G78,DATE(2026,7,31))-MAX($E78,DATE(2026,7,1))+1))/30.4 -> 0.88815789 | X78: =$H78*MAX(0,(MIN($G78,DATE(2026,8,31))-MAX($E78,DATE(2026,8,1))+1))/30.4 -> 0 | Y78: =$H78*MAX(0,(MIN($G78,DATE(2026,9,30))-MAX($E78,DATE(2026,9,1))+1))/30.4 -> 0 | Z78: =$H78*MAX(0,(MIN($G78,DATE(2026,10,31))-MAX($E78,DATE(2026,10,1))+1))/30.4 -> 0 | AA78: =$H78*MAX(0,(MIN($G78,DATE(2026,11,30))-MAX($E78,DATE(2026,11,1))+1))/30.4 -> 0 | AB78: =$H78*MAX(0,(MIN($G78,DATE(2026,12,31))-MAX($E78,DATE(2026,12,1))+1))/30.4 -> 0
A79: 29 | B79: 5 | D79: PA | E79: 46195 | F79: 5 | G79: 46230 | H79: 0.25 | I79: Not Resourced | J79: =IFERROR(VLOOKUP(D79,Role_Mapping!$A$5:$D$31,2,FALSE()),"UNMAPPED") -> Principal Technology Architect | K79: =IFERROR(VLOOKUP(D79,Role_Mapping!$A$5:$D$31,3,FALSE()),"IN") -> IN | L79: =IFERROR(SUMPRODUCT((Rate_Card!$A$5:$A$34=J79)*(Rate_Card!$B$5:$B$34=K79)*Rate_Card!$C$5:$C$34),0) -> 845 | M79: =F79*5 -> 25 | N79: =L79*M79*H79 -> 5281.25 | O79: =(G79-E79)+1 -> 36 | P79: =IFERROR(VLOOKUP(D79,Role_Mapping!$A$5:$D$31,4,FALSE()),"UNMAPPED") -> Full Stack | Q79: =$N79*MAX(0,(MIN($G79,DATE(2026,7,31))-MAX($E79,DATE(2026,7,1))+1))/$O79 -> 3960.9375 | R79: =$N79*MAX(0,(MIN($G79,DATE(2026,8,31))-MAX($E79,DATE(2026,8,1))+1))/$O79 -> 0 | S79: =$N79*MAX(0,(MIN($G79,DATE(2026,9,30))-MAX($E79,DATE(2026,9,1))+1))/$O79 -> 0 | T79: =$N79*MAX(0,(MIN($G79,DATE(2026,10,31))-MAX($E79,DATE(2026,10,1))+1))/$O79 -> 0 | U79: =$N79*MAX(0,(MIN($G79,DATE(2026,11,30))-MAX($E79,DATE(2026,11,1))+1))/$O79 -> 0 | V79: =$N79*MAX(0,(MIN($G79,DATE(2026,12,31))-MAX($E79,DATE(2026,12,1))+1))/$O79 -> 0 | W79: =$H79*MAX(0,(MIN($G79,DATE(2026,7,31))-MAX($E79,DATE(2026,7,1))+1))/30.4 -> 0.22203947 | X79: =$H79*MAX(0,(MIN($G79,DATE(2026,8,31))-MAX($E79,DATE(2026,8,1))+1))/30.4 -> 0 | Y79: =$H79*MAX(0,(MIN($G79,DATE(2026,9,30))-MAX($E79,DATE(2026,9,1))+1))/30.4 -> 0 | Z79: =$H79*MAX(0,(MIN($G79,DATE(2026,10,31))-MAX($E79,DATE(2026,10,1))+1))/30.4 -> 0 | AA79: =$H79*MAX(0,(MIN($G79,DATE(2026,11,30))-MAX($E79,DATE(2026,11,1))+1))/30.4 -> 0 | AB79: =$H79*MAX(0,(MIN($G79,DATE(2026,12,31))-MAX($E79,DATE(2026,12,1))+1))/30.4 -> 0
A80: 30 | B80: 5 | D80: Sol Con | E80: 46195 | F80: 5 | G80: 46230 | H80: 1 | I80: Not Resourced | J80: =IFERROR(VLOOKUP(D80,Role_Mapping!$A$5:$D$31,2,FALSE()),"UNMAPPED") -> Solutions Consultant | K80: =IFERROR(VLOOKUP(D80,Role_Mapping!$A$5:$D$31,3,FALSE()),"IN") -> IN | L80: =IFERROR(SUMPRODUCT((Rate_Card!$A$5:$A$34=J80)*(Rate_Card!$B$5:$B$34=K80)*Rate_Card!$C$5:$C$34),0) -> 683 | M80: =F80*5 -> 25 | N80: =L80*M80*H80 -> 17075 | O80: =(G80-E80)+1 -> 36 | P80: =IFERROR(VLOOKUP(D80,Role_Mapping!$A$5:$D$31,4,FALSE()),"UNMAPPED") -> Power BI & Consulting | Q80: =$N80*MAX(0,(MIN($G80,DATE(2026,7,31))-MAX($E80,DATE(2026,7,1))+1))/$O80 -> 12806.25 | R80: =$N80*MAX(0,(MIN($G80,DATE(2026,8,31))-MAX($E80,DATE(2026,8,1))+1))/$O80 -> 0 | S80: =$N80*MAX(0,(MIN($G80,DATE(2026,9,30))-MAX($E80,DATE(2026,9,1))+1))/$O80 -> 0 | T80: =$N80*MAX(0,(MIN($G80,DATE(2026,10,31))-MAX($E80,DATE(2026,10,1))+1))/$O80 -> 0 | U80: =$N80*MAX(0,(MIN($G80,DATE(2026,11,30))-MAX($E80,DATE(2026,11,1))+1))/$O80 -> 0 | V80: =$N80*MAX(0,(MIN($G80,DATE(2026,12,31))-MAX($E80,DATE(2026,12,1))+1))/$O80 -> 0 | W80: =$H80*MAX(0,(MIN($G80,DATE(2026,7,31))-MAX($E80,DATE(2026,7,1))+1))/30.4 -> 0.88815789 | X80: =$H80*MAX(0,(MIN($G80,DATE(2026,8,31))-MAX($E80,DATE(2026,8,1))+1))/30.4 -> 0 | Y80: =$H80*MAX(0,(MIN($G80,DATE(2026,9,30))-MAX($E80,DATE(2026,9,1))+1))/30.4 -> 0 | Z80: =$H80*MAX(0,(MIN($G80,DATE(2026,10,31))-MAX($E80,DATE(2026,10,1))+1))/30.4 -> 0 | AA80: =$H80*MAX(0,(MIN($G80,DATE(2026,11,30))-MAX($E80,DATE(2026,11,1))+1))/30.4 -> 0 | AB80: =$H80*MAX(0,(MIN($G80,DATE(2026,12,31))-MAX($E80,DATE(2026,12,1))+1))/30.4 -> 0
A81: 31 | B81: 5 | D81: SE | E81: 46195 | F81: 5 | G81: 46230 | H81: 1 | I81: Not Resourced | J81: =IFERROR(VLOOKUP(D81,Role_Mapping!$A$5:$D$31,2,FALSE()),"UNMAPPED") -> Software Engineer | K81: =IFERROR(VLOOKUP(D81,Role_Mapping!$A$5:$D$31,3,FALSE()),"IN") -> IN | L81: =IFERROR(SUMPRODUCT((Rate_Card!$A$5:$A$34=J81)*(Rate_Card!$B$5:$B$34=K81)*Rate_Card!$C$5:$C$34),0) -> 455 | M81: =F81*5 -> 25 | N81: =L81*M81*H81 -> 11375 | O81: =(G81-E81)+1 -> 36 | P81: =IFERROR(VLOOKUP(D81,Role_Mapping!$A$5:$D$31,4,FALSE()),"UNMAPPED") -> Full Stack | Q81: =$N81*MAX(0,(MIN($G81,DATE(2026,7,31))-MAX($E81,DATE(2026,7,1))+1))/$O81 -> 8531.25 | R81: =$N81*MAX(0,(MIN($G81,DATE(2026,8,31))-MAX($E81,DATE(2026,8,1))+1))/$O81 -> 0 | S81: =$N81*MAX(0,(MIN($G81,DATE(2026,9,30))-MAX($E81,DATE(2026,9,1))+1))/$O81 -> 0 | T81: =$N81*MAX(0,(MIN($G81,DATE(2026,10,31))-MAX($E81,DATE(2026,10,1))+1))/$O81 -> 0 | U81: =$N81*MAX(0,(MIN($G81,DATE(2026,11,30))-MAX($E81,DATE(2026,11,1))+1))/$O81 -> 0 | V81: =$N81*MAX(0,(MIN($G81,DATE(2026,12,31))-MAX($E81,DATE(2026,12,1))+1))/$O81 -> 0 | W81: =$H81*MAX(0,(MIN($G81,DATE(2026,7,31))-MAX($E81,DATE(2026,7,1))+1))/30.4 -> 0.88815789 | X81: =$H81*MAX(0,(MIN($G81,DATE(2026,8,31))-MAX($E81,DATE(2026,8,1))+1))/30.4 -> 0 | Y81: =$H81*MAX(0,(MIN($G81,DATE(2026,9,30))-MAX($E81,DATE(2026,9,1))+1))/30.4 -> 0 | Z81: =$H81*MAX(0,(MIN($G81,DATE(2026,10,31))-MAX($E81,DATE(2026,10,1))+1))/30.4 -> 0 | AA81: =$H81*MAX(0,(MIN($G81,DATE(2026,11,30))-MAX($E81,DATE(2026,11,1))+1))/30.4 -> 0 | AB81: =$H81*MAX(0,(MIN($G81,DATE(2026,12,31))-MAX($E81,DATE(2026,12,1))+1))/30.4 -> 0
A82: 32 | B82: 5 | C82: Hyundai | D82: P | E82: 46265 | F82: 5 | G82: 46300 | H82: 0.125 | I82: Not Resourced | J82: =IFERROR(VLOOKUP(D82,Role_Mapping!$A$5:$D$31,2,FALSE()),"UNMAPPED") -> Associate Partner | K82: =IFERROR(VLOOKUP(D82,Role_Mapping!$A$5:$D$31,3,FALSE()),"IN") -> UK | L82: =IFERROR(SUMPRODUCT((Rate_Card!$A$5:$A$34=J82)*(Rate_Card!$B$5:$B$34=K82)*Rate_Card!$C$5:$C$34),0) -> 3526 | M82: =F82*5 -> 25 | N82: =L82*M82*H82 -> 11018.75 | O82: =(G82-E82)+1 -> 36 | P82: =IFERROR(VLOOKUP(D82,Role_Mapping!$A$5:$D$31,4,FALSE()),"UNMAPPED") -> GTM | Q82: =$N82*MAX(0,(MIN($G82,DATE(2026,7,31))-MAX($E82,DATE(2026,7,1))+1))/$O82 -> 0 | R82: =$N82*MAX(0,(MIN($G82,DATE(2026,8,31))-MAX($E82,DATE(2026,8,1))+1))/$O82 -> 306.07639 | S82: =$N82*MAX(0,(MIN($G82,DATE(2026,9,30))-MAX($E82,DATE(2026,9,1))+1))/$O82 -> 9182.2917 | T82: =$N82*MAX(0,(MIN($G82,DATE(2026,10,31))-MAX($E82,DATE(2026,10,1))+1))/$O82 -> 1530.3819 | U82: =$N82*MAX(0,(MIN($G82,DATE(2026,11,30))-MAX($E82,DATE(2026,11,1))+1))/$O82 -> 0 | V82: =$N82*MAX(0,(MIN($G82,DATE(2026,12,31))-MAX($E82,DATE(2026,12,1))+1))/$O82 -> 0 | W82: =$H82*MAX(0,(MIN($G82,DATE(2026,7,31))-MAX($E82,DATE(2026,7,1))+1))/30.4 -> 0 | X82: =$H82*MAX(0,(MIN($G82,DATE(2026,8,31))-MAX($E82,DATE(2026,8,1))+1))/30.4 -> 0.0041118421 | Y82: =$H82*MAX(0,(MIN($G82,DATE(2026,9,30))-MAX($E82,DATE(2026,9,1))+1))/30.4 -> 0.12335526 | Z82: =$H82*MAX(0,(MIN($G82,DATE(2026,10,31))-MAX($E82,DATE(2026,10,1))+1))/30.4 -> 0.020559211 | AA82: =$H82*MAX(0,(MIN($G82,DATE(2026,11,30))-MAX($E82,DATE(2026,11,1))+1))/30.4 -> 0 | AB82: =$H82*MAX(0,(MIN($G82,DATE(2026,12,31))-MAX($E82,DATE(2026,12,1))+1))/30.4 -> 0
A83: 33 | B83: 5 | D83: M | E83: 46265 | F83: 5 | G83: 46300 | H83: 0.125 | I83: Not Resourced | J83: =IFERROR(VLOOKUP(D83,Role_Mapping!$A$5:$D$31,2,FALSE()),"UNMAPPED") -> Manager | K83: =IFERROR(VLOOKUP(D83,Role_Mapping!$A$5:$D$31,3,FALSE()),"IN") -> UK | L83: =IFERROR(SUMPRODUCT((Rate_Card!$A$5:$A$34=J83)*(Rate_Card!$B$5:$B$34=K83)*Rate_Card!$C$5:$C$34),0) -> 2984 | M83: =F83*5 -> 25 | N83: =L83*M83*H83 -> 9325 | O83: =(G83-E83)+1 -> 36 | P83: =IFERROR(VLOOKUP(D83,Role_Mapping!$A$5:$D$31,4,FALSE()),"UNMAPPED") -> Consulting | Q83: =$N83*MAX(0,(MIN($G83,DATE(2026,7,31))-MAX($E83,DATE(2026,7,1))+1))/$O83 -> 0 | R83: =$N83*MAX(0,(MIN($G83,DATE(2026,8,31))-MAX($E83,DATE(2026,8,1))+1))/$O83 -> 259.02778 | S83: =$N83*MAX(0,(MIN($G83,DATE(2026,9,30))-MAX($E83,DATE(2026,9,1))+1))/$O83 -> 7770.8333 | T83: =$N83*MAX(0,(MIN($G83,DATE(2026,10,31))-MAX($E83,DATE(2026,10,1))+1))/$O83 -> 1295.1389 | U83: =$N83*MAX(0,(MIN($G83,DATE(2026,11,30))-MAX($E83,DATE(2026,11,1))+1))/$O83 -> 0 | V83: =$N83*MAX(0,(MIN($G83,DATE(2026,12,31))-MAX($E83,DATE(2026,12,1))+1))/$O83 -> 0 | W83: =$H83*MAX(0,(MIN($G83,DATE(2026,7,31))-MAX($E83,DATE(2026,7,1))+1))/30.4 -> 0 | X83: =$H83*MAX(0,(MIN($G83,DATE(2026,8,31))-MAX($E83,DATE(2026,8,1))+1))/30.4 -> 0.0041118421 | Y83: =$H83*MAX(0,(MIN($G83,DATE(2026,9,30))-MAX($E83,DATE(2026,9,1))+1))/30.4 -> 0.12335526 | Z83: =$H83*MAX(0,(MIN($G83,DATE(2026,10,31))-MAX($E83,DATE(2026,10,1))+1))/30.4 -> 0.020559211 | AA83: =$H83*MAX(0,(MIN($G83,DATE(2026,11,30))-MAX($E83,DATE(2026,11,1))+1))/30.4 -> 0 | AB83: =$H83*MAX(0,(MIN($G83,DATE(2026,12,31))-MAX($E83,DATE(2026,12,1))+1))/30.4 -> 0
A84: 34 | B84: 5 | D84: Snr Sol Con | E84: 46265 | F84: 8 | G84: 46321 | H84: 0.5 | I84: Not Resourced | J84: =IFERROR(VLOOKUP(D84,Role_Mapping!$A$5:$D$31,2,FALSE()),"UNMAPPED") -> Senior Solutions Consultant | K84: =IFERROR(VLOOKUP(D84,Role_Mapping!$A$5:$D$31,3,FALSE()),"IN") -> IN | L84: =IFERROR(SUMPRODUCT((Rate_Card!$A$5:$A$34=J84)*(Rate_Card!$B$5:$B$34=K84)*Rate_Card!$C$5:$C$34),0) -> 715 | M84: =F84*5 -> 40 | N84: =L84*M84*H84 -> 14300 | O84: =(G84-E84)+1 -> 57 | P84: =IFERROR(VLOOKUP(D84,Role_Mapping!$A$5:$D$31,4,FALSE()),"UNMAPPED") -> Power BI & Consulting | Q84: =$N84*MAX(0,(MIN($G84,DATE(2026,7,31))-MAX($E84,DATE(2026,7,1))+1))/$O84 -> 0 | R84: =$N84*MAX(0,(MIN($G84,DATE(2026,8,31))-MAX($E84,DATE(2026,8,1))+1))/$O84 -> 250.87719 | S84: =$N84*MAX(0,(MIN($G84,DATE(2026,9,30))-MAX($E84,DATE(2026,9,1))+1))/$O84 -> 7526.3158 | T84: =$N84*MAX(0,(MIN($G84,DATE(2026,10,31))-MAX($E84,DATE(2026,10,1))+1))/$O84 -> 6522.807 | U84: =$N84*MAX(0,(MIN($G84,DATE(2026,11,30))-MAX($E84,DATE(2026,11,1))+1))/$O84 -> 0 | V84: =$N84*MAX(0,(MIN($G84,DATE(2026,12,31))-MAX($E84,DATE(2026,12,1))+1))/$O84 -> 0 | W84: =$H84*MAX(0,(MIN($G84,DATE(2026,7,31))-MAX($E84,DATE(2026,7,1))+1))/30.4 -> 0 | X84: =$H84*MAX(0,(MIN($G84,DATE(2026,8,31))-MAX($E84,DATE(2026,8,1))+1))/30.4 -> 0.016447368 | Y84: =$H84*MAX(0,(MIN($G84,DATE(2026,9,30))-MAX($E84,DATE(2026,9,1))+1))/30.4 -> 0.49342105 | Z84: =$H84*MAX(0,(MIN($G84,DATE(2026,10,31))-MAX($E84,DATE(2026,10,1))+1))/30.4 -> 0.42763158 | AA84: =$H84*MAX(0,(MIN($G84,DATE(2026,11,30))-MAX($E84,DATE(2026,11,1))+1))/30.4 -> 0 | AB84: =$H84*MAX(0,(MIN($G84,DATE(2026,12,31))-MAX($E84,DATE(2026,12,1))+1))/30.4 -> 0
A85: 35 | B85: 5 | D85: Enabler | E85: 46265 | F85: 5 | G85: 46300 | H85: 1 | I85: Not Resourced | J85: =IFERROR(VLOOKUP(D85,Role_Mapping!$A$5:$D$31,2,FALSE()),"UNMAPPED") -> Solutions Enabler | K85: =IFERROR(VLOOKUP(D85,Role_Mapping!$A$5:$D$31,3,FALSE()),"IN") -> IN | L85: =IFERROR(SUMPRODUCT((Rate_Card!$A$5:$A$34=J85)*(Rate_Card!$B$5:$B$34=K85)*Rate_Card!$C$5:$C$34),0) -> 683 | M85: =F85*5 -> 25 | N85: =L85*M85*H85 -> 17075 | O85: =(G85-E85)+1 -> 36 | P85: =IFERROR(VLOOKUP(D85,Role_Mapping!$A$5:$D$31,4,FALSE()),"UNMAPPED") -> Data Engineering | Q85: =$N85*MAX(0,(MIN($G85,DATE(2026,7,31))-MAX($E85,DATE(2026,7,1))+1))/$O85 -> 0 | R85: =$N85*MAX(0,(MIN($G85,DATE(2026,8,31))-MAX($E85,DATE(2026,8,1))+1))/$O85 -> 474.30556 | S85: =$N85*MAX(0,(MIN($G85,DATE(2026,9,30))-MAX($E85,DATE(2026,9,1))+1))/$O85 -> 14229.167 | T85: =$N85*MAX(0,(MIN($G85,DATE(2026,10,31))-MAX($E85,DATE(2026,10,1))+1))/$O85 -> 2371.5278 | U85: =$N85*MAX(0,(MIN($G85,DATE(2026,11,30))-MAX($E85,DATE(2026,11,1))+1))/$O85 -> 0 | V85: =$N85*MAX(0,(MIN($G85,DATE(2026,12,31))-MAX($E85,DATE(2026,12,1))+1))/$O85 -> 0 | W85: =$H85*MAX(0,(MIN($G85,DATE(2026,7,31))-MAX($E85,DATE(2026,7,1))+1))/30.4 -> 0 | X85: =$H85*MAX(0,(MIN($G85,DATE(2026,8,31))-MAX($E85,DATE(2026,8,1))+1))/30.4 -> 0.032894737 | Y85: =$H85*MAX(0,(MIN($G85,DATE(2026,9,30))-MAX($E85,DATE(2026,9,1))+1))/30.4 -> 0.98684211 | Z85: =$H85*MAX(0,(MIN($G85,DATE(2026,10,31))-MAX($E85,DATE(2026,10,1))+1))/30.4 -> 0.16447368 | AA85: =$H85*MAX(0,(MIN($G85,DATE(2026,11,30))-MAX($E85,DATE(2026,11,1))+1))/30.4 -> 0 | AB85: =$H85*MAX(0,(MIN($G85,DATE(2026,12,31))-MAX($E85,DATE(2026,12,1))+1))/30.4 -> 0
A86: 36 | B86: 5 | D86: SSE | E86: 46265 | F86: 5 | G86: 46300 | H86: 1 | I86: Not Resourced | J86: =IFERROR(VLOOKUP(D86,Role_Mapping!$A$5:$D$31,2,FALSE()),"UNMAPPED") -> Senior Software Engineer | K86: =IFERROR(VLOOKUP(D86,Role_Mapping!$A$5:$D$31,3,FALSE()),"IN") -> IN | L86: =IFERROR(SUMPRODUCT((Rate_Card!$A$5:$A$34=J86)*(Rate_Card!$B$5:$B$34=K86)*Rate_Card!$C$5:$C$34),0) -> 585 | M86: =F86*5 -> 25 | N86: =L86*M86*H86 -> 14625 | O86: =(G86-E86)+1 -> 36 | P86: =IFERROR(VLOOKUP(D86,Role_Mapping!$A$5:$D$31,4,FALSE()),"UNMAPPED") -> Full Stack | Q86: =$N86*MAX(0,(MIN($G86,DATE(2026,7,31))-MAX($E86,DATE(2026,7,1))+1))/$O86 -> 0 | R86: =$N86*MAX(0,(MIN($G86,DATE(2026,8,31))-MAX($E86,DATE(2026,8,1))+1))/$O86 -> 406.25 | S86: =$N86*MAX(0,(MIN($G86,DATE(2026,9,30))-MAX($E86,DATE(2026,9,1))+1))/$O86 -> 12187.5 | T86: =$N86*MAX(0,(MIN($G86,DATE(2026,10,31))-MAX($E86,DATE(2026,10,1))+1))/$O86 -> 2031.25 | U86: =$N86*MAX(0,(MIN($G86,DATE(2026,11,30))-MAX($E86,DATE(2026,11,1))+1))/$O86 -> 0 | V86: =$N86*MAX(0,(MIN($G86,DATE(2026,12,31))-MAX($E86,DATE(2026,12,1))+1))/$O86 -> 0 | W86: =$H86*MAX(0,(MIN($G86,DATE(2026,7,31))-MAX($E86,DATE(2026,7,1))+1))/30.4 -> 0 | X86: =$H86*MAX(0,(MIN($G86,DATE(2026,8,31))-MAX($E86,DATE(2026,8,1))+1))/30.4 -> 0.032894737 | Y86: =$H86*MAX(0,(MIN($G86,DATE(2026,9,30))-MAX($E86,DATE(2026,9,1))+1))/30.4 -> 0.98684211 | Z86: =$H86*MAX(0,(MIN($G86,DATE(2026,10,31))-MAX($E86,DATE(2026,10,1))+1))/30.4 -> 0.16447368 | AA86: =$H86*MAX(0,(MIN($G86,DATE(2026,11,30))-MAX($E86,DATE(2026,11,1))+1))/30.4 -> 0 | AB86: =$H86*MAX(0,(MIN($G86,DATE(2026,12,31))-MAX($E86,DATE(2026,12,1))+1))/30.4 -> 0
A87: 37 | B87: 3 | C87: BMW | D87: P | E87: 46209 | F87: 4 | G87: 46237 | H87: 0.125 | I87: Not Resourced | J87: =IFERROR(VLOOKUP(D87,Role_Mapping!$A$5:$D$31,2,FALSE()),"UNMAPPED") -> Associate Partner | K87: =IFERROR(VLOOKUP(D87,Role_Mapping!$A$5:$D$31,3,FALSE()),"IN") -> UK | L87: =IFERROR(SUMPRODUCT((Rate_Card!$A$5:$A$34=J87)*(Rate_Card!$B$5:$B$34=K87)*Rate_Card!$C$5:$C$34),0) -> 3526 | M87: =F87*5 -> 20 | N87: =L87*M87*H87 -> 8815 | O87: =(G87-E87)+1 -> 29 | P87: =IFERROR(VLOOKUP(D87,Role_Mapping!$A$5:$D$31,4,FALSE()),"UNMAPPED") -> GTM | Q87: =$N87*MAX(0,(MIN($G87,DATE(2026,7,31))-MAX($E87,DATE(2026,7,1))+1))/$O87 -> 7903.1034 | R87: =$N87*MAX(0,(MIN($G87,DATE(2026,8,31))-MAX($E87,DATE(2026,8,1))+1))/$O87 -> 911.89655 | S87: =$N87*MAX(0,(MIN($G87,DATE(2026,9,30))-MAX($E87,DATE(2026,9,1))+1))/$O87 -> 0 | T87: =$N87*MAX(0,(MIN($G87,DATE(2026,10,31))-MAX($E87,DATE(2026,10,1))+1))/$O87 -> 0 | U87: =$N87*MAX(0,(MIN($G87,DATE(2026,11,30))-MAX($E87,DATE(2026,11,1))+1))/$O87 -> 0 | V87: =$N87*MAX(0,(MIN($G87,DATE(2026,12,31))-MAX($E87,DATE(2026,12,1))+1))/$O87 -> 0 | W87: =$H87*MAX(0,(MIN($G87,DATE(2026,7,31))-MAX($E87,DATE(2026,7,1))+1))/30.4 -> 0.10690789 | X87: =$H87*MAX(0,(MIN($G87,DATE(2026,8,31))-MAX($E87,DATE(2026,8,1))+1))/30.4 -> 0.012335526 | Y87: =$H87*MAX(0,(MIN($G87,DATE(2026,9,30))-MAX($E87,DATE(2026,9,1))+1))/30.4 -> 0 | Z87: =$H87*MAX(0,(MIN($G87,DATE(2026,10,31))-MAX($E87,DATE(2026,10,1))+1))/30.4 -> 0 | AA87: =$H87*MAX(0,(MIN($G87,DATE(2026,11,30))-MAX($E87,DATE(2026,11,1))+1))/30.4 -> 0 | AB87: =$H87*MAX(0,(MIN($G87,DATE(2026,12,31))-MAX($E87,DATE(2026,12,1))+1))/30.4 -> 0
A88: 38 | B88: 3 | D88: SC | E88: 46209 | F88: 5 | G88: 46244 | H88: 0.5 | I88: Not Resourced | J88: =IFERROR(VLOOKUP(D88,Role_Mapping!$A$5:$D$31,2,FALSE()),"UNMAPPED") -> Senior Consultant | K88: =IFERROR(VLOOKUP(D88,Role_Mapping!$A$5:$D$31,3,FALSE()),"IN") -> UK | L88: =IFERROR(SUMPRODUCT((Rate_Card!$A$5:$A$34=J88)*(Rate_Card!$B$5:$B$34=K88)*Rate_Card!$C$5:$C$34),0) -> 2798 | M88: =F88*5 -> 25 | N88: =L88*M88*H88 -> 34975 | O88: =(G88-E88)+1 -> 36 | P88: =IFERROR(VLOOKUP(D88,Role_Mapping!$A$5:$D$31,4,FALSE()),"UNMAPPED") -> Consulting | Q88: =$N88*MAX(0,(MIN($G88,DATE(2026,7,31))-MAX($E88,DATE(2026,7,1))+1))/$O88 -> 25259.722 | R88: =$N88*MAX(0,(MIN($G88,DATE(2026,8,31))-MAX($E88,DATE(2026,8,1))+1))/$O88 -> 9715.2778 | S88: =$N88*MAX(0,(MIN($G88,DATE(2026,9,30))-MAX($E88,DATE(2026,9,1))+1))/$O88 -> 0 | T88: =$N88*MAX(0,(MIN($G88,DATE(2026,10,31))-MAX($E88,DATE(2026,10,1))+1))/$O88 -> 0 | U88: =$N88*MAX(0,(MIN($G88,DATE(2026,11,30))-MAX($E88,DATE(2026,11,1))+1))/$O88 -> 0 | V88: =$N88*MAX(0,(MIN($G88,DATE(2026,12,31))-MAX($E88,DATE(2026,12,1))+1))/$O88 -> 0 | W88: =$H88*MAX(0,(MIN($G88,DATE(2026,7,31))-MAX($E88,DATE(2026,7,1))+1))/30.4 -> 0.42763158 | X88: =$H88*MAX(0,(MIN($G88,DATE(2026,8,31))-MAX($E88,DATE(2026,8,1))+1))/30.4 -> 0.16447368 | Y88: =$H88*MAX(0,(MIN($G88,DATE(2026,9,30))-MAX($E88,DATE(2026,9,1))+1))/30.4 -> 0 | Z88: =$H88*MAX(0,(MIN($G88,DATE(2026,10,31))-MAX($E88,DATE(2026,10,1))+1))/30.4 -> 0 | AA88: =$H88*MAX(0,(MIN($G88,DATE(2026,11,30))-MAX($E88,DATE(2026,11,1))+1))/30.4 -> 0 | AB88: =$H88*MAX(0,(MIN($G88,DATE(2026,12,31))-MAX($E88,DATE(2026,12,1))+1))/30.4 -> 0
A89: 39 | B89: 3 | D89: AC | E89: 46209 | F89: 5 | G89: 46244 | H89: 1 | I89: Not Resourced | J89: =IFERROR(VLOOKUP(D89,Role_Mapping!$A$5:$D$31,2,FALSE()),"UNMAPPED") -> Associate Consultant | K89: =IFERROR(VLOOKUP(D89,Role_Mapping!$A$5:$D$31,3,FALSE()),"IN") -> IN | L89: =IFERROR(SUMPRODUCT((Rate_Card!$A$5:$A$34=J89)*(Rate_Card!$B$5:$B$34=K89)*Rate_Card!$C$5:$C$34),0) -> 585 | M89: =F89*5 -> 25 | N89: =L89*M89*H89 -> 14625 | O89: =(G89-E89)+1 -> 36 | P89: =IFERROR(VLOOKUP(D89,Role_Mapping!$A$5:$D$31,4,FALSE()),"UNMAPPED") -> Consulting | Q89: =$N89*MAX(0,(MIN($G89,DATE(2026,7,31))-MAX($E89,DATE(2026,7,1))+1))/$O89 -> 10562.5 | R89: =$N89*MAX(0,(MIN($G89,DATE(2026,8,31))-MAX($E89,DATE(2026,8,1))+1))/$O89 -> 4062.5 | S89: =$N89*MAX(0,(MIN($G89,DATE(2026,9,30))-MAX($E89,DATE(2026,9,1))+1))/$O89 -> 0 | T89: =$N89*MAX(0,(MIN($G89,DATE(2026,10,31))-MAX($E89,DATE(2026,10,1))+1))/$O89 -> 0 | U89: =$N89*MAX(0,(MIN($G89,DATE(2026,11,30))-MAX($E89,DATE(2026,11,1))+1))/$O89 -> 0 | V89: =$N89*MAX(0,(MIN($G89,DATE(2026,12,31))-MAX($E89,DATE(2026,12,1))+1))/$O89 -> 0 | W89: =$H89*MAX(0,(MIN($G89,DATE(2026,7,31))-MAX($E89,DATE(2026,7,1))+1))/30.4 -> 0.85526316 | X89: =$H89*MAX(0,(MIN($G89,DATE(2026,8,31))-MAX($E89,DATE(2026,8,1))+1))/30.4 -> 0.32894737 | Y89: =$H89*MAX(0,(MIN($G89,DATE(2026,9,30))-MAX($E89,DATE(2026,9,1))+1))/30.4 -> 0 | Z89: =$H89*MAX(0,(MIN($G89,DATE(2026,10,31))-MAX($E89,DATE(2026,10,1))+1))/30.4 -> 0 | AA89: =$H89*MAX(0,(MIN($G89,DATE(2026,11,30))-MAX($E89,DATE(2026,11,1))+1))/30.4 -> 0 | AB89: =$H89*MAX(0,(MIN($G89,DATE(2026,12,31))-MAX($E89,DATE(2026,12,1))+1))/30.4 -> 0
A90: 40 | B90: 3 | D90: PA | E90: 46209 | F90: 5 | G90: 46244 | H90: 0.25 | I90: Not Resourced | J90: =IFERROR(VLOOKUP(D90,Role_Mapping!$A$5:$D$31,2,FALSE()),"UNMAPPED") -> Principal Technology Architect | K90: =IFERROR(VLOOKUP(D90,Role_Mapping!$A$5:$D$31,3,FALSE()),"IN") -> IN | L90: =IFERROR(SUMPRODUCT((Rate_Card!$A$5:$A$34=J90)*(Rate_Card!$B$5:$B$34=K90)*Rate_Card!$C$5:$C$34),0) -> 845 | M90: =F90*5 -> 25 | N90: =L90*M90*H90 -> 5281.25 | O90: =(G90-E90)+1 -> 36 | P90: =IFERROR(VLOOKUP(D90,Role_Mapping!$A$5:$D$31,4,FALSE()),"UNMAPPED") -> Full Stack | Q90: =$N90*MAX(0,(MIN($G90,DATE(2026,7,31))-MAX($E90,DATE(2026,7,1))+1))/$O90 -> 3814.2361 | R90: =$N90*MAX(0,(MIN($G90,DATE(2026,8,31))-MAX($E90,DATE(2026,8,1))+1))/$O90 -> 1467.0139 | S90: =$N90*MAX(0,(MIN($G90,DATE(2026,9,30))-MAX($E90,DATE(2026,9,1))+1))/$O90 -> 0 | T90: =$N90*MAX(0,(MIN($G90,DATE(2026,10,31))-MAX($E90,DATE(2026,10,1))+1))/$O90 -> 0 | U90: =$N90*MAX(0,(MIN($G90,DATE(2026,11,30))-MAX($E90,DATE(2026,11,1))+1))/$O90 -> 0 | V90: =$N90*MAX(0,(MIN($G90,DATE(2026,12,31))-MAX($E90,DATE(2026,12,1))+1))/$O90 -> 0 | W90: =$H90*MAX(0,(MIN($G90,DATE(2026,7,31))-MAX($E90,DATE(2026,7,1))+1))/30.4 -> 0.21381579 | X90: =$H90*MAX(0,(MIN($G90,DATE(2026,8,31))-MAX($E90,DATE(2026,8,1))+1))/30.4 -> 0.082236842 | Y90: =$H90*MAX(0,(MIN($G90,DATE(2026,9,30))-MAX($E90,DATE(2026,9,1))+1))/30.4 -> 0 | Z90: =$H90*MAX(0,(MIN($G90,DATE(2026,10,31))-MAX($E90,DATE(2026,10,1))+1))/30.4 -> 0 | AA90: =$H90*MAX(0,(MIN($G90,DATE(2026,11,30))-MAX($E90,DATE(2026,11,1))+1))/30.4 -> 0 | AB90: =$H90*MAX(0,(MIN($G90,DATE(2026,12,31))-MAX($E90,DATE(2026,12,1))+1))/30.4 -> 0
A91: 41 | B91: 3 | D91: Sol Con | E91: 46209 | F91: 5 | G91: 46244 | H91: 1 | I91: Not Resourced | J91: =IFERROR(VLOOKUP(D91,Role_Mapping!$A$5:$D$31,2,FALSE()),"UNMAPPED") -> Solutions Consultant | K91: =IFERROR(VLOOKUP(D91,Role_Mapping!$A$5:$D$31,3,FALSE()),"IN") -> IN | L91: =IFERROR(SUMPRODUCT((Rate_Card!$A$5:$A$34=J91)*(Rate_Card!$B$5:$B$34=K91)*Rate_Card!$C$5:$C$34),0) -> 683 | M91: =F91*5 -> 25 | N91: =L91*M91*H91 -> 17075 | O91: =(G91-E91)+1 -> 36 | P91: =IFERROR(VLOOKUP(D91,Role_Mapping!$A$5:$D$31,4,FALSE()),"UNMAPPED") -> Power BI & Consulting | Q91: =$N91*MAX(0,(MIN($G91,DATE(2026,7,31))-MAX($E91,DATE(2026,7,1))+1))/$O91 -> 12331.944 | R91: =$N91*MAX(0,(MIN($G91,DATE(2026,8,31))-MAX($E91,DATE(2026,8,1))+1))/$O91 -> 4743.0556 | S91: =$N91*MAX(0,(MIN($G91,DATE(2026,9,30))-MAX($E91,DATE(2026,9,1))+1))/$O91 -> 0 | T91: =$N91*MAX(0,(MIN($G91,DATE(2026,10,31))-MAX($E91,DATE(2026,10,1))+1))/$O91 -> 0 | U91: =$N91*MAX(0,(MIN($G91,DATE(2026,11,30))-MAX($E91,DATE(2026,11,1))+1))/$O91 -> 0 | V91: =$N91*MAX(0,(MIN($G91,DATE(2026,12,31))-MAX($E91,DATE(2026,12,1))+1))/$O91 -> 0 | W91: =$H91*MAX(0,(MIN($G91,DATE(2026,7,31))-MAX($E91,DATE(2026,7,1))+1))/30.4 -> 0.85526316 | X91: =$H91*MAX(0,(MIN($G91,DATE(2026,8,31))-MAX($E91,DATE(2026,8,1))+1))/30.4 -> 0.32894737 | Y91: =$H91*MAX(0,(MIN($G91,DATE(2026,9,30))-MAX($E91,DATE(2026,9,1))+1))/30.4 -> 0 | Z91: =$H91*MAX(0,(MIN($G91,DATE(2026,10,31))-MAX($E91,DATE(2026,10,1))+1))/30.4 -> 0 | AA91: =$H91*MAX(0,(MIN($G91,DATE(2026,11,30))-MAX($E91,DATE(2026,11,1))+1))/30.4 -> 0 | AB91: =$H91*MAX(0,(MIN($G91,DATE(2026,12,31))-MAX($E91,DATE(2026,12,1))+1))/30.4 -> 0
A92: 42 | B92: 3 | D92: SSE | E92: 46209 | F92: 5 | G92: 46244 | H92: 1 | I92: Not Resourced | J92: =IFERROR(VLOOKUP(D92,Role_Mapping!$A$5:$D$31,2,FALSE()),"UNMAPPED") -> Senior Software Engineer | K92: =IFERROR(VLOOKUP(D92,Role_Mapping!$A$5:$D$31,3,FALSE()),"IN") -> IN | L92: =IFERROR(SUMPRODUCT((Rate_Card!$A$5:$A$34=J92)*(Rate_Card!$B$5:$B$34=K92)*Rate_Card!$C$5:$C$34),0) -> 585 | M92: =F92*5 -> 25 | N92: =L92*M92*H92 -> 14625 | O92: =(G92-E92)+1 -> 36 | P92: =IFERROR(VLOOKUP(D92,Role_Mapping!$A$5:$D$31,4,FALSE()),"UNMAPPED") -> Full Stack | Q92: =$N92*MAX(0,(MIN($G92,DATE(2026,7,31))-MAX($E92,DATE(2026,7,1))+1))/$O92 -> 10562.5 | R92: =$N92*MAX(0,(MIN($G92,DATE(2026,8,31))-MAX($E92,DATE(2026,8,1))+1))/$O92 -> 4062.5 | S92: =$N92*MAX(0,(MIN($G92,DATE(2026,9,30))-MAX($E92,DATE(2026,9,1))+1))/$O92 -> 0 | T92: =$N92*MAX(0,(MIN($G92,DATE(2026,10,31))-MAX($E92,DATE(2026,10,1))+1))/$O92 -> 0 | U92: =$N92*MAX(0,(MIN($G92,DATE(2026,11,30))-MAX($E92,DATE(2026,11,1))+1))/$O92 -> 0 | V92: =$N92*MAX(0,(MIN($G92,DATE(2026,12,31))-MAX($E92,DATE(2026,12,1))+1))/$O92 -> 0 | W92: =$H92*MAX(0,(MIN($G92,DATE(2026,7,31))-MAX($E92,DATE(2026,7,1))+1))/30.4 -> 0.85526316 | X92: =$H92*MAX(0,(MIN($G92,DATE(2026,8,31))-MAX($E92,DATE(2026,8,1))+1))/30.4 -> 0.32894737 | Y92: =$H92*MAX(0,(MIN($G92,DATE(2026,9,30))-MAX($E92,DATE(2026,9,1))+1))/30.4 -> 0 | Z92: =$H92*MAX(0,(MIN($G92,DATE(2026,10,31))-MAX($E92,DATE(2026,10,1))+1))/30.4 -> 0 | AA92: =$H92*MAX(0,(MIN($G92,DATE(2026,11,30))-MAX($E92,DATE(2026,11,1))+1))/30.4 -> 0 | AB92: =$H92*MAX(0,(MIN($G92,DATE(2026,12,31))-MAX($E92,DATE(2026,12,1))+1))/30.4 -> 0
A93: 43 | B93: 3 | D93: SSE | E93: 46209 | F93: 5 | G93: 46244 | H93: 1 | I93: Not Resourced | J93: =IFERROR(VLOOKUP(D93,Role_Mapping!$A$5:$D$31,2,FALSE()),"UNMAPPED") -> Senior Software Engineer | K93: =IFERROR(VLOOKUP(D93,Role_Mapping!$A$5:$D$31,3,FALSE()),"IN") -> IN | L93: =IFERROR(SUMPRODUCT((Rate_Card!$A$5:$A$34=J93)*(Rate_Card!$B$5:$B$34=K93)*Rate_Card!$C$5:$C$34),0) -> 585 | M93: =F93*5 -> 25 | N93: =L93*M93*H93 -> 14625 | O93: =(G93-E93)+1 -> 36 | P93: =IFERROR(VLOOKUP(D93,Role_Mapping!$A$5:$D$31,4,FALSE()),"UNMAPPED") -> Full Stack | Q93: =$N93*MAX(0,(MIN($G93,DATE(2026,7,31))-MAX($E93,DATE(2026,7,1))+1))/$O93 -> 10562.5 | R93: =$N93*MAX(0,(MIN($G93,DATE(2026,8,31))-MAX($E93,DATE(2026,8,1))+1))/$O93 -> 4062.5 | S93: =$N93*MAX(0,(MIN($G93,DATE(2026,9,30))-MAX($E93,DATE(2026,9,1))+1))/$O93 -> 0 | T93: =$N93*MAX(0,(MIN($G93,DATE(2026,10,31))-MAX($E93,DATE(2026,10,1))+1))/$O93 -> 0 | U93: =$N93*MAX(0,(MIN($G93,DATE(2026,11,30))-MAX($E93,DATE(2026,11,1))+1))/$O93 -> 0 | V93: =$N93*MAX(0,(MIN($G93,DATE(2026,12,31))-MAX($E93,DATE(2026,12,1))+1))/$O93 -> 0 | W93: =$H93*MAX(0,(MIN($G93,DATE(2026,7,31))-MAX($E93,DATE(2026,7,1))+1))/30.4 -> 0.85526316 | X93: =$H93*MAX(0,(MIN($G93,DATE(2026,8,31))-MAX($E93,DATE(2026,8,1))+1))/30.4 -> 0.32894737 | Y93: =$H93*MAX(0,(MIN($G93,DATE(2026,9,30))-MAX($E93,DATE(2026,9,1))+1))/30.4 -> 0 | Z93: =$H93*MAX(0,(MIN($G93,DATE(2026,10,31))-MAX($E93,DATE(2026,10,1))+1))/30.4 -> 0 | AA93: =$H93*MAX(0,(MIN($G93,DATE(2026,11,30))-MAX($E93,DATE(2026,11,1))+1))/30.4 -> 0 | AB93: =$H93*MAX(0,(MIN($G93,DATE(2026,12,31))-MAX($E93,DATE(2026,12,1))+1))/30.4 -> 0
A94: 44 | B94: 3 | C94: Triumph | D94: SC | E94: 46195 | F94: 2 | G94: 46209 | H94: 0.125 | I94: Resourced | J94: =IFERROR(VLOOKUP(D94,Role_Mapping!$A$5:$D$31,2,FALSE()),"UNMAPPED") -> Senior Consultant | K94: =IFERROR(VLOOKUP(D94,Role_Mapping!$A$5:$D$31,3,FALSE()),"IN") -> UK | L94: =IFERROR(SUMPRODUCT((Rate_Card!$A$5:$A$34=J94)*(Rate_Card!$B$5:$B$34=K94)*Rate_Card!$C$5:$C$34),0) -> 2798 | M94: =F94*5 -> 10 | N94: =L94*M94*H94 -> 3497.5 | O94: =(G94-E94)+1 -> 15 | P94: =IFERROR(VLOOKUP(D94,Role_Mapping!$A$5:$D$31,4,FALSE()),"UNMAPPED") -> Consulting | Q94: =$N94*MAX(0,(MIN($G94,DATE(2026,7,31))-MAX($E94,DATE(2026,7,1))+1))/$O94 -> 1399 | R94: =$N94*MAX(0,(MIN($G94,DATE(2026,8,31))-MAX($E94,DATE(2026,8,1))+1))/$O94 -> 0 | S94: =$N94*MAX(0,(MIN($G94,DATE(2026,9,30))-MAX($E94,DATE(2026,9,1))+1))/$O94 -> 0 | T94: =$N94*MAX(0,(MIN($G94,DATE(2026,10,31))-MAX($E94,DATE(2026,10,1))+1))/$O94 -> 0 | U94: =$N94*MAX(0,(MIN($G94,DATE(2026,11,30))-MAX($E94,DATE(2026,11,1))+1))/$O94 -> 0 | V94: =$N94*MAX(0,(MIN($G94,DATE(2026,12,31))-MAX($E94,DATE(2026,12,1))+1))/$O94 -> 0 | W94: =$H94*MAX(0,(MIN($G94,DATE(2026,7,31))-MAX($E94,DATE(2026,7,1))+1))/30.4 -> 0.024671053 | X94: =$H94*MAX(0,(MIN($G94,DATE(2026,8,31))-MAX($E94,DATE(2026,8,1))+1))/30.4 -> 0 | Y94: =$H94*MAX(0,(MIN($G94,DATE(2026,9,30))-MAX($E94,DATE(2026,9,1))+1))/30.4 -> 0 | Z94: =$H94*MAX(0,(MIN($G94,DATE(2026,10,31))-MAX($E94,DATE(2026,10,1))+1))/30.4 -> 0 | AA94: =$H94*MAX(0,(MIN($G94,DATE(2026,11,30))-MAX($E94,DATE(2026,11,1))+1))/30.4 -> 0 | AB94: =$H94*MAX(0,(MIN($G94,DATE(2026,12,31))-MAX($E94,DATE(2026,12,1))+1))/30.4 -> 0
A95: 45 | B95: 3 | D95: SSE | E95: 46195 | F95: 5 | G95: 46230 | H95: 1 | I95: Not Resourced | J95: =IFERROR(VLOOKUP(D95,Role_Mapping!$A$5:$D$31,2,FALSE()),"UNMAPPED") -> Senior Software Engineer | K95: =IFERROR(VLOOKUP(D95,Role_Mapping!$A$5:$D$31,3,FALSE()),"IN") -> IN | L95: =IFERROR(SUMPRODUCT((Rate_Card!$A$5:$A$34=J95)*(Rate_Card!$B$5:$B$34=K95)*Rate_Card!$C$5:$C$34),0) -> 585 | M95: =F95*5 -> 25 | N95: =L95*M95*H95 -> 14625 | O95: =(G95-E95)+1 -> 36 | P95: =IFERROR(VLOOKUP(D95,Role_Mapping!$A$5:$D$31,4,FALSE()),"UNMAPPED") -> Full Stack | Q95: =$N95*MAX(0,(MIN($G95,DATE(2026,7,31))-MAX($E95,DATE(2026,7,1))+1))/$O95 -> 10968.75 | R95: =$N95*MAX(0,(MIN($G95,DATE(2026,8,31))-MAX($E95,DATE(2026,8,1))+1))/$O95 -> 0 | S95: =$N95*MAX(0,(MIN($G95,DATE(2026,9,30))-MAX($E95,DATE(2026,9,1))+1))/$O95 -> 0 | T95: =$N95*MAX(0,(MIN($G95,DATE(2026,10,31))-MAX($E95,DATE(2026,10,1))+1))/$O95 -> 0 | U95: =$N95*MAX(0,(MIN($G95,DATE(2026,11,30))-MAX($E95,DATE(2026,11,1))+1))/$O95 -> 0 | V95: =$N95*MAX(0,(MIN($G95,DATE(2026,12,31))-MAX($E95,DATE(2026,12,1))+1))/$O95 -> 0 | W95: =$H95*MAX(0,(MIN($G95,DATE(2026,7,31))-MAX($E95,DATE(2026,7,1))+1))/30.4 -> 0.88815789 | X95: =$H95*MAX(0,(MIN($G95,DATE(2026,8,31))-MAX($E95,DATE(2026,8,1))+1))/30.4 -> 0 | Y95: =$H95*MAX(0,(MIN($G95,DATE(2026,9,30))-MAX($E95,DATE(2026,9,1))+1))/30.4 -> 0 | Z95: =$H95*MAX(0,(MIN($G95,DATE(2026,10,31))-MAX($E95,DATE(2026,10,1))+1))/30.4 -> 0 | AA95: =$H95*MAX(0,(MIN($G95,DATE(2026,11,30))-MAX($E95,DATE(2026,11,1))+1))/30.4 -> 0 | AB95: =$H95*MAX(0,(MIN($G95,DATE(2026,12,31))-MAX($E95,DATE(2026,12,1))+1))/30.4 -> 0
A96: 46 | B96: 3 | D96: SSE | E96: 46195 | F96: 5 | G96: 46230 | H96: 1 | I96: Not Resourced | J96: =IFERROR(VLOOKUP(D96,Role_Mapping!$A$5:$D$31,2,FALSE()),"UNMAPPED") -> Senior Software Engineer | K96: =IFERROR(VLOOKUP(D96,Role_Mapping!$A$5:$D$31,3,FALSE()),"IN") -> IN | L96: =IFERROR(SUMPRODUCT((Rate_Card!$A$5:$A$34=J96)*(Rate_Card!$B$5:$B$34=K96)*Rate_Card!$C$5:$C$34),0) -> 585 | M96: =F96*5 -> 25 | N96: =L96*M96*H96 -> 14625 | O96: =(G96-E96)+1 -> 36 | P96: =IFERROR(VLOOKUP(D96,Role_Mapping!$A$5:$D$31,4,FALSE()),"UNMAPPED") -> Full Stack | Q96: =$N96*MAX(0,(MIN($G96,DATE(2026,7,31))-MAX($E96,DATE(2026,7,1))+1))/$O96 -> 10968.75 | R96: =$N96*MAX(0,(MIN($G96,DATE(2026,8,31))-MAX($E96,DATE(2026,8,1))+1))/$O96 -> 0 | S96: =$N96*MAX(0,(MIN($G96,DATE(2026,9,30))-MAX($E96,DATE(2026,9,1))+1))/$O96 -> 0 | T96: =$N96*MAX(0,(MIN($G96,DATE(2026,10,31))-MAX($E96,DATE(2026,10,1))+1))/$O96 -> 0 | U96: =$N96*MAX(0,(MIN($G96,DATE(2026,11,30))-MAX($E96,DATE(2026,11,1))+1))/$O96 -> 0 | V96: =$N96*MAX(0,(MIN($G96,DATE(2026,12,31))-MAX($E96,DATE(2026,12,1))+1))/$O96 -> 0 | W96: =$H96*MAX(0,(MIN($G96,DATE(2026,7,31))-MAX($E96,DATE(2026,7,1))+1))/30.4 -> 0.88815789 | X96: =$H96*MAX(0,(MIN($G96,DATE(2026,8,31))-MAX($E96,DATE(2026,8,1))+1))/30.4 -> 0 | Y96: =$H96*MAX(0,(MIN($G96,DATE(2026,9,30))-MAX($E96,DATE(2026,9,1))+1))/30.4 -> 0 | Z96: =$H96*MAX(0,(MIN($G96,DATE(2026,10,31))-MAX($E96,DATE(2026,10,1))+1))/30.4 -> 0 | AA96: =$H96*MAX(0,(MIN($G96,DATE(2026,11,30))-MAX($E96,DATE(2026,11,1))+1))/30.4 -> 0 | AB96: =$H96*MAX(0,(MIN($G96,DATE(2026,12,31))-MAX($E96,DATE(2026,12,1))+1))/30.4 -> 0
A97: 47 | B97: 3 | D97: SE | E97: 46195 | F97: 5 | G97: 46230 | H97: 1 | I97: Not Resourced | J97: =IFERROR(VLOOKUP(D97,Role_Mapping!$A$5:$D$31,2,FALSE()),"UNMAPPED") -> Software Engineer | K97: =IFERROR(VLOOKUP(D97,Role_Mapping!$A$5:$D$31,3,FALSE()),"IN") -> IN | L97: =IFERROR(SUMPRODUCT((Rate_Card!$A$5:$A$34=J97)*(Rate_Card!$B$5:$B$34=K97)*Rate_Card!$C$5:$C$34),0) -> 455 | M97: =F97*5 -> 25 | N97: =L97*M97*H97 -> 11375 | O97: =(G97-E97)+1 -> 36 | P97: =IFERROR(VLOOKUP(D97,Role_Mapping!$A$5:$D$31,4,FALSE()),"UNMAPPED") -> Full Stack | Q97: =$N97*MAX(0,(MIN($G97,DATE(2026,7,31))-MAX($E97,DATE(2026,7,1))+1))/$O97 -> 8531.25 | R97: =$N97*MAX(0,(MIN($G97,DATE(2026,8,31))-MAX($E97,DATE(2026,8,1))+1))/$O97 -> 0 | S97: =$N97*MAX(0,(MIN($G97,DATE(2026,9,30))-MAX($E97,DATE(2026,9,1))+1))/$O97 -> 0 | T97: =$N97*MAX(0,(MIN($G97,DATE(2026,10,31))-MAX($E97,DATE(2026,10,1))+1))/$O97 -> 0 | U97: =$N97*MAX(0,(MIN($G97,DATE(2026,11,30))-MAX($E97,DATE(2026,11,1))+1))/$O97 -> 0 | V97: =$N97*MAX(0,(MIN($G97,DATE(2026,12,31))-MAX($E97,DATE(2026,12,1))+1))/$O97 -> 0 | W97: =$H97*MAX(0,(MIN($G97,DATE(2026,7,31))-MAX($E97,DATE(2026,7,1))+1))/30.4 -> 0.88815789 | X97: =$H97*MAX(0,(MIN($G97,DATE(2026,8,31))-MAX($E97,DATE(2026,8,1))+1))/30.4 -> 0 | Y97: =$H97*MAX(0,(MIN($G97,DATE(2026,9,30))-MAX($E97,DATE(2026,9,1))+1))/30.4 -> 0 | Z97: =$H97*MAX(0,(MIN($G97,DATE(2026,10,31))-MAX($E97,DATE(2026,10,1))+1))/30.4 -> 0 | AA97: =$H97*MAX(0,(MIN($G97,DATE(2026,11,30))-MAX($E97,DATE(2026,11,1))+1))/30.4 -> 0 | AB97: =$H97*MAX(0,(MIN($G97,DATE(2026,12,31))-MAX($E97,DATE(2026,12,1))+1))/30.4 -> 0
A98: 48 | B98: 3 | D98: SE | E98: 46195 | F98: 5 | G98: 46230 | H98: 1 | I98: Not Resourced | J98: =IFERROR(VLOOKUP(D98,Role_Mapping!$A$5:$D$31,2,FALSE()),"UNMAPPED") -> Software Engineer | K98: =IFERROR(VLOOKUP(D98,Role_Mapping!$A$5:$D$31,3,FALSE()),"IN") -> IN | L98: =IFERROR(SUMPRODUCT((Rate_Card!$A$5:$A$34=J98)*(Rate_Card!$B$5:$B$34=K98)*Rate_Card!$C$5:$C$34),0) -> 455 | M98: =F98*5 -> 25 | N98: =L98*M98*H98 -> 11375 | O98: =(G98-E98)+1 -> 36 | P98: =IFERROR(VLOOKUP(D98,Role_Mapping!$A$5:$D$31,4,FALSE()),"UNMAPPED") -> Full Stack | Q98: =$N98*MAX(0,(MIN($G98,DATE(2026,7,31))-MAX($E98,DATE(2026,7,1))+1))/$O98 -> 8531.25 | R98: =$N98*MAX(0,(MIN($G98,DATE(2026,8,31))-MAX($E98,DATE(2026,8,1))+1))/$O98 -> 0 | S98: =$N98*MAX(0,(MIN($G98,DATE(2026,9,30))-MAX($E98,DATE(2026,9,1))+1))/$O98 -> 0 | T98: =$N98*MAX(0,(MIN($G98,DATE(2026,10,31))-MAX($E98,DATE(2026,10,1))+1))/$O98 -> 0 | U98: =$N98*MAX(0,(MIN($G98,DATE(2026,11,30))-MAX($E98,DATE(2026,11,1))+1))/$O98 -> 0 | V98: =$N98*MAX(0,(MIN($G98,DATE(2026,12,31))-MAX($E98,DATE(2026,12,1))+1))/$O98 -> 0 | W98: =$H98*MAX(0,(MIN($G98,DATE(2026,7,31))-MAX($E98,DATE(2026,7,1))+1))/30.4 -> 0.88815789 | X98: =$H98*MAX(0,(MIN($G98,DATE(2026,8,31))-MAX($E98,DATE(2026,8,1))+1))/30.4 -> 0 | Y98: =$H98*MAX(0,(MIN($G98,DATE(2026,9,30))-MAX($E98,DATE(2026,9,1))+1))/30.4 -> 0 | Z98: =$H98*MAX(0,(MIN($G98,DATE(2026,10,31))-MAX($E98,DATE(2026,10,1))+1))/30.4 -> 0 | AA98: =$H98*MAX(0,(MIN($G98,DATE(2026,11,30))-MAX($E98,DATE(2026,11,1))+1))/30.4 -> 0 | AB98: =$H98*MAX(0,(MIN($G98,DATE(2026,12,31))-MAX($E98,DATE(2026,12,1))+1))/30.4 -> 0
A99: 49 | B99: 3 | C99: Yamaha | D99: SC | E99: 46209 | F99: 9 | G99: 46272 | H99: 0.125 | I99: Resourced | J99: =IFERROR(VLOOKUP(D99,Role_Mapping!$A$5:$D$31,2,FALSE()),"UNMAPPED") -> Senior Consultant | K99: =IFERROR(VLOOKUP(D99,Role_Mapping!$A$5:$D$31,3,FALSE()),"IN") -> UK | L99: =IFERROR(SUMPRODUCT((Rate_Card!$A$5:$A$34=J99)*(Rate_Card!$B$5:$B$34=K99)*Rate_Card!$C$5:$C$34),0) -> 2798 | M99: =F99*5 -> 45 | N99: =L99*M99*H99 -> 15738.75 | O99: =(G99-E99)+1 -> 64 | P99: =IFERROR(VLOOKUP(D99,Role_Mapping!$A$5:$D$31,4,FALSE()),"UNMAPPED") -> Consulting | Q99: =$N99*MAX(0,(MIN($G99,DATE(2026,7,31))-MAX($E99,DATE(2026,7,1))+1))/$O99 -> 6393.8672 | R99: =$N99*MAX(0,(MIN($G99,DATE(2026,8,31))-MAX($E99,DATE(2026,8,1))+1))/$O99 -> 7623.457 | S99: =$N99*MAX(0,(MIN($G99,DATE(2026,9,30))-MAX($E99,DATE(2026,9,1))+1))/$O99 -> 1721.4258 | T99: =$N99*MAX(0,(MIN($G99,DATE(2026,10,31))-MAX($E99,DATE(2026,10,1))+1))/$O99 -> 0 | U99: =$N99*MAX(0,(MIN($G99,DATE(2026,11,30))-MAX($E99,DATE(2026,11,1))+1))/$O99 -> 0 | V99: =$N99*MAX(0,(MIN($G99,DATE(2026,12,31))-MAX($E99,DATE(2026,12,1))+1))/$O99 -> 0 | W99: =$H99*MAX(0,(MIN($G99,DATE(2026,7,31))-MAX($E99,DATE(2026,7,1))+1))/30.4 -> 0.10690789 | X99: =$H99*MAX(0,(MIN($G99,DATE(2026,8,31))-MAX($E99,DATE(2026,8,1))+1))/30.4 -> 0.12746711 | Y99: =$H99*MAX(0,(MIN($G99,DATE(2026,9,30))-MAX($E99,DATE(2026,9,1))+1))/30.4 -> 0.028782895 | Z99: =$H99*MAX(0,(MIN($G99,DATE(2026,10,31))-MAX($E99,DATE(2026,10,1))+1))/30.4 -> 0 | AA99: =$H99*MAX(0,(MIN($G99,DATE(2026,11,30))-MAX($E99,DATE(2026,11,1))+1))/30.4 -> 0 | AB99: =$H99*MAX(0,(MIN($G99,DATE(2026,12,31))-MAX($E99,DATE(2026,12,1))+1))/30.4 -> 0
A100: 50 | B100: 3 | D100: C | E100: 46209 | F100: 5 | G100: 46244 | H100: 1 | I100: Not Resourced | J100: =IFERROR(VLOOKUP(D100,Role_Mapping!$A$5:$D$31,2,FALSE()),"UNMAPPED") -> Consultant | K100: =IFERROR(VLOOKUP(D100,Role_Mapping!$A$5:$D$31,3,FALSE()),"IN") -> IN | L100: =IFERROR(SUMPRODUCT((Rate_Card!$A$5:$A$34=J100)*(Rate_Card!$B$5:$B$34=K100)*Rate_Card!$C$5:$C$34),0) -> 683 | M100: =F100*5 -> 25 | N100: =L100*M100*H100 -> 17075 | O100: =(G100-E100)+1 -> 36 | P100: =IFERROR(VLOOKUP(D100,Role_Mapping!$A$5:$D$31,4,FALSE()),"UNMAPPED") -> Consulting | Q100: =$N100*MAX(0,(MIN($G100,DATE(2026,7,31))-MAX($E100,DATE(2026,7,1))+1))/$O100 -> 12331.944 | R100: =$N100*MAX(0,(MIN($G100,DATE(2026,8,31))-MAX($E100,DATE(2026,8,1))+1))/$O100 -> 4743.0556 | S100: =$N100*MAX(0,(MIN($G100,DATE(2026,9,30))-MAX($E100,DATE(2026,9,1))+1))/$O100 -> 0 | T100: =$N100*MAX(0,(MIN($G100,DATE(2026,10,31))-MAX($E100,DATE(2026,10,1))+1))/$O100 -> 0 | U100: =$N100*MAX(0,(MIN($G100,DATE(2026,11,30))-MAX($E100,DATE(2026,11,1))+1))/$O100 -> 0 | V100: =$N100*MAX(0,(MIN($G100,DATE(2026,12,31))-MAX($E100,DATE(2026,12,1))+1))/$O100 -> 0 | W100: =$H100*MAX(0,(MIN($G100,DATE(2026,7,31))-MAX($E100,DATE(2026,7,1))+1))/30.4 -> 0.85526316 | X100: =$H100*MAX(0,(MIN($G100,DATE(2026,8,31))-MAX($E100,DATE(2026,8,1))+1))/30.4 -> 0.32894737 | Y100: =$H100*MAX(0,(MIN($G100,DATE(2026,9,30))-MAX($E100,DATE(2026,9,1))+1))/30.4 -> 0 | Z100: =$H100*MAX(0,(MIN($G100,DATE(2026,10,31))-MAX($E100,DATE(2026,10,1))+1))/30.4 -> 0 | AA100: =$H100*MAX(0,(MIN($G100,DATE(2026,11,30))-MAX($E100,DATE(2026,11,1))+1))/30.4 -> 0 | AB100: =$H100*MAX(0,(MIN($G100,DATE(2026,12,31))-MAX($E100,DATE(2026,12,1))+1))/30.4 -> 0
A101: 51 | B101: 3 | D101: SE | E101: 46209 | F101: 5 | G101: 46244 | H101: 1 | I101: Not Resourced | J101: =IFERROR(VLOOKUP(D101,Role_Mapping!$A$5:$D$31,2,FALSE()),"UNMAPPED") -> Software Engineer | K101: =IFERROR(VLOOKUP(D101,Role_Mapping!$A$5:$D$31,3,FALSE()),"IN") -> IN | L101: =IFERROR(SUMPRODUCT((Rate_Card!$A$5:$A$34=J101)*(Rate_Card!$B$5:$B$34=K101)*Rate_Card!$C$5:$C$34),0) -> 455 | M101: =F101*5 -> 25 | N101: =L101*M101*H101 -> 11375 | O101: =(G101-E101)+1 -> 36 | P101: =IFERROR(VLOOKUP(D101,Role_Mapping!$A$5:$D$31,4,FALSE()),"UNMAPPED") -> Full Stack | Q101: =$N101*MAX(0,(MIN($G101,DATE(2026,7,31))-MAX($E101,DATE(2026,7,1))+1))/$O101 -> 8215.2778 | R101: =$N101*MAX(0,(MIN($G101,DATE(2026,8,31))-MAX($E101,DATE(2026,8,1))+1))/$O101 -> 3159.7222 | S101: =$N101*MAX(0,(MIN($G101,DATE(2026,9,30))-MAX($E101,DATE(2026,9,1))+1))/$O101 -> 0 | T101: =$N101*MAX(0,(MIN($G101,DATE(2026,10,31))-MAX($E101,DATE(2026,10,1))+1))/$O101 -> 0 | U101: =$N101*MAX(0,(MIN($G101,DATE(2026,11,30))-MAX($E101,DATE(2026,11,1))+1))/$O101 -> 0 | V101: =$N101*MAX(0,(MIN($G101,DATE(2026,12,31))-MAX($E101,DATE(2026,12,1))+1))/$O101 -> 0 | W101: =$H101*MAX(0,(MIN($G101,DATE(2026,7,31))-MAX($E101,DATE(2026,7,1))+1))/30.4 -> 0.85526316 | X101: =$H101*MAX(0,(MIN($G101,DATE(2026,8,31))-MAX($E101,DATE(2026,8,1))+1))/30.4 -> 0.32894737 | Y101: =$H101*MAX(0,(MIN($G101,DATE(2026,9,30))-MAX($E101,DATE(2026,9,1))+1))/30.4 -> 0 | Z101: =$H101*MAX(0,(MIN($G101,DATE(2026,10,31))-MAX($E101,DATE(2026,10,1))+1))/30.4 -> 0 | AA101: =$H101*MAX(0,(MIN($G101,DATE(2026,11,30))-MAX($E101,DATE(2026,11,1))+1))/30.4 -> 0 | AB101: =$H101*MAX(0,(MIN($G101,DATE(2026,12,31))-MAX($E101,DATE(2026,12,1))+1))/30.4 -> 0
A102: 52 | B102: 3 | D102: SSE | E102: 46209 | F102: 5 | G102: 46244 | H102: 1 | I102: Not Resourced | J102: =IFERROR(VLOOKUP(D102,Role_Mapping!$A$5:$D$31,2,FALSE()),"UNMAPPED") -> Senior Software Engineer | K102: =IFERROR(VLOOKUP(D102,Role_Mapping!$A$5:$D$31,3,FALSE()),"IN") -> IN | L102: =IFERROR(SUMPRODUCT((Rate_Card!$A$5:$A$34=J102)*(Rate_Card!$B$5:$B$34=K102)*Rate_Card!$C$5:$C$34),0) -> 585 | M102: =F102*5 -> 25 | N102: =L102*M102*H102 -> 14625 | O102: =(G102-E102)+1 -> 36 | P102: =IFERROR(VLOOKUP(D102,Role_Mapping!$A$5:$D$31,4,FALSE()),"UNMAPPED") -> Full Stack | Q102: =$N102*MAX(0,(MIN($G102,DATE(2026,7,31))-MAX($E102,DATE(2026,7,1))+1))/$O102 -> 10562.5 | R102: =$N102*MAX(0,(MIN($G102,DATE(2026,8,31))-MAX($E102,DATE(2026,8,1))+1))/$O102 -> 4062.5 | S102: =$N102*MAX(0,(MIN($G102,DATE(2026,9,30))-MAX($E102,DATE(2026,9,1))+1))/$O102 -> 0 | T102: =$N102*MAX(0,(MIN($G102,DATE(2026,10,31))-MAX($E102,DATE(2026,10,1))+1))/$O102 -> 0 | U102: =$N102*MAX(0,(MIN($G102,DATE(2026,11,30))-MAX($E102,DATE(2026,11,1))+1))/$O102 -> 0 | V102: =$N102*MAX(0,(MIN($G102,DATE(2026,12,31))-MAX($E102,DATE(2026,12,1))+1))/$O102 -> 0 | W102: =$H102*MAX(0,(MIN($G102,DATE(2026,7,31))-MAX($E102,DATE(2026,7,1))+1))/30.4 -> 0.85526316 | X102: =$H102*MAX(0,(MIN($G102,DATE(2026,8,31))-MAX($E102,DATE(2026,8,1))+1))/30.4 -> 0.32894737 | Y102: =$H102*MAX(0,(MIN($G102,DATE(2026,9,30))-MAX($E102,DATE(2026,9,1))+1))/30.4 -> 0 | Z102: =$H102*MAX(0,(MIN($G102,DATE(2026,10,31))-MAX($E102,DATE(2026,10,1))+1))/30.4 -> 0 | AA102: =$H102*MAX(0,(MIN($G102,DATE(2026,11,30))-MAX($E102,DATE(2026,11,1))+1))/30.4 -> 0 | AB102: =$H102*MAX(0,(MIN($G102,DATE(2026,12,31))-MAX($E102,DATE(2026,12,1))+1))/30.4 -> 0
A103: 53 | B103: 3 | D103: SSE | E103: 46209 | F103: 5 | G103: 46244 | H103: 1 | I103: Not Resourced | J103: =IFERROR(VLOOKUP(D103,Role_Mapping!$A$5:$D$31,2,FALSE()),"UNMAPPED") -> Senior Software Engineer | K103: =IFERROR(VLOOKUP(D103,Role_Mapping!$A$5:$D$31,3,FALSE()),"IN") -> IN | L103: =IFERROR(SUMPRODUCT((Rate_Card!$A$5:$A$34=J103)*(Rate_Card!$B$5:$B$34=K103)*Rate_Card!$C$5:$C$34),0) -> 585 | M103: =F103*5 -> 25 | N103: =L103*M103*H103 -> 14625 | O103: =(G103-E103)+1 -> 36 | P103: =IFERROR(VLOOKUP(D103,Role_Mapping!$A$5:$D$31,4,FALSE()),"UNMAPPED") -> Full Stack | Q103: =$N103*MAX(0,(MIN($G103,DATE(2026,7,31))-MAX($E103,DATE(2026,7,1))+1))/$O103 -> 10562.5 | R103: =$N103*MAX(0,(MIN($G103,DATE(2026,8,31))-MAX($E103,DATE(2026,8,1))+1))/$O103 -> 4062.5 | S103: =$N103*MAX(0,(MIN($G103,DATE(2026,9,30))-MAX($E103,DATE(2026,9,1))+1))/$O103 -> 0 | T103: =$N103*MAX(0,(MIN($G103,DATE(2026,10,31))-MAX($E103,DATE(2026,10,1))+1))/$O103 -> 0 | U103: =$N103*MAX(0,(MIN($G103,DATE(2026,11,30))-MAX($E103,DATE(2026,11,1))+1))/$O103 -> 0 | V103: =$N103*MAX(0,(MIN($G103,DATE(2026,12,31))-MAX($E103,DATE(2026,12,1))+1))/$O103 -> 0 | W103: =$H103*MAX(0,(MIN($G103,DATE(2026,7,31))-MAX($E103,DATE(2026,7,1))+1))/30.4 -> 0.85526316 | X103: =$H103*MAX(0,(MIN($G103,DATE(2026,8,31))-MAX($E103,DATE(2026,8,1))+1))/30.4 -> 0.32894737 | Y103: =$H103*MAX(0,(MIN($G103,DATE(2026,9,30))-MAX($E103,DATE(2026,9,1))+1))/30.4 -> 0 | Z103: =$H103*MAX(0,(MIN($G103,DATE(2026,10,31))-MAX($E103,DATE(2026,10,1))+1))/30.4 -> 0 | AA103: =$H103*MAX(0,(MIN($G103,DATE(2026,11,30))-MAX($E103,DATE(2026,11,1))+1))/30.4 -> 0 | AB103: =$H103*MAX(0,(MIN($G103,DATE(2026,12,31))-MAX($E103,DATE(2026,12,1))+1))/30.4 -> 0
A104: 54 | B104: 3 | D104: SE | E104: 46209 | F104: 5 | G104: 46244 | H104: 1 | I104: Not Resourced | J104: =IFERROR(VLOOKUP(D104,Role_Mapping!$A$5:$D$31,2,FALSE()),"UNMAPPED") -> Software Engineer | K104: =IFERROR(VLOOKUP(D104,Role_Mapping!$A$5:$D$31,3,FALSE()),"IN") -> IN | L104: =IFERROR(SUMPRODUCT((Rate_Card!$A$5:$A$34=J104)*(Rate_Card!$B$5:$B$34=K104)*Rate_Card!$C$5:$C$34),0) -> 455 | M104: =F104*5 -> 25 | N104: =L104*M104*H104 -> 11375 | O104: =(G104-E104)+1 -> 36 | P104: =IFERROR(VLOOKUP(D104,Role_Mapping!$A$5:$D$31,4,FALSE()),"UNMAPPED") -> Full Stack | Q104: =$N104*MAX(0,(MIN($G104,DATE(2026,7,31))-MAX($E104,DATE(2026,7,1))+1))/$O104 -> 8215.2778 | R104: =$N104*MAX(0,(MIN($G104,DATE(2026,8,31))-MAX($E104,DATE(2026,8,1))+1))/$O104 -> 3159.7222 | S104: =$N104*MAX(0,(MIN($G104,DATE(2026,9,30))-MAX($E104,DATE(2026,9,1))+1))/$O104 -> 0 | T104: =$N104*MAX(0,(MIN($G104,DATE(2026,10,31))-MAX($E104,DATE(2026,10,1))+1))/$O104 -> 0 | U104: =$N104*MAX(0,(MIN($G104,DATE(2026,11,30))-MAX($E104,DATE(2026,11,1))+1))/$O104 -> 0 | V104: =$N104*MAX(0,(MIN($G104,DATE(2026,12,31))-MAX($E104,DATE(2026,12,1))+1))/$O104 -> 0 | W104: =$H104*MAX(0,(MIN($G104,DATE(2026,7,31))-MAX($E104,DATE(2026,7,1))+1))/30.4 -> 0.85526316 | X104: =$H104*MAX(0,(MIN($G104,DATE(2026,8,31))-MAX($E104,DATE(2026,8,1))+1))/30.4 -> 0.32894737 | Y104: =$H104*MAX(0,(MIN($G104,DATE(2026,9,30))-MAX($E104,DATE(2026,9,1))+1))/30.4 -> 0 | Z104: =$H104*MAX(0,(MIN($G104,DATE(2026,10,31))-MAX($E104,DATE(2026,10,1))+1))/30.4 -> 0 | AA104: =$H104*MAX(0,(MIN($G104,DATE(2026,11,30))-MAX($E104,DATE(2026,11,1))+1))/30.4 -> 0 | AB104: =$H104*MAX(0,(MIN($G104,DATE(2026,12,31))-MAX($E104,DATE(2026,12,1))+1))/30.4 -> 0
A105: 55 | B105: 3 | D105: SE | E105: 46209 | F105: 5 | G105: 46244 | H105: 1 | I105: Not Resourced | J105: =IFERROR(VLOOKUP(D105,Role_Mapping!$A$5:$D$31,2,FALSE()),"UNMAPPED") -> Software Engineer | K105: =IFERROR(VLOOKUP(D105,Role_Mapping!$A$5:$D$31,3,FALSE()),"IN") -> IN | L105: =IFERROR(SUMPRODUCT((Rate_Card!$A$5:$A$34=J105)*(Rate_Card!$B$5:$B$34=K105)*Rate_Card!$C$5:$C$34),0) -> 455 | M105: =F105*5 -> 25 | N105: =L105*M105*H105 -> 11375 | O105: =(G105-E105)+1 -> 36 | P105: =IFERROR(VLOOKUP(D105,Role_Mapping!$A$5:$D$31,4,FALSE()),"UNMAPPED") -> Full Stack | Q105: =$N105*MAX(0,(MIN($G105,DATE(2026,7,31))-MAX($E105,DATE(2026,7,1))+1))/$O105 -> 8215.2778 | R105: =$N105*MAX(0,(MIN($G105,DATE(2026,8,31))-MAX($E105,DATE(2026,8,1))+1))/$O105 -> 3159.7222 | S105: =$N105*MAX(0,(MIN($G105,DATE(2026,9,30))-MAX($E105,DATE(2026,9,1))+1))/$O105 -> 0 | T105: =$N105*MAX(0,(MIN($G105,DATE(2026,10,31))-MAX($E105,DATE(2026,10,1))+1))/$O105 -> 0 | U105: =$N105*MAX(0,(MIN($G105,DATE(2026,11,30))-MAX($E105,DATE(2026,11,1))+1))/$O105 -> 0 | V105: =$N105*MAX(0,(MIN($G105,DATE(2026,12,31))-MAX($E105,DATE(2026,12,1))+1))/$O105 -> 0 | W105: =$H105*MAX(0,(MIN($G105,DATE(2026,7,31))-MAX($E105,DATE(2026,7,1))+1))/30.4 -> 0.85526316 | X105: =$H105*MAX(0,(MIN($G105,DATE(2026,8,31))-MAX($E105,DATE(2026,8,1))+1))/30.4 -> 0.32894737 | Y105: =$H105*MAX(0,(MIN($G105,DATE(2026,9,30))-MAX($E105,DATE(2026,9,1))+1))/30.4 -> 0 | Z105: =$H105*MAX(0,(MIN($G105,DATE(2026,10,31))-MAX($E105,DATE(2026,10,1))+1))/30.4 -> 0 | AA105: =$H105*MAX(0,(MIN($G105,DATE(2026,11,30))-MAX($E105,DATE(2026,11,1))+1))/30.4 -> 0 | AB105: =$H105*MAX(0,(MIN($G105,DATE(2026,12,31))-MAX($E105,DATE(2026,12,1))+1))/30.4 -> 0
A106: 56 | B106: 1 | C106: Lexus | D106: SE | E106: 46181 | F106: 5 | G106: 46216 | H106: 1 | I106: Not Resourced | J106: =IFERROR(VLOOKUP(D106,Role_Mapping!$A$5:$D$31,2,FALSE()),"UNMAPPED") -> Software Engineer | K106: =IFERROR(VLOOKUP(D106,Role_Mapping!$A$5:$D$31,3,FALSE()),"IN") -> IN | L106: =IFERROR(SUMPRODUCT((Rate_Card!$A$5:$A$34=J106)*(Rate_Card!$B$5:$B$34=K106)*Rate_Card!$C$5:$C$34),0) -> 455 | M106: =F106*5 -> 25 | N106: =L106*M106*H106 -> 11375 | O106: =(G106-E106)+1 -> 36 | P106: =IFERROR(VLOOKUP(D106,Role_Mapping!$A$5:$D$31,4,FALSE()),"UNMAPPED") -> Full Stack | Q106: =$N106*MAX(0,(MIN($G106,DATE(2026,7,31))-MAX($E106,DATE(2026,7,1))+1))/$O106 -> 4107.6389 | R106: =$N106*MAX(0,(MIN($G106,DATE(2026,8,31))-MAX($E106,DATE(2026,8,1))+1))/$O106 -> 0 | S106: =$N106*MAX(0,(MIN($G106,DATE(2026,9,30))-MAX($E106,DATE(2026,9,1))+1))/$O106 -> 0 | T106: =$N106*MAX(0,(MIN($G106,DATE(2026,10,31))-MAX($E106,DATE(2026,10,1))+1))/$O106 -> 0 | U106: =$N106*MAX(0,(MIN($G106,DATE(2026,11,30))-MAX($E106,DATE(2026,11,1))+1))/$O106 -> 0 | V106: =$N106*MAX(0,(MIN($G106,DATE(2026,12,31))-MAX($E106,DATE(2026,12,1))+1))/$O106 -> 0 | W106: =$H106*MAX(0,(MIN($G106,DATE(2026,7,31))-MAX($E106,DATE(2026,7,1))+1))/30.4 -> 0.42763158 | X106: =$H106*MAX(0,(MIN($G106,DATE(2026,8,31))-MAX($E106,DATE(2026,8,1))+1))/30.4 -> 0 | Y106: =$H106*MAX(0,(MIN($G106,DATE(2026,9,30))-MAX($E106,DATE(2026,9,1))+1))/30.4 -> 0 | Z106: =$H106*MAX(0,(MIN($G106,DATE(2026,10,31))-MAX($E106,DATE(2026,10,1))+1))/30.4 -> 0 | AA106: =$H106*MAX(0,(MIN($G106,DATE(2026,11,30))-MAX($E106,DATE(2026,11,1))+1))/30.4 -> 0 | AB106: =$H106*MAX(0,(MIN($G106,DATE(2026,12,31))-MAX($E106,DATE(2026,12,1))+1))/30.4 -> 0
A107: 57 | B107: 2 | C107: BYD | D107: P | E107: 46202 | F107: 4 | G107: 46230 | H107: 0.5 | I107: Not Resourced | J107: =IFERROR(VLOOKUP(D107,Role_Mapping!$A$5:$D$31,2,FALSE()),"UNMAPPED") -> Associate Partner | K107: =IFERROR(VLOOKUP(D107,Role_Mapping!$A$5:$D$31,3,FALSE()),"IN") -> UK | L107: =IFERROR(SUMPRODUCT((Rate_Card!$A$5:$A$34=J107)*(Rate_Card!$B$5:$B$34=K107)*Rate_Card!$C$5:$C$34),0) -> 3526 | M107: =F107*5 -> 20 | N107: =L107*M107*H107 -> 35260 | O107: =(G107-E107)+1 -> 29 | P107: =IFERROR(VLOOKUP(D107,Role_Mapping!$A$5:$D$31,4,FALSE()),"UNMAPPED") -> GTM | Q107: =$N107*MAX(0,(MIN($G107,DATE(2026,7,31))-MAX($E107,DATE(2026,7,1))+1))/$O107 -> 32828.276 | R107: =$N107*MAX(0,(MIN($G107,DATE(2026,8,31))-MAX($E107,DATE(2026,8,1))+1))/$O107 -> 0 | S107: =$N107*MAX(0,(MIN($G107,DATE(2026,9,30))-MAX($E107,DATE(2026,9,1))+1))/$O107 -> 0 | T107: =$N107*MAX(0,(MIN($G107,DATE(2026,10,31))-MAX($E107,DATE(2026,10,1))+1))/$O107 -> 0 | U107: =$N107*MAX(0,(MIN($G107,DATE(2026,11,30))-MAX($E107,DATE(2026,11,1))+1))/$O107 -> 0 | V107: =$N107*MAX(0,(MIN($G107,DATE(2026,12,31))-MAX($E107,DATE(2026,12,1))+1))/$O107 -> 0 | W107: =$H107*MAX(0,(MIN($G107,DATE(2026,7,31))-MAX($E107,DATE(2026,7,1))+1))/30.4 -> 0.44407895 | X107: =$H107*MAX(0,(MIN($G107,DATE(2026,8,31))-MAX($E107,DATE(2026,8,1))+1))/30.4 -> 0 | Y107: =$H107*MAX(0,(MIN($G107,DATE(2026,9,30))-MAX($E107,DATE(2026,9,1))+1))/30.4 -> 0 | Z107: =$H107*MAX(0,(MIN($G107,DATE(2026,10,31))-MAX($E107,DATE(2026,10,1))+1))/30.4 -> 0 | AA107: =$H107*MAX(0,(MIN($G107,DATE(2026,11,30))-MAX($E107,DATE(2026,11,1))+1))/30.4 -> 0 | AB107: =$H107*MAX(0,(MIN($G107,DATE(2026,12,31))-MAX($E107,DATE(2026,12,1))+1))/30.4 -> 0
A108: 58 | B108: 2 | D108: SC (EM) | E108: 46202 | F108: 5 | G108: 46237 | H108: 0.5 | I108: Not Resourced | J108: =IFERROR(VLOOKUP(D108,Role_Mapping!$A$5:$D$31,2,FALSE()),"UNMAPPED") -> Senior Consultant | K108: =IFERROR(VLOOKUP(D108,Role_Mapping!$A$5:$D$31,3,FALSE()),"IN") -> UK | L108: =IFERROR(SUMPRODUCT((Rate_Card!$A$5:$A$34=J108)*(Rate_Card!$B$5:$B$34=K108)*Rate_Card!$C$5:$C$34),0) -> 2798 | M108: =F108*5 -> 25 | N108: =L108*M108*H108 -> 34975 | O108: =(G108-E108)+1 -> 36 | P108: =IFERROR(VLOOKUP(D108,Role_Mapping!$A$5:$D$31,4,FALSE()),"UNMAPPED") -> Consulting | Q108: =$N108*MAX(0,(MIN($G108,DATE(2026,7,31))-MAX($E108,DATE(2026,7,1))+1))/$O108 -> 30117.361 | R108: =$N108*MAX(0,(MIN($G108,DATE(2026,8,31))-MAX($E108,DATE(2026,8,1))+1))/$O108 -> 2914.5833 | S108: =$N108*MAX(0,(MIN($G108,DATE(2026,9,30))-MAX($E108,DATE(2026,9,1))+1))/$O108 -> 0 | T108: =$N108*MAX(0,(MIN($G108,DATE(2026,10,31))-MAX($E108,DATE(2026,10,1))+1))/$O108 -> 0 | U108: =$N108*MAX(0,(MIN($G108,DATE(2026,11,30))-MAX($E108,DATE(2026,11,1))+1))/$O108 -> 0 | V108: =$N108*MAX(0,(MIN($G108,DATE(2026,12,31))-MAX($E108,DATE(2026,12,1))+1))/$O108 -> 0 | W108: =$H108*MAX(0,(MIN($G108,DATE(2026,7,31))-MAX($E108,DATE(2026,7,1))+1))/30.4 -> 0.50986842 | X108: =$H108*MAX(0,(MIN($G108,DATE(2026,8,31))-MAX($E108,DATE(2026,8,1))+1))/30.4 -> 0.049342105 | Y108: =$H108*MAX(0,(MIN($G108,DATE(2026,9,30))-MAX($E108,DATE(2026,9,1))+1))/30.4 -> 0 | Z108: =$H108*MAX(0,(MIN($G108,DATE(2026,10,31))-MAX($E108,DATE(2026,10,1))+1))/30.4 -> 0 | AA108: =$H108*MAX(0,(MIN($G108,DATE(2026,11,30))-MAX($E108,DATE(2026,11,1))+1))/30.4 -> 0 | AB108: =$H108*MAX(0,(MIN($G108,DATE(2026,12,31))-MAX($E108,DATE(2026,12,1))+1))/30.4 -> 0
A109: 59 | B109: 2 | D109: C | E109: 46202 | F109: 5 | G109: 46237 | H109: 1 | I109: Not Resourced | J109: =IFERROR(VLOOKUP(D109,Role_Mapping!$A$5:$D$31,2,FALSE()),"UNMAPPED") -> Consultant | K109: =IFERROR(VLOOKUP(D109,Role_Mapping!$A$5:$D$31,3,FALSE()),"IN") -> IN | L109: =IFERROR(SUMPRODUCT((Rate_Card!$A$5:$A$34=J109)*(Rate_Card!$B$5:$B$34=K109)*Rate_Card!$C$5:$C$34),0) -> 683 | M109: =F109*5 -> 25 | N109: =L109*M109*H109 -> 17075 | O109: =(G109-E109)+1 -> 36 | P109: =IFERROR(VLOOKUP(D109,Role_Mapping!$A$5:$D$31,4,FALSE()),"UNMAPPED") -> Consulting | Q109: =$N109*MAX(0,(MIN($G109,DATE(2026,7,31))-MAX($E109,DATE(2026,7,1))+1))/$O109 -> 14703.472 | R109: =$N109*MAX(0,(MIN($G109,DATE(2026,8,31))-MAX($E109,DATE(2026,8,1))+1))/$O109 -> 1422.9167 | S109: =$N109*MAX(0,(MIN($G109,DATE(2026,9,30))-MAX($E109,DATE(2026,9,1))+1))/$O109 -> 0 | T109: =$N109*MAX(0,(MIN($G109,DATE(2026,10,31))-MAX($E109,DATE(2026,10,1))+1))/$O109 -> 0 | U109: =$N109*MAX(0,(MIN($G109,DATE(2026,11,30))-MAX($E109,DATE(2026,11,1))+1))/$O109 -> 0 | V109: =$N109*MAX(0,(MIN($G109,DATE(2026,12,31))-MAX($E109,DATE(2026,12,1))+1))/$O109 -> 0 | W109: =$H109*MAX(0,(MIN($G109,DATE(2026,7,31))-MAX($E109,DATE(2026,7,1))+1))/30.4 -> 1.0197368 | X109: =$H109*MAX(0,(MIN($G109,DATE(2026,8,31))-MAX($E109,DATE(2026,8,1))+1))/30.4 -> 0.098684211 | Y109: =$H109*MAX(0,(MIN($G109,DATE(2026,9,30))-MAX($E109,DATE(2026,9,1))+1))/30.4 -> 0 | Z109: =$H109*MAX(0,(MIN($G109,DATE(2026,10,31))-MAX($E109,DATE(2026,10,1))+1))/30.4 -> 0 | AA109: =$H109*MAX(0,(MIN($G109,DATE(2026,11,30))-MAX($E109,DATE(2026,11,1))+1))/30.4 -> 0 | AB109: =$H109*MAX(0,(MIN($G109,DATE(2026,12,31))-MAX($E109,DATE(2026,12,1))+1))/30.4 -> 0
A110: 59 | B110: 2 | D110: SC | E110: 46202 | F110: 5 | G110: 46237 | H110: 0.5 | I110: Not Resourced | J110: =IFERROR(VLOOKUP(D110,Role_Mapping!$A$5:$D$31,2,FALSE()),"UNMAPPED") -> Senior Consultant | K110: =IFERROR(VLOOKUP(D110,Role_Mapping!$A$5:$D$31,3,FALSE()),"IN") -> UK | L110: =IFERROR(SUMPRODUCT((Rate_Card!$A$5:$A$34=J110)*(Rate_Card!$B$5:$B$34=K110)*Rate_Card!$C$5:$C$34),0) -> 2798 | M110: =F110*5 -> 25 | N110: =L110*M110*H110 -> 34975 | O110: =(G110-E110)+1 -> 36 | P110: =IFERROR(VLOOKUP(D110,Role_Mapping!$A$5:$D$31,4,FALSE()),"UNMAPPED") -> Consulting | Q110: =$N110*MAX(0,(MIN($G110,DATE(2026,7,31))-MAX($E110,DATE(2026,7,1))+1))/$O110 -> 30117.361 | R110: =$N110*MAX(0,(MIN($G110,DATE(2026,8,31))-MAX($E110,DATE(2026,8,1))+1))/$O110 -> 2914.5833 | S110: =$N110*MAX(0,(MIN($G110,DATE(2026,9,30))-MAX($E110,DATE(2026,9,1))+1))/$O110 -> 0 | T110: =$N110*MAX(0,(MIN($G110,DATE(2026,10,31))-MAX($E110,DATE(2026,10,1))+1))/$O110 -> 0 | U110: =$N110*MAX(0,(MIN($G110,DATE(2026,11,30))-MAX($E110,DATE(2026,11,1))+1))/$O110 -> 0 | V110: =$N110*MAX(0,(MIN($G110,DATE(2026,12,31))-MAX($E110,DATE(2026,12,1))+1))/$O110 -> 0 | W110: =$H110*MAX(0,(MIN($G110,DATE(2026,7,31))-MAX($E110,DATE(2026,7,1))+1))/30.4 -> 0.50986842 | X110: =$H110*MAX(0,(MIN($G110,DATE(2026,8,31))-MAX($E110,DATE(2026,8,1))+1))/30.4 -> 0.049342105 | Y110: =$H110*MAX(0,(MIN($G110,DATE(2026,9,30))-MAX($E110,DATE(2026,9,1))+1))/30.4 -> 0 | Z110: =$H110*MAX(0,(MIN($G110,DATE(2026,10,31))-MAX($E110,DATE(2026,10,1))+1))/30.4 -> 0 | AA110: =$H110*MAX(0,(MIN($G110,DATE(2026,11,30))-MAX($E110,DATE(2026,11,1))+1))/30.4 -> 0 | AB110: =$H110*MAX(0,(MIN($G110,DATE(2026,12,31))-MAX($E110,DATE(2026,12,1))+1))/30.4 -> 0
A111: 60 | B111: 2 | D111: SSE | E111: 46202 | F111: 5 | G111: 46237 | H111: 1 | I111: Not Resourced | J111: =IFERROR(VLOOKUP(D111,Role_Mapping!$A$5:$D$31,2,FALSE()),"UNMAPPED") -> Senior Software Engineer | K111: =IFERROR(VLOOKUP(D111,Role_Mapping!$A$5:$D$31,3,FALSE()),"IN") -> IN | L111: =IFERROR(SUMPRODUCT((Rate_Card!$A$5:$A$34=J111)*(Rate_Card!$B$5:$B$34=K111)*Rate_Card!$C$5:$C$34),0) -> 585 | M111: =F111*5 -> 25 | N111: =L111*M111*H111 -> 14625 | O111: =(G111-E111)+1 -> 36 | P111: =IFERROR(VLOOKUP(D111,Role_Mapping!$A$5:$D$31,4,FALSE()),"UNMAPPED") -> Full Stack | Q111: =$N111*MAX(0,(MIN($G111,DATE(2026,7,31))-MAX($E111,DATE(2026,7,1))+1))/$O111 -> 12593.75 | R111: =$N111*MAX(0,(MIN($G111,DATE(2026,8,31))-MAX($E111,DATE(2026,8,1))+1))/$O111 -> 1218.75 | S111: =$N111*MAX(0,(MIN($G111,DATE(2026,9,30))-MAX($E111,DATE(2026,9,1))+1))/$O111 -> 0 | T111: =$N111*MAX(0,(MIN($G111,DATE(2026,10,31))-MAX($E111,DATE(2026,10,1))+1))/$O111 -> 0 | U111: =$N111*MAX(0,(MIN($G111,DATE(2026,11,30))-MAX($E111,DATE(2026,11,1))+1))/$O111 -> 0 | V111: =$N111*MAX(0,(MIN($G111,DATE(2026,12,31))-MAX($E111,DATE(2026,12,1))+1))/$O111 -> 0 | W111: =$H111*MAX(0,(MIN($G111,DATE(2026,7,31))-MAX($E111,DATE(2026,7,1))+1))/30.4 -> 1.0197368 | X111: =$H111*MAX(0,(MIN($G111,DATE(2026,8,31))-MAX($E111,DATE(2026,8,1))+1))/30.4 -> 0.098684211 | Y111: =$H111*MAX(0,(MIN($G111,DATE(2026,9,30))-MAX($E111,DATE(2026,9,1))+1))/30.4 -> 0 | Z111: =$H111*MAX(0,(MIN($G111,DATE(2026,10,31))-MAX($E111,DATE(2026,10,1))+1))/30.4 -> 0 | AA111: =$H111*MAX(0,(MIN($G111,DATE(2026,11,30))-MAX($E111,DATE(2026,11,1))+1))/30.4 -> 0 | AB111: =$H111*MAX(0,(MIN($G111,DATE(2026,12,31))-MAX($E111,DATE(2026,12,1))+1))/30.4 -> 0
A112: 61 | B112: 2 | D112: SSE | E112: 46202 | F112: 5 | G112: 46237 | H112: 1 | I112: Not Resourced | J112: =IFERROR(VLOOKUP(D112,Role_Mapping!$A$5:$D$31,2,FALSE()),"UNMAPPED") -> Senior Software Engineer | K112: =IFERROR(VLOOKUP(D112,Role_Mapping!$A$5:$D$31,3,FALSE()),"IN") -> IN | L112: =IFERROR(SUMPRODUCT((Rate_Card!$A$5:$A$34=J112)*(Rate_Card!$B$5:$B$34=K112)*Rate_Card!$C$5:$C$34),0) -> 585 | M112: =F112*5 -> 25 | N112: =L112*M112*H112 -> 14625 | O112: =(G112-E112)+1 -> 36 | P112: =IFERROR(VLOOKUP(D112,Role_Mapping!$A$5:$D$31,4,FALSE()),"UNMAPPED") -> Full Stack | Q112: =$N112*MAX(0,(MIN($G112,DATE(2026,7,31))-MAX($E112,DATE(2026,7,1))+1))/$O112 -> 12593.75 | R112: =$N112*MAX(0,(MIN($G112,DATE(2026,8,31))-MAX($E112,DATE(2026,8,1))+1))/$O112 -> 1218.75 | S112: =$N112*MAX(0,(MIN($G112,DATE(2026,9,30))-MAX($E112,DATE(2026,9,1))+1))/$O112 -> 0 | T112: =$N112*MAX(0,(MIN($G112,DATE(2026,10,31))-MAX($E112,DATE(2026,10,1))+1))/$O112 -> 0 | U112: =$N112*MAX(0,(MIN($G112,DATE(2026,11,30))-MAX($E112,DATE(2026,11,1))+1))/$O112 -> 0 | V112: =$N112*MAX(0,(MIN($G112,DATE(2026,12,31))-MAX($E112,DATE(2026,12,1))+1))/$O112 -> 0 | W112: =$H112*MAX(0,(MIN($G112,DATE(2026,7,31))-MAX($E112,DATE(2026,7,1))+1))/30.4 -> 1.0197368 | X112: =$H112*MAX(0,(MIN($G112,DATE(2026,8,31))-MAX($E112,DATE(2026,8,1))+1))/30.4 -> 0.098684211 | Y112: =$H112*MAX(0,(MIN($G112,DATE(2026,9,30))-MAX($E112,DATE(2026,9,1))+1))/30.4 -> 0 | Z112: =$H112*MAX(0,(MIN($G112,DATE(2026,10,31))-MAX($E112,DATE(2026,10,1))+1))/30.4 -> 0 | AA112: =$H112*MAX(0,(MIN($G112,DATE(2026,11,30))-MAX($E112,DATE(2026,11,1))+1))/30.4 -> 0 | AB112: =$H112*MAX(0,(MIN($G112,DATE(2026,12,31))-MAX($E112,DATE(2026,12,1))+1))/30.4 -> 0
A113: 62 | B113: 4 | C113: Toyata | D113: SC or C - EM | E113: 46188 | F113: 5 | G113: 46223 | H113: 0.5 | I113: Not Resourced | J113: =IFERROR(VLOOKUP(D113,Role_Mapping!$A$5:$D$31,2,FALSE()),"UNMAPPED") -> Senior Consultant | K113: =IFERROR(VLOOKUP(D113,Role_Mapping!$A$5:$D$31,3,FALSE()),"IN") -> UK | L113: =IFERROR(SUMPRODUCT((Rate_Card!$A$5:$A$34=J113)*(Rate_Card!$B$5:$B$34=K113)*Rate_Card!$C$5:$C$34),0) -> 2798 | M113: =F113*5 -> 25 | N113: =L113*M113*H113 -> 34975 | O113: =(G113-E113)+1 -> 36 | P113: =IFERROR(VLOOKUP(D113,Role_Mapping!$A$5:$D$31,4,FALSE()),"UNMAPPED") -> Consulting | Q113: =$N113*MAX(0,(MIN($G113,DATE(2026,7,31))-MAX($E113,DATE(2026,7,1))+1))/$O113 -> 19430.556 | R113: =$N113*MAX(0,(MIN($G113,DATE(2026,8,31))-MAX($E113,DATE(2026,8,1))+1))/$O113 -> 0 | S113: =$N113*MAX(0,(MIN($G113,DATE(2026,9,30))-MAX($E113,DATE(2026,9,1))+1))/$O113 -> 0 | T113: =$N113*MAX(0,(MIN($G113,DATE(2026,10,31))-MAX($E113,DATE(2026,10,1))+1))/$O113 -> 0 | U113: =$N113*MAX(0,(MIN($G113,DATE(2026,11,30))-MAX($E113,DATE(2026,11,1))+1))/$O113 -> 0 | V113: =$N113*MAX(0,(MIN($G113,DATE(2026,12,31))-MAX($E113,DATE(2026,12,1))+1))/$O113 -> 0 | W113: =$H113*MAX(0,(MIN($G113,DATE(2026,7,31))-MAX($E113,DATE(2026,7,1))+1))/30.4 -> 0.32894737 | X113: =$H113*MAX(0,(MIN($G113,DATE(2026,8,31))-MAX($E113,DATE(2026,8,1))+1))/30.4 -> 0 | Y113: =$H113*MAX(0,(MIN($G113,DATE(2026,9,30))-MAX($E113,DATE(2026,9,1))+1))/30.4 -> 0 | Z113: =$H113*MAX(0,(MIN($G113,DATE(2026,10,31))-MAX($E113,DATE(2026,10,1))+1))/30.4 -> 0 | AA113: =$H113*MAX(0,(MIN($G113,DATE(2026,11,30))-MAX($E113,DATE(2026,11,1))+1))/30.4 -> 0 | AB113: =$H113*MAX(0,(MIN($G113,DATE(2026,12,31))-MAX($E113,DATE(2026,12,1))+1))/30.4 -> 0
A114: 63 | B114: 4 | C114: Chevy | D114: AP | E114: 46188 | F114: 5 | G114: 46223 | H114: 0.125 | I114: Resourced | J114: =IFERROR(VLOOKUP(D114,Role_Mapping!$A$5:$D$31,2,FALSE()),"UNMAPPED") -> Associate Partner | K114: =IFERROR(VLOOKUP(D114,Role_Mapping!$A$5:$D$31,3,FALSE()),"IN") -> UK | L114: =IFERROR(SUMPRODUCT((Rate_Card!$A$5:$A$34=J114)*(Rate_Card!$B$5:$B$34=K114)*Rate_Card!$C$5:$C$34),0) -> 3526 | M114: =F114*5 -> 25 | N114: =L114*M114*H114 -> 11018.75 | O114: =(G114-E114)+1 -> 36 | P114: =IFERROR(VLOOKUP(D114,Role_Mapping!$A$5:$D$31,4,FALSE()),"UNMAPPED") -> GTM | Q114: =$N114*MAX(0,(MIN($G114,DATE(2026,7,31))-MAX($E114,DATE(2026,7,1))+1))/$O114 -> 6121.5278 | R114: =$N114*MAX(0,(MIN($G114,DATE(2026,8,31))-MAX($E114,DATE(2026,8,1))+1))/$O114 -> 0 | S114: =$N114*MAX(0,(MIN($G114,DATE(2026,9,30))-MAX($E114,DATE(2026,9,1))+1))/$O114 -> 0 | T114: =$N114*MAX(0,(MIN($G114,DATE(2026,10,31))-MAX($E114,DATE(2026,10,1))+1))/$O114 -> 0 | U114: =$N114*MAX(0,(MIN($G114,DATE(2026,11,30))-MAX($E114,DATE(2026,11,1))+1))/$O114 -> 0 | V114: =$N114*MAX(0,(MIN($G114,DATE(2026,12,31))-MAX($E114,DATE(2026,12,1))+1))/$O114 -> 0 | W114: =$H114*MAX(0,(MIN($G114,DATE(2026,7,31))-MAX($E114,DATE(2026,7,1))+1))/30.4 -> 0.082236842 | X114: =$H114*MAX(0,(MIN($G114,DATE(2026,8,31))-MAX($E114,DATE(2026,8,1))+1))/30.4 -> 0 | Y114: =$H114*MAX(0,(MIN($G114,DATE(2026,9,30))-MAX($E114,DATE(2026,9,1))+1))/30.4 -> 0 | Z114: =$H114*MAX(0,(MIN($G114,DATE(2026,10,31))-MAX($E114,DATE(2026,10,1))+1))/30.4 -> 0 | AA114: =$H114*MAX(0,(MIN($G114,DATE(2026,11,30))-MAX($E114,DATE(2026,11,1))+1))/30.4 -> 0 | AB114: =$H114*MAX(0,(MIN($G114,DATE(2026,12,31))-MAX($E114,DATE(2026,12,1))+1))/30.4 -> 0
A115: 64 | B115: 4 | D115: PA | E115: 46188 | F115: 5 | G115: 46223 | H115: 0.125 | I115: Resourced | J115: =IFERROR(VLOOKUP(D115,Role_Mapping!$A$5:$D$31,2,FALSE()),"UNMAPPED") -> Principal Technology Architect | K115: =IFERROR(VLOOKUP(D115,Role_Mapping!$A$5:$D$31,3,FALSE()),"IN") -> IN | L115: =IFERROR(SUMPRODUCT((Rate_Card!$A$5:$A$34=J115)*(Rate_Card!$B$5:$B$34=K115)*Rate_Card!$C$5:$C$34),0) -> 845 | M115: =F115*5 -> 25 | N115: =L115*M115*H115 -> 2640.625 | O115: =(G115-E115)+1 -> 36 | P115: =IFERROR(VLOOKUP(D115,Role_Mapping!$A$5:$D$31,4,FALSE()),"UNMAPPED") -> Full Stack | Q115: =$N115*MAX(0,(MIN($G115,DATE(2026,7,31))-MAX($E115,DATE(2026,7,1))+1))/$O115 -> 1467.0139 | R115: =$N115*MAX(0,(MIN($G115,DATE(2026,8,31))-MAX($E115,DATE(2026,8,1))+1))/$O115 -> 0 | S115: =$N115*MAX(0,(MIN($G115,DATE(2026,9,30))-MAX($E115,DATE(2026,9,1))+1))/$O115 -> 0 | T115: =$N115*MAX(0,(MIN($G115,DATE(2026,10,31))-MAX($E115,DATE(2026,10,1))+1))/$O115 -> 0 | U115: =$N115*MAX(0,(MIN($G115,DATE(2026,11,30))-MAX($E115,DATE(2026,11,1))+1))/$O115 -> 0 | V115: =$N115*MAX(0,(MIN($G115,DATE(2026,12,31))-MAX($E115,DATE(2026,12,1))+1))/$O115 -> 0 | W115: =$H115*MAX(0,(MIN($G115,DATE(2026,7,31))-MAX($E115,DATE(2026,7,1))+1))/30.4 -> 0.082236842 | X115: =$H115*MAX(0,(MIN($G115,DATE(2026,8,31))-MAX($E115,DATE(2026,8,1))+1))/30.4 -> 0 | Y115: =$H115*MAX(0,(MIN($G115,DATE(2026,9,30))-MAX($E115,DATE(2026,9,1))+1))/30.4 -> 0 | Z115: =$H115*MAX(0,(MIN($G115,DATE(2026,10,31))-MAX($E115,DATE(2026,10,1))+1))/30.4 -> 0 | AA115: =$H115*MAX(0,(MIN($G115,DATE(2026,11,30))-MAX($E115,DATE(2026,11,1))+1))/30.4 -> 0 | AB115: =$H115*MAX(0,(MIN($G115,DATE(2026,12,31))-MAX($E115,DATE(2026,12,1))+1))/30.4 -> 0
A116: 65 | B116: 4 | D116: M | E116: 46188 | F116: 5 | G116: 46223 | H116: 0.5 | I116: Resourced | J116: =IFERROR(VLOOKUP(D116,Role_Mapping!$A$5:$D$31,2,FALSE()),"UNMAPPED") -> Manager | K116: =IFERROR(VLOOKUP(D116,Role_Mapping!$A$5:$D$31,3,FALSE()),"IN") -> UK | L116: =IFERROR(SUMPRODUCT((Rate_Card!$A$5:$A$34=J116)*(Rate_Card!$B$5:$B$34=K116)*Rate_Card!$C$5:$C$34),0) -> 2984 | M116: =F116*5 -> 25 | N116: =L116*M116*H116 -> 37300 | O116: =(G116-E116)+1 -> 36 | P116: =IFERROR(VLOOKUP(D116,Role_Mapping!$A$5:$D$31,4,FALSE()),"UNMAPPED") -> Consulting | Q116: =$N116*MAX(0,(MIN($G116,DATE(2026,7,31))-MAX($E116,DATE(2026,7,1))+1))/$O116 -> 20722.222 | R116: =$N116*MAX(0,(MIN($G116,DATE(2026,8,31))-MAX($E116,DATE(2026,8,1))+1))/$O116 -> 0 | S116: =$N116*MAX(0,(MIN($G116,DATE(2026,9,30))-MAX($E116,DATE(2026,9,1))+1))/$O116 -> 0 | T116: =$N116*MAX(0,(MIN($G116,DATE(2026,10,31))-MAX($E116,DATE(2026,10,1))+1))/$O116 -> 0 | U116: =$N116*MAX(0,(MIN($G116,DATE(2026,11,30))-MAX($E116,DATE(2026,11,1))+1))/$O116 -> 0 | V116: =$N116*MAX(0,(MIN($G116,DATE(2026,12,31))-MAX($E116,DATE(2026,12,1))+1))/$O116 -> 0 | W116: =$H116*MAX(0,(MIN($G116,DATE(2026,7,31))-MAX($E116,DATE(2026,7,1))+1))/30.4 -> 0.32894737 | X116: =$H116*MAX(0,(MIN($G116,DATE(2026,8,31))-MAX($E116,DATE(2026,8,1))+1))/30.4 -> 0 | Y116: =$H116*MAX(0,(MIN($G116,DATE(2026,9,30))-MAX($E116,DATE(2026,9,1))+1))/30.4 -> 0 | Z116: =$H116*MAX(0,(MIN($G116,DATE(2026,10,31))-MAX($E116,DATE(2026,10,1))+1))/30.4 -> 0 | AA116: =$H116*MAX(0,(MIN($G116,DATE(2026,11,30))-MAX($E116,DATE(2026,11,1))+1))/30.4 -> 0 | AB116: =$H116*MAX(0,(MIN($G116,DATE(2026,12,31))-MAX($E116,DATE(2026,12,1))+1))/30.4 -> 0
A117: 66 | B117: 4 | D117: SAC | E117: 46188 | F117: 5 | G117: 46223 | H117: 1 | I117: Resourced | J117: =IFERROR(VLOOKUP(D117,Role_Mapping!$A$5:$D$31,2,FALSE()),"UNMAPPED") -> Senior Associate Consultant | K117: =IFERROR(VLOOKUP(D117,Role_Mapping!$A$5:$D$31,3,FALSE()),"IN") -> IN | L117: =IFERROR(SUMPRODUCT((Rate_Card!$A$5:$A$34=J117)*(Rate_Card!$B$5:$B$34=K117)*Rate_Card!$C$5:$C$34),0) -> 683 | M117: =F117*5 -> 25 | N117: =L117*M117*H117 -> 17075 | O117: =(G117-E117)+1 -> 36 | P117: =IFERROR(VLOOKUP(D117,Role_Mapping!$A$5:$D$31,4,FALSE()),"UNMAPPED") -> Consulting | Q117: =$N117*MAX(0,(MIN($G117,DATE(2026,7,31))-MAX($E117,DATE(2026,7,1))+1))/$O117 -> 9486.1111 | R117: =$N117*MAX(0,(MIN($G117,DATE(2026,8,31))-MAX($E117,DATE(2026,8,1))+1))/$O117 -> 0 | S117: =$N117*MAX(0,(MIN($G117,DATE(2026,9,30))-MAX($E117,DATE(2026,9,1))+1))/$O117 -> 0 | T117: =$N117*MAX(0,(MIN($G117,DATE(2026,10,31))-MAX($E117,DATE(2026,10,1))+1))/$O117 -> 0 | U117: =$N117*MAX(0,(MIN($G117,DATE(2026,11,30))-MAX($E117,DATE(2026,11,1))+1))/$O117 -> 0 | V117: =$N117*MAX(0,(MIN($G117,DATE(2026,12,31))-MAX($E117,DATE(2026,12,1))+1))/$O117 -> 0 | W117: =$H117*MAX(0,(MIN($G117,DATE(2026,7,31))-MAX($E117,DATE(2026,7,1))+1))/30.4 -> 0.65789474 | X117: =$H117*MAX(0,(MIN($G117,DATE(2026,8,31))-MAX($E117,DATE(2026,8,1))+1))/30.4 -> 0 | Y117: =$H117*MAX(0,(MIN($G117,DATE(2026,9,30))-MAX($E117,DATE(2026,9,1))+1))/30.4 -> 0 | Z117: =$H117*MAX(0,(MIN($G117,DATE(2026,10,31))-MAX($E117,DATE(2026,10,1))+1))/30.4 -> 0 | AA117: =$H117*MAX(0,(MIN($G117,DATE(2026,11,30))-MAX($E117,DATE(2026,11,1))+1))/30.4 -> 0 | AB117: =$H117*MAX(0,(MIN($G117,DATE(2026,12,31))-MAX($E117,DATE(2026,12,1))+1))/30.4 -> 0
A118: 67 | B118: 4 | D118: Sol Con | E118: 46188 | F118: 5 | G118: 46223 | H118: 0.5 | I118: Resourced | J118: =IFERROR(VLOOKUP(D118,Role_Mapping!$A$5:$D$31,2,FALSE()),"UNMAPPED") -> Solutions Consultant | K118: =IFERROR(VLOOKUP(D118,Role_Mapping!$A$5:$D$31,3,FALSE()),"IN") -> IN | L118: =IFERROR(SUMPRODUCT((Rate_Card!$A$5:$A$34=J118)*(Rate_Card!$B$5:$B$34=K118)*Rate_Card!$C$5:$C$34),0) -> 683 | M118: =F118*5 -> 25 | N118: =L118*M118*H118 -> 8537.5 | O118: =(G118-E118)+1 -> 36 | P118: =IFERROR(VLOOKUP(D118,Role_Mapping!$A$5:$D$31,4,FALSE()),"UNMAPPED") -> Power BI & Consulting | Q118: =$N118*MAX(0,(MIN($G118,DATE(2026,7,31))-MAX($E118,DATE(2026,7,1))+1))/$O118 -> 4743.0556 | R118: =$N118*MAX(0,(MIN($G118,DATE(2026,8,31))-MAX($E118,DATE(2026,8,1))+1))/$O118 -> 0 | S118: =$N118*MAX(0,(MIN($G118,DATE(2026,9,30))-MAX($E118,DATE(2026,9,1))+1))/$O118 -> 0 | T118: =$N118*MAX(0,(MIN($G118,DATE(2026,10,31))-MAX($E118,DATE(2026,10,1))+1))/$O118 -> 0 | U118: =$N118*MAX(0,(MIN($G118,DATE(2026,11,30))-MAX($E118,DATE(2026,11,1))+1))/$O118 -> 0 | V118: =$N118*MAX(0,(MIN($G118,DATE(2026,12,31))-MAX($E118,DATE(2026,12,1))+1))/$O118 -> 0 | W118: =$H118*MAX(0,(MIN($G118,DATE(2026,7,31))-MAX($E118,DATE(2026,7,1))+1))/30.4 -> 0.32894737 | X118: =$H118*MAX(0,(MIN($G118,DATE(2026,8,31))-MAX($E118,DATE(2026,8,1))+1))/30.4 -> 0 | Y118: =$H118*MAX(0,(MIN($G118,DATE(2026,9,30))-MAX($E118,DATE(2026,9,1))+1))/30.4 -> 0 | Z118: =$H118*MAX(0,(MIN($G118,DATE(2026,10,31))-MAX($E118,DATE(2026,10,1))+1))/30.4 -> 0 | AA118: =$H118*MAX(0,(MIN($G118,DATE(2026,11,30))-MAX($E118,DATE(2026,11,1))+1))/30.4 -> 0 | AB118: =$H118*MAX(0,(MIN($G118,DATE(2026,12,31))-MAX($E118,DATE(2026,12,1))+1))/30.4 -> 0
A119: 68 | B119: 4 | D119: Enabler | E119: 46188 | F119: 5 | G119: 46223 | H119: 1 | I119: Resourced | J119: =IFERROR(VLOOKUP(D119,Role_Mapping!$A$5:$D$31,2,FALSE()),"UNMAPPED") -> Solutions Enabler | K119: =IFERROR(VLOOKUP(D119,Role_Mapping!$A$5:$D$31,3,FALSE()),"IN") -> IN | L119: =IFERROR(SUMPRODUCT((Rate_Card!$A$5:$A$34=J119)*(Rate_Card!$B$5:$B$34=K119)*Rate_Card!$C$5:$C$34),0) -> 683 | M119: =F119*5 -> 25 | N119: =L119*M119*H119 -> 17075 | O119: =(G119-E119)+1 -> 36 | P119: =IFERROR(VLOOKUP(D119,Role_Mapping!$A$5:$D$31,4,FALSE()),"UNMAPPED") -> Data Engineering | Q119: =$N119*MAX(0,(MIN($G119,DATE(2026,7,31))-MAX($E119,DATE(2026,7,1))+1))/$O119 -> 9486.1111 | R119: =$N119*MAX(0,(MIN($G119,DATE(2026,8,31))-MAX($E119,DATE(2026,8,1))+1))/$O119 -> 0 | S119: =$N119*MAX(0,(MIN($G119,DATE(2026,9,30))-MAX($E119,DATE(2026,9,1))+1))/$O119 -> 0 | T119: =$N119*MAX(0,(MIN($G119,DATE(2026,10,31))-MAX($E119,DATE(2026,10,1))+1))/$O119 -> 0 | U119: =$N119*MAX(0,(MIN($G119,DATE(2026,11,30))-MAX($E119,DATE(2026,11,1))+1))/$O119 -> 0 | V119: =$N119*MAX(0,(MIN($G119,DATE(2026,12,31))-MAX($E119,DATE(2026,12,1))+1))/$O119 -> 0 | W119: =$H119*MAX(0,(MIN($G119,DATE(2026,7,31))-MAX($E119,DATE(2026,7,1))+1))/30.4 -> 0.65789474 | X119: =$H119*MAX(0,(MIN($G119,DATE(2026,8,31))-MAX($E119,DATE(2026,8,1))+1))/30.4 -> 0 | Y119: =$H119*MAX(0,(MIN($G119,DATE(2026,9,30))-MAX($E119,DATE(2026,9,1))+1))/30.4 -> 0 | Z119: =$H119*MAX(0,(MIN($G119,DATE(2026,10,31))-MAX($E119,DATE(2026,10,1))+1))/30.4 -> 0 | AA119: =$H119*MAX(0,(MIN($G119,DATE(2026,11,30))-MAX($E119,DATE(2026,11,1))+1))/30.4 -> 0 | AB119: =$H119*MAX(0,(MIN($G119,DATE(2026,12,31))-MAX($E119,DATE(2026,12,1))+1))/30.4 -> 0
A120: 69 | B120: 4 | D120: SSE | E120: 46188 | F120: 5 | G120: 46223 | H120: 1 | I120: Not Resourced | J120: =IFERROR(VLOOKUP(D120,Role_Mapping!$A$5:$D$31,2,FALSE()),"UNMAPPED") -> Senior Software Engineer | K120: =IFERROR(VLOOKUP(D120,Role_Mapping!$A$5:$D$31,3,FALSE()),"IN") -> IN | L120: =IFERROR(SUMPRODUCT((Rate_Card!$A$5:$A$34=J120)*(Rate_Card!$B$5:$B$34=K120)*Rate_Card!$C$5:$C$34),0) -> 585 | M120: =F120*5 -> 25 | N120: =L120*M120*H120 -> 14625 | O120: =(G120-E120)+1 -> 36 | P120: =IFERROR(VLOOKUP(D120,Role_Mapping!$A$5:$D$31,4,FALSE()),"UNMAPPED") -> Full Stack | Q120: =$N120*MAX(0,(MIN($G120,DATE(2026,7,31))-MAX($E120,DATE(2026,7,1))+1))/$O120 -> 8125 | R120: =$N120*MAX(0,(MIN($G120,DATE(2026,8,31))-MAX($E120,DATE(2026,8,1))+1))/$O120 -> 0 | S120: =$N120*MAX(0,(MIN($G120,DATE(2026,9,30))-MAX($E120,DATE(2026,9,1))+1))/$O120 -> 0 | T120: =$N120*MAX(0,(MIN($G120,DATE(2026,10,31))-MAX($E120,DATE(2026,10,1))+1))/$O120 -> 0 | U120: =$N120*MAX(0,(MIN($G120,DATE(2026,11,30))-MAX($E120,DATE(2026,11,1))+1))/$O120 -> 0 | V120: =$N120*MAX(0,(MIN($G120,DATE(2026,12,31))-MAX($E120,DATE(2026,12,1))+1))/$O120 -> 0 | W120: =$H120*MAX(0,(MIN($G120,DATE(2026,7,31))-MAX($E120,DATE(2026,7,1))+1))/30.4 -> 0.65789474 | X120: =$H120*MAX(0,(MIN($G120,DATE(2026,8,31))-MAX($E120,DATE(2026,8,1))+1))/30.4 -> 0 | Y120: =$H120*MAX(0,(MIN($G120,DATE(2026,9,30))-MAX($E120,DATE(2026,9,1))+1))/30.4 -> 0 | Z120: =$H120*MAX(0,(MIN($G120,DATE(2026,10,31))-MAX($E120,DATE(2026,10,1))+1))/30.4 -> 0 | AA120: =$H120*MAX(0,(MIN($G120,DATE(2026,11,30))-MAX($E120,DATE(2026,11,1))+1))/30.4 -> 0 | AB120: =$H120*MAX(0,(MIN($G120,DATE(2026,12,31))-MAX($E120,DATE(2026,12,1))+1))/30.4 -> 0
A121: 70 | B121: 3 | C121: RE | D121: EM | E121: 46216 | F121: 5 | G121: 46251 | H121: 0.5 | I121: Not Resourced | J121: =IFERROR(VLOOKUP(D121,Role_Mapping!$A$5:$D$31,2,FALSE()),"UNMAPPED") -> Manager | K121: =IFERROR(VLOOKUP(D121,Role_Mapping!$A$5:$D$31,3,FALSE()),"IN") -> UK | L121: =IFERROR(SUMPRODUCT((Rate_Card!$A$5:$A$34=J121)*(Rate_Card!$B$5:$B$34=K121)*Rate_Card!$C$5:$C$34),0) -> 2984 | M121: =F121*5 -> 25 | N121: =L121*M121*H121 -> 37300 | O121: =(G121-E121)+1 -> 36 | P121: =IFERROR(VLOOKUP(D121,Role_Mapping!$A$5:$D$31,4,FALSE()),"UNMAPPED") -> Consulting | Q121: =$N121*MAX(0,(MIN($G121,DATE(2026,7,31))-MAX($E121,DATE(2026,7,1))+1))/$O121 -> 19686.111 | R121: =$N121*MAX(0,(MIN($G121,DATE(2026,8,31))-MAX($E121,DATE(2026,8,1))+1))/$O121 -> 17613.889 | S121: =$N121*MAX(0,(MIN($G121,DATE(2026,9,30))-MAX($E121,DATE(2026,9,1))+1))/$O121 -> 0 | T121: =$N121*MAX(0,(MIN($G121,DATE(2026,10,31))-MAX($E121,DATE(2026,10,1))+1))/$O121 -> 0 | U121: =$N121*MAX(0,(MIN($G121,DATE(2026,11,30))-MAX($E121,DATE(2026,11,1))+1))/$O121 -> 0 | V121: =$N121*MAX(0,(MIN($G121,DATE(2026,12,31))-MAX($E121,DATE(2026,12,1))+1))/$O121 -> 0 | W121: =$H121*MAX(0,(MIN($G121,DATE(2026,7,31))-MAX($E121,DATE(2026,7,1))+1))/30.4 -> 0.3125 | X121: =$H121*MAX(0,(MIN($G121,DATE(2026,8,31))-MAX($E121,DATE(2026,8,1))+1))/30.4 -> 0.27960526 | Y121: =$H121*MAX(0,(MIN($G121,DATE(2026,9,30))-MAX($E121,DATE(2026,9,1))+1))/30.4 -> 0 | Z121: =$H121*MAX(0,(MIN($G121,DATE(2026,10,31))-MAX($E121,DATE(2026,10,1))+1))/30.4 -> 0 | AA121: =$H121*MAX(0,(MIN($G121,DATE(2026,11,30))-MAX($E121,DATE(2026,11,1))+1))/30.4 -> 0 | AB121: =$H121*MAX(0,(MIN($G121,DATE(2026,12,31))-MAX($E121,DATE(2026,12,1))+1))/30.4 -> 0
A122: 71 | B122: 3 | D122: SAC or AC | E122: 46216 | F122: 5 | G122: 46251 | H122: 1 | I122: Not Resourced | J122: =IFERROR(VLOOKUP(D122,Role_Mapping!$A$5:$D$31,2,FALSE()),"UNMAPPED") -> Senior Associate Consultant | K122: =IFERROR(VLOOKUP(D122,Role_Mapping!$A$5:$D$31,3,FALSE()),"IN") -> IN | L122: =IFERROR(SUMPRODUCT((Rate_Card!$A$5:$A$34=J122)*(Rate_Card!$B$5:$B$34=K122)*Rate_Card!$C$5:$C$34),0) -> 683 | M122: =F122*5 -> 25 | N122: =L122*M122*H122 -> 17075 | O122: =(G122-E122)+1 -> 36 | P122: =IFERROR(VLOOKUP(D122,Role_Mapping!$A$5:$D$31,4,FALSE()),"UNMAPPED") -> Consulting | Q122: =$N122*MAX(0,(MIN($G122,DATE(2026,7,31))-MAX($E122,DATE(2026,7,1))+1))/$O122 -> 9011.8056 | R122: =$N122*MAX(0,(MIN($G122,DATE(2026,8,31))-MAX($E122,DATE(2026,8,1))+1))/$O122 -> 8063.1944 | S122: =$N122*MAX(0,(MIN($G122,DATE(2026,9,30))-MAX($E122,DATE(2026,9,1))+1))/$O122 -> 0 | T122: =$N122*MAX(0,(MIN($G122,DATE(2026,10,31))-MAX($E122,DATE(2026,10,1))+1))/$O122 -> 0 | U122: =$N122*MAX(0,(MIN($G122,DATE(2026,11,30))-MAX($E122,DATE(2026,11,1))+1))/$O122 -> 0 | V122: =$N122*MAX(0,(MIN($G122,DATE(2026,12,31))-MAX($E122,DATE(2026,12,1))+1))/$O122 -> 0 | W122: =$H122*MAX(0,(MIN($G122,DATE(2026,7,31))-MAX($E122,DATE(2026,7,1))+1))/30.4 -> 0.625 | X122: =$H122*MAX(0,(MIN($G122,DATE(2026,8,31))-MAX($E122,DATE(2026,8,1))+1))/30.4 -> 0.55921053 | Y122: =$H122*MAX(0,(MIN($G122,DATE(2026,9,30))-MAX($E122,DATE(2026,9,1))+1))/30.4 -> 0 | Z122: =$H122*MAX(0,(MIN($G122,DATE(2026,10,31))-MAX($E122,DATE(2026,10,1))+1))/30.4 -> 0 | AA122: =$H122*MAX(0,(MIN($G122,DATE(2026,11,30))-MAX($E122,DATE(2026,11,1))+1))/30.4 -> 0 | AB122: =$H122*MAX(0,(MIN($G122,DATE(2026,12,31))-MAX($E122,DATE(2026,12,1))+1))/30.4 -> 0
A123: 72 | B123: 3 | D123: Enabler | E123: 46216 | F123: 5 | G123: 46251 | H123: 1 | I123: Not Resourced | J123: =IFERROR(VLOOKUP(D123,Role_Mapping!$A$5:$D$31,2,FALSE()),"UNMAPPED") -> Solutions Enabler | K123: =IFERROR(VLOOKUP(D123,Role_Mapping!$A$5:$D$31,3,FALSE()),"IN") -> IN | L123: =IFERROR(SUMPRODUCT((Rate_Card!$A$5:$A$34=J123)*(Rate_Card!$B$5:$B$34=K123)*Rate_Card!$C$5:$C$34),0) -> 683 | M123: =F123*5 -> 25 | N123: =L123*M123*H123 -> 17075 | O123: =(G123-E123)+1 -> 36 | P123: =IFERROR(VLOOKUP(D123,Role_Mapping!$A$5:$D$31,4,FALSE()),"UNMAPPED") -> Data Engineering | Q123: =$N123*MAX(0,(MIN($G123,DATE(2026,7,31))-MAX($E123,DATE(2026,7,1))+1))/$O123 -> 9011.8056 | R123: =$N123*MAX(0,(MIN($G123,DATE(2026,8,31))-MAX($E123,DATE(2026,8,1))+1))/$O123 -> 8063.1944 | S123: =$N123*MAX(0,(MIN($G123,DATE(2026,9,30))-MAX($E123,DATE(2026,9,1))+1))/$O123 -> 0 | T123: =$N123*MAX(0,(MIN($G123,DATE(2026,10,31))-MAX($E123,DATE(2026,10,1))+1))/$O123 -> 0 | U123: =$N123*MAX(0,(MIN($G123,DATE(2026,11,30))-MAX($E123,DATE(2026,11,1))+1))/$O123 -> 0 | V123: =$N123*MAX(0,(MIN($G123,DATE(2026,12,31))-MAX($E123,DATE(2026,12,1))+1))/$O123 -> 0 | W123: =$H123*MAX(0,(MIN($G123,DATE(2026,7,31))-MAX($E123,DATE(2026,7,1))+1))/30.4 -> 0.625 | X123: =$H123*MAX(0,(MIN($G123,DATE(2026,8,31))-MAX($E123,DATE(2026,8,1))+1))/30.4 -> 0.55921053 | Y123: =$H123*MAX(0,(MIN($G123,DATE(2026,9,30))-MAX($E123,DATE(2026,9,1))+1))/30.4 -> 0 | Z123: =$H123*MAX(0,(MIN($G123,DATE(2026,10,31))-MAX($E123,DATE(2026,10,1))+1))/30.4 -> 0 | AA123: =$H123*MAX(0,(MIN($G123,DATE(2026,11,30))-MAX($E123,DATE(2026,11,1))+1))/30.4 -> 0 | AB123: =$H123*MAX(0,(MIN($G123,DATE(2026,12,31))-MAX($E123,DATE(2026,12,1))+1))/30.4 -> 0
A124: 73 | B124: 3 | D124: SE | E124: 46216 | F124: 5 | G124: 46251 | H124: 1 | I124: Not Resourced | J124: =IFERROR(VLOOKUP(D124,Role_Mapping!$A$5:$D$31,2,FALSE()),"UNMAPPED") -> Software Engineer | K124: =IFERROR(VLOOKUP(D124,Role_Mapping!$A$5:$D$31,3,FALSE()),"IN") -> IN | L124: =IFERROR(SUMPRODUCT((Rate_Card!$A$5:$A$34=J124)*(Rate_Card!$B$5:$B$34=K124)*Rate_Card!$C$5:$C$34),0) -> 455 | M124: =F124*5 -> 25 | N124: =L124*M124*H124 -> 11375 | O124: =(G124-E124)+1 -> 36 | P124: =IFERROR(VLOOKUP(D124,Role_Mapping!$A$5:$D$31,4,FALSE()),"UNMAPPED") -> Full Stack | Q124: =$N124*MAX(0,(MIN($G124,DATE(2026,7,31))-MAX($E124,DATE(2026,7,1))+1))/$O124 -> 6003.4722 | R124: =$N124*MAX(0,(MIN($G124,DATE(2026,8,31))-MAX($E124,DATE(2026,8,1))+1))/$O124 -> 5371.5278 | S124: =$N124*MAX(0,(MIN($G124,DATE(2026,9,30))-MAX($E124,DATE(2026,9,1))+1))/$O124 -> 0 | T124: =$N124*MAX(0,(MIN($G124,DATE(2026,10,31))-MAX($E124,DATE(2026,10,1))+1))/$O124 -> 0 | U124: =$N124*MAX(0,(MIN($G124,DATE(2026,11,30))-MAX($E124,DATE(2026,11,1))+1))/$O124 -> 0 | V124: =$N124*MAX(0,(MIN($G124,DATE(2026,12,31))-MAX($E124,DATE(2026,12,1))+1))/$O124 -> 0 | W124: =$H124*MAX(0,(MIN($G124,DATE(2026,7,31))-MAX($E124,DATE(2026,7,1))+1))/30.4 -> 0.625 | X124: =$H124*MAX(0,(MIN($G124,DATE(2026,8,31))-MAX($E124,DATE(2026,8,1))+1))/30.4 -> 0.55921053 | Y124: =$H124*MAX(0,(MIN($G124,DATE(2026,9,30))-MAX($E124,DATE(2026,9,1))+1))/30.4 -> 0 | Z124: =$H124*MAX(0,(MIN($G124,DATE(2026,10,31))-MAX($E124,DATE(2026,10,1))+1))/30.4 -> 0 | AA124: =$H124*MAX(0,(MIN($G124,DATE(2026,11,30))-MAX($E124,DATE(2026,11,1))+1))/30.4 -> 0 | AB124: =$H124*MAX(0,(MIN($G124,DATE(2026,12,31))-MAX($E124,DATE(2026,12,1))+1))/30.4 -> 0
A125: 74 | B125: 3 | D125: SE | E125: 46216 | F125: 5 | G125: 46251 | H125: 1 | I125: Not Resourced | J125: =IFERROR(VLOOKUP(D125,Role_Mapping!$A$5:$D$31,2,FALSE()),"UNMAPPED") -> Software Engineer | K125: =IFERROR(VLOOKUP(D125,Role_Mapping!$A$5:$D$31,3,FALSE()),"IN") -> IN | L125: =IFERROR(SUMPRODUCT((Rate_Card!$A$5:$A$34=J125)*(Rate_Card!$B$5:$B$34=K125)*Rate_Card!$C$5:$C$34),0) -> 455 | M125: =F125*5 -> 25 | N125: =L125*M125*H125 -> 11375 | O125: =(G125-E125)+1 -> 36 | P125: =IFERROR(VLOOKUP(D125,Role_Mapping!$A$5:$D$31,4,FALSE()),"UNMAPPED") -> Full Stack | Q125: =$N125*MAX(0,(MIN($G125,DATE(2026,7,31))-MAX($E125,DATE(2026,7,1))+1))/$O125 -> 6003.4722 | R125: =$N125*MAX(0,(MIN($G125,DATE(2026,8,31))-MAX($E125,DATE(2026,8,1))+1))/$O125 -> 5371.5278 | S125: =$N125*MAX(0,(MIN($G125,DATE(2026,9,30))-MAX($E125,DATE(2026,9,1))+1))/$O125 -> 0 | T125: =$N125*MAX(0,(MIN($G125,DATE(2026,10,31))-MAX($E125,DATE(2026,10,1))+1))/$O125 -> 0 | U125: =$N125*MAX(0,(MIN($G125,DATE(2026,11,30))-MAX($E125,DATE(2026,11,1))+1))/$O125 -> 0 | V125: =$N125*MAX(0,(MIN($G125,DATE(2026,12,31))-MAX($E125,DATE(2026,12,1))+1))/$O125 -> 0 | W125: =$H125*MAX(0,(MIN($G125,DATE(2026,7,31))-MAX($E125,DATE(2026,7,1))+1))/30.4 -> 0.625 | X125: =$H125*MAX(0,(MIN($G125,DATE(2026,8,31))-MAX($E125,DATE(2026,8,1))+1))/30.4 -> 0.55921053 | Y125: =$H125*MAX(0,(MIN($G125,DATE(2026,9,30))-MAX($E125,DATE(2026,9,1))+1))/30.4 -> 0 | Z125: =$H125*MAX(0,(MIN($G125,DATE(2026,10,31))-MAX($E125,DATE(2026,10,1))+1))/30.4 -> 0 | AA125: =$H125*MAX(0,(MIN($G125,DATE(2026,11,30))-MAX($E125,DATE(2026,11,1))+1))/30.4 -> 0 | AB125: =$H125*MAX(0,(MIN($G125,DATE(2026,12,31))-MAX($E125,DATE(2026,12,1))+1))/30.4 -> 0
A126: 75 | B126: 3 | D126: SE | E126: 46216 | F126: 5 | G126: 46251 | H126: 1 | I126: Not Resourced | J126: =IFERROR(VLOOKUP(D126,Role_Mapping!$A$5:$D$31,2,FALSE()),"UNMAPPED") -> Software Engineer | K126: =IFERROR(VLOOKUP(D126,Role_Mapping!$A$5:$D$31,3,FALSE()),"IN") -> IN | L126: =IFERROR(SUMPRODUCT((Rate_Card!$A$5:$A$34=J126)*(Rate_Card!$B$5:$B$34=K126)*Rate_Card!$C$5:$C$34),0) -> 455 | M126: =F126*5 -> 25 | N126: =L126*M126*H126 -> 11375 | O126: =(G126-E126)+1 -> 36 | P126: =IFERROR(VLOOKUP(D126,Role_Mapping!$A$5:$D$31,4,FALSE()),"UNMAPPED") -> Full Stack | Q126: =$N126*MAX(0,(MIN($G126,DATE(2026,7,31))-MAX($E126,DATE(2026,7,1))+1))/$O126 -> 6003.4722 | R126: =$N126*MAX(0,(MIN($G126,DATE(2026,8,31))-MAX($E126,DATE(2026,8,1))+1))/$O126 -> 5371.5278 | S126: =$N126*MAX(0,(MIN($G126,DATE(2026,9,30))-MAX($E126,DATE(2026,9,1))+1))/$O126 -> 0 | T126: =$N126*MAX(0,(MIN($G126,DATE(2026,10,31))-MAX($E126,DATE(2026,10,1))+1))/$O126 -> 0 | U126: =$N126*MAX(0,(MIN($G126,DATE(2026,11,30))-MAX($E126,DATE(2026,11,1))+1))/$O126 -> 0 | V126: =$N126*MAX(0,(MIN($G126,DATE(2026,12,31))-MAX($E126,DATE(2026,12,1))+1))/$O126 -> 0 | W126: =$H126*MAX(0,(MIN($G126,DATE(2026,7,31))-MAX($E126,DATE(2026,7,1))+1))/30.4 -> 0.625 | X126: =$H126*MAX(0,(MIN($G126,DATE(2026,8,31))-MAX($E126,DATE(2026,8,1))+1))/30.4 -> 0.55921053 | Y126: =$H126*MAX(0,(MIN($G126,DATE(2026,9,30))-MAX($E126,DATE(2026,9,1))+1))/30.4 -> 0 | Z126: =$H126*MAX(0,(MIN($G126,DATE(2026,10,31))-MAX($E126,DATE(2026,10,1))+1))/30.4 -> 0 | AA126: =$H126*MAX(0,(MIN($G126,DATE(2026,11,30))-MAX($E126,DATE(2026,11,1))+1))/30.4 -> 0 | AB126: =$H126*MAX(0,(MIN($G126,DATE(2026,12,31))-MAX($E126,DATE(2026,12,1))+1))/30.4 -> 0
A127: 76 | B127: 3 | C127: Porsche | D127: P | E127: 46195 | F127: 5 | G127: 46230 | H127: 0.125 | I127: Resourced | J127: =IFERROR(VLOOKUP(D127,Role_Mapping!$A$5:$D$31,2,FALSE()),"UNMAPPED") -> Associate Partner | K127: =IFERROR(VLOOKUP(D127,Role_Mapping!$A$5:$D$31,3,FALSE()),"IN") -> UK | L127: =IFERROR(SUMPRODUCT((Rate_Card!$A$5:$A$34=J127)*(Rate_Card!$B$5:$B$34=K127)*Rate_Card!$C$5:$C$34),0) -> 3526 | M127: =F127*5 -> 25 | N127: =L127*M127*H127 -> 11018.75 | O127: =(G127-E127)+1 -> 36 | P127: =IFERROR(VLOOKUP(D127,Role_Mapping!$A$5:$D$31,4,FALSE()),"UNMAPPED") -> GTM | Q127: =$N127*MAX(0,(MIN($G127,DATE(2026,7,31))-MAX($E127,DATE(2026,7,1))+1))/$O127 -> 8264.0625 | R127: =$N127*MAX(0,(MIN($G127,DATE(2026,8,31))-MAX($E127,DATE(2026,8,1))+1))/$O127 -> 0 | S127: =$N127*MAX(0,(MIN($G127,DATE(2026,9,30))-MAX($E127,DATE(2026,9,1))+1))/$O127 -> 0 | T127: =$N127*MAX(0,(MIN($G127,DATE(2026,10,31))-MAX($E127,DATE(2026,10,1))+1))/$O127 -> 0 | U127: =$N127*MAX(0,(MIN($G127,DATE(2026,11,30))-MAX($E127,DATE(2026,11,1))+1))/$O127 -> 0 | V127: =$N127*MAX(0,(MIN($G127,DATE(2026,12,31))-MAX($E127,DATE(2026,12,1))+1))/$O127 -> 0 | W127: =$H127*MAX(0,(MIN($G127,DATE(2026,7,31))-MAX($E127,DATE(2026,7,1))+1))/30.4 -> 0.11101974 | X127: =$H127*MAX(0,(MIN($G127,DATE(2026,8,31))-MAX($E127,DATE(2026,8,1))+1))/30.4 -> 0 | Y127: =$H127*MAX(0,(MIN($G127,DATE(2026,9,30))-MAX($E127,DATE(2026,9,1))+1))/30.4 -> 0 | Z127: =$H127*MAX(0,(MIN($G127,DATE(2026,10,31))-MAX($E127,DATE(2026,10,1))+1))/30.4 -> 0 | AA127: =$H127*MAX(0,(MIN($G127,DATE(2026,11,30))-MAX($E127,DATE(2026,11,1))+1))/30.4 -> 0 | AB127: =$H127*MAX(0,(MIN($G127,DATE(2026,12,31))-MAX($E127,DATE(2026,12,1))+1))/30.4 -> 0
A128: 77 | B128: 3 | D128: M | E128: 46195 | F128: 5 | G128: 46230 | H128: 0.5 | I128: Resourced | J128: =IFERROR(VLOOKUP(D128,Role_Mapping!$A$5:$D$31,2,FALSE()),"UNMAPPED") -> Manager | K128: =IFERROR(VLOOKUP(D128,Role_Mapping!$A$5:$D$31,3,FALSE()),"IN") -> UK | L128: =IFERROR(SUMPRODUCT((Rate_Card!$A$5:$A$34=J128)*(Rate_Card!$B$5:$B$34=K128)*Rate_Card!$C$5:$C$34),0) -> 2984 | M128: =F128*5 -> 25 | N128: =L128*M128*H128 -> 37300 | O128: =(G128-E128)+1 -> 36 | P128: =IFERROR(VLOOKUP(D128,Role_Mapping!$A$5:$D$31,4,FALSE()),"UNMAPPED") -> Consulting | Q128: =$N128*MAX(0,(MIN($G128,DATE(2026,7,31))-MAX($E128,DATE(2026,7,1))+1))/$O128 -> 27975 | R128: =$N128*MAX(0,(MIN($G128,DATE(2026,8,31))-MAX($E128,DATE(2026,8,1))+1))/$O128 -> 0 | S128: =$N128*MAX(0,(MIN($G128,DATE(2026,9,30))-MAX($E128,DATE(2026,9,1))+1))/$O128 -> 0 | T128: =$N128*MAX(0,(MIN($G128,DATE(2026,10,31))-MAX($E128,DATE(2026,10,1))+1))/$O128 -> 0 | U128: =$N128*MAX(0,(MIN($G128,DATE(2026,11,30))-MAX($E128,DATE(2026,11,1))+1))/$O128 -> 0 | V128: =$N128*MAX(0,(MIN($G128,DATE(2026,12,31))-MAX($E128,DATE(2026,12,1))+1))/$O128 -> 0 | W128: =$H128*MAX(0,(MIN($G128,DATE(2026,7,31))-MAX($E128,DATE(2026,7,1))+1))/30.4 -> 0.44407895 | X128: =$H128*MAX(0,(MIN($G128,DATE(2026,8,31))-MAX($E128,DATE(2026,8,1))+1))/30.4 -> 0 | Y128: =$H128*MAX(0,(MIN($G128,DATE(2026,9,30))-MAX($E128,DATE(2026,9,1))+1))/30.4 -> 0 | Z128: =$H128*MAX(0,(MIN($G128,DATE(2026,10,31))-MAX($E128,DATE(2026,10,1))+1))/30.4 -> 0 | AA128: =$H128*MAX(0,(MIN($G128,DATE(2026,11,30))-MAX($E128,DATE(2026,11,1))+1))/30.4 -> 0 | AB128: =$H128*MAX(0,(MIN($G128,DATE(2026,12,31))-MAX($E128,DATE(2026,12,1))+1))/30.4 -> 0
A129: 78 | B129: 3 | D129: AC | E129: 46195 | F129: 5 | G129: 46230 | H129: 1 | I129: Resourced | J129: =IFERROR(VLOOKUP(D129,Role_Mapping!$A$5:$D$31,2,FALSE()),"UNMAPPED") -> Associate Consultant | K129: =IFERROR(VLOOKUP(D129,Role_Mapping!$A$5:$D$31,3,FALSE()),"IN") -> IN | L129: =IFERROR(SUMPRODUCT((Rate_Card!$A$5:$A$34=J129)*(Rate_Card!$B$5:$B$34=K129)*Rate_Card!$C$5:$C$34),0) -> 585 | M129: =F129*5 -> 25 | N129: =L129*M129*H129 -> 14625 | O129: =(G129-E129)+1 -> 36 | P129: =IFERROR(VLOOKUP(D129,Role_Mapping!$A$5:$D$31,4,FALSE()),"UNMAPPED") -> Consulting | Q129: =$N129*MAX(0,(MIN($G129,DATE(2026,7,31))-MAX($E129,DATE(2026,7,1))+1))/$O129 -> 10968.75 | R129: =$N129*MAX(0,(MIN($G129,DATE(2026,8,31))-MAX($E129,DATE(2026,8,1))+1))/$O129 -> 0 | S129: =$N129*MAX(0,(MIN($G129,DATE(2026,9,30))-MAX($E129,DATE(2026,9,1))+1))/$O129 -> 0 | T129: =$N129*MAX(0,(MIN($G129,DATE(2026,10,31))-MAX($E129,DATE(2026,10,1))+1))/$O129 -> 0 | U129: =$N129*MAX(0,(MIN($G129,DATE(2026,11,30))-MAX($E129,DATE(2026,11,1))+1))/$O129 -> 0 | V129: =$N129*MAX(0,(MIN($G129,DATE(2026,12,31))-MAX($E129,DATE(2026,12,1))+1))/$O129 -> 0 | W129: =$H129*MAX(0,(MIN($G129,DATE(2026,7,31))-MAX($E129,DATE(2026,7,1))+1))/30.4 -> 0.88815789 | X129: =$H129*MAX(0,(MIN($G129,DATE(2026,8,31))-MAX($E129,DATE(2026,8,1))+1))/30.4 -> 0 | Y129: =$H129*MAX(0,(MIN($G129,DATE(2026,9,30))-MAX($E129,DATE(2026,9,1))+1))/30.4 -> 0 | Z129: =$H129*MAX(0,(MIN($G129,DATE(2026,10,31))-MAX($E129,DATE(2026,10,1))+1))/30.4 -> 0 | AA129: =$H129*MAX(0,(MIN($G129,DATE(2026,11,30))-MAX($E129,DATE(2026,11,1))+1))/30.4 -> 0 | AB129: =$H129*MAX(0,(MIN($G129,DATE(2026,12,31))-MAX($E129,DATE(2026,12,1))+1))/30.4 -> 0
A130: 79 | B130: 3 | D130: Sol Con | E130: 46195 | F130: 5 | G130: 46230 | H130: 1 | I130: Resourced | J130: =IFERROR(VLOOKUP(D130,Role_Mapping!$A$5:$D$31,2,FALSE()),"UNMAPPED") -> Solutions Consultant | K130: =IFERROR(VLOOKUP(D130,Role_Mapping!$A$5:$D$31,3,FALSE()),"IN") -> IN | L130: =IFERROR(SUMPRODUCT((Rate_Card!$A$5:$A$34=J130)*(Rate_Card!$B$5:$B$34=K130)*Rate_Card!$C$5:$C$34),0) -> 683 | M130: =F130*5 -> 25 | N130: =L130*M130*H130 -> 17075 | O130: =(G130-E130)+1 -> 36 | P130: =IFERROR(VLOOKUP(D130,Role_Mapping!$A$5:$D$31,4,FALSE()),"UNMAPPED") -> Power BI & Consulting | Q130: =$N130*MAX(0,(MIN($G130,DATE(2026,7,31))-MAX($E130,DATE(2026,7,1))+1))/$O130 -> 12806.25 | R130: =$N130*MAX(0,(MIN($G130,DATE(2026,8,31))-MAX($E130,DATE(2026,8,1))+1))/$O130 -> 0 | S130: =$N130*MAX(0,(MIN($G130,DATE(2026,9,30))-MAX($E130,DATE(2026,9,1))+1))/$O130 -> 0 | T130: =$N130*MAX(0,(MIN($G130,DATE(2026,10,31))-MAX($E130,DATE(2026,10,1))+1))/$O130 -> 0 | U130: =$N130*MAX(0,(MIN($G130,DATE(2026,11,30))-MAX($E130,DATE(2026,11,1))+1))/$O130 -> 0 | V130: =$N130*MAX(0,(MIN($G130,DATE(2026,12,31))-MAX($E130,DATE(2026,12,1))+1))/$O130 -> 0 | W130: =$H130*MAX(0,(MIN($G130,DATE(2026,7,31))-MAX($E130,DATE(2026,7,1))+1))/30.4 -> 0.88815789 | X130: =$H130*MAX(0,(MIN($G130,DATE(2026,8,31))-MAX($E130,DATE(2026,8,1))+1))/30.4 -> 0 | Y130: =$H130*MAX(0,(MIN($G130,DATE(2026,9,30))-MAX($E130,DATE(2026,9,1))+1))/30.4 -> 0 | Z130: =$H130*MAX(0,(MIN($G130,DATE(2026,10,31))-MAX($E130,DATE(2026,10,1))+1))/30.4 -> 0 | AA130: =$H130*MAX(0,(MIN($G130,DATE(2026,11,30))-MAX($E130,DATE(2026,11,1))+1))/30.4 -> 0 | AB130: =$H130*MAX(0,(MIN($G130,DATE(2026,12,31))-MAX($E130,DATE(2026,12,1))+1))/30.4 -> 0
A131: 80 | B131: 3 | D131: Enabler | E131: 46195 | F131: 5 | G131: 46230 | H131: 1 | I131: Resourced | J131: =IFERROR(VLOOKUP(D131,Role_Mapping!$A$5:$D$31,2,FALSE()),"UNMAPPED") -> Solutions Enabler | K131: =IFERROR(VLOOKUP(D131,Role_Mapping!$A$5:$D$31,3,FALSE()),"IN") -> IN | L131: =IFERROR(SUMPRODUCT((Rate_Card!$A$5:$A$34=J131)*(Rate_Card!$B$5:$B$34=K131)*Rate_Card!$C$5:$C$34),0) -> 683 | M131: =F131*5 -> 25 | N131: =L131*M131*H131 -> 17075 | O131: =(G131-E131)+1 -> 36 | P131: =IFERROR(VLOOKUP(D131,Role_Mapping!$A$5:$D$31,4,FALSE()),"UNMAPPED") -> Data Engineering | Q131: =$N131*MAX(0,(MIN($G131,DATE(2026,7,31))-MAX($E131,DATE(2026,7,1))+1))/$O131 -> 12806.25 | R131: =$N131*MAX(0,(MIN($G131,DATE(2026,8,31))-MAX($E131,DATE(2026,8,1))+1))/$O131 -> 0 | S131: =$N131*MAX(0,(MIN($G131,DATE(2026,9,30))-MAX($E131,DATE(2026,9,1))+1))/$O131 -> 0 | T131: =$N131*MAX(0,(MIN($G131,DATE(2026,10,31))-MAX($E131,DATE(2026,10,1))+1))/$O131 -> 0 | U131: =$N131*MAX(0,(MIN($G131,DATE(2026,11,30))-MAX($E131,DATE(2026,11,1))+1))/$O131 -> 0 | V131: =$N131*MAX(0,(MIN($G131,DATE(2026,12,31))-MAX($E131,DATE(2026,12,1))+1))/$O131 -> 0 | W131: =$H131*MAX(0,(MIN($G131,DATE(2026,7,31))-MAX($E131,DATE(2026,7,1))+1))/30.4 -> 0.88815789 | X131: =$H131*MAX(0,(MIN($G131,DATE(2026,8,31))-MAX($E131,DATE(2026,8,1))+1))/30.4 -> 0 | Y131: =$H131*MAX(0,(MIN($G131,DATE(2026,9,30))-MAX($E131,DATE(2026,9,1))+1))/30.4 -> 0 | Z131: =$H131*MAX(0,(MIN($G131,DATE(2026,10,31))-MAX($E131,DATE(2026,10,1))+1))/30.4 -> 0 | AA131: =$H131*MAX(0,(MIN($G131,DATE(2026,11,30))-MAX($E131,DATE(2026,11,1))+1))/30.4 -> 0 | AB131: =$H131*MAX(0,(MIN($G131,DATE(2026,12,31))-MAX($E131,DATE(2026,12,1))+1))/30.4 -> 0
A132: 81 | B132: 3 | D132: SSE | E132: 46195 | F132: 5 | G132: 46230 | H132: 1 | I132: Resourced | J132: =IFERROR(VLOOKUP(D132,Role_Mapping!$A$5:$D$31,2,FALSE()),"UNMAPPED") -> Senior Software Engineer | K132: =IFERROR(VLOOKUP(D132,Role_Mapping!$A$5:$D$31,3,FALSE()),"IN") -> IN | L132: =IFERROR(SUMPRODUCT((Rate_Card!$A$5:$A$34=J132)*(Rate_Card!$B$5:$B$34=K132)*Rate_Card!$C$5:$C$34),0) -> 585 | M132: =F132*5 -> 25 | N132: =L132*M132*H132 -> 14625 | O132: =(G132-E132)+1 -> 36 | P132: =IFERROR(VLOOKUP(D132,Role_Mapping!$A$5:$D$31,4,FALSE()),"UNMAPPED") -> Full Stack | Q132: =$N132*MAX(0,(MIN($G132,DATE(2026,7,31))-MAX($E132,DATE(2026,7,1))+1))/$O132 -> 10968.75 | R132: =$N132*MAX(0,(MIN($G132,DATE(2026,8,31))-MAX($E132,DATE(2026,8,1))+1))/$O132 -> 0 | S132: =$N132*MAX(0,(MIN($G132,DATE(2026,9,30))-MAX($E132,DATE(2026,9,1))+1))/$O132 -> 0 | T132: =$N132*MAX(0,(MIN($G132,DATE(2026,10,31))-MAX($E132,DATE(2026,10,1))+1))/$O132 -> 0 | U132: =$N132*MAX(0,(MIN($G132,DATE(2026,11,30))-MAX($E132,DATE(2026,11,1))+1))/$O132 -> 0 | V132: =$N132*MAX(0,(MIN($G132,DATE(2026,12,31))-MAX($E132,DATE(2026,12,1))+1))/$O132 -> 0 | W132: =$H132*MAX(0,(MIN($G132,DATE(2026,7,31))-MAX($E132,DATE(2026,7,1))+1))/30.4 -> 0.88815789 | X132: =$H132*MAX(0,(MIN($G132,DATE(2026,8,31))-MAX($E132,DATE(2026,8,1))+1))/30.4 -> 0 | Y132: =$H132*MAX(0,(MIN($G132,DATE(2026,9,30))-MAX($E132,DATE(2026,9,1))+1))/30.4 -> 0 | Z132: =$H132*MAX(0,(MIN($G132,DATE(2026,10,31))-MAX($E132,DATE(2026,10,1))+1))/30.4 -> 0 | AA132: =$H132*MAX(0,(MIN($G132,DATE(2026,11,30))-MAX($E132,DATE(2026,11,1))+1))/30.4 -> 0 | AB132: =$H132*MAX(0,(MIN($G132,DATE(2026,12,31))-MAX($E132,DATE(2026,12,1))+1))/30.4 -> 0
A133: 82 | B133: 3 | D133: AC (UK) | E133: 46195 | F133: 5 | G133: 46230 | H133: 1 | I133: Resourced | J133: =IFERROR(VLOOKUP(D133,Role_Mapping!$A$5:$D$31,2,FALSE()),"UNMAPPED") -> Associate Consultant | K133: =IFERROR(VLOOKUP(D133,Role_Mapping!$A$5:$D$31,3,FALSE()),"IN") -> UK | L133: =IFERROR(SUMPRODUCT((Rate_Card!$A$5:$A$34=J133)*(Rate_Card!$B$5:$B$34=K133)*Rate_Card!$C$5:$C$34),0) -> 1866 | M133: =F133*5 -> 25 | N133: =L133*M133*H133 -> 46650 | O133: =(G133-E133)+1 -> 36 | P133: =IFERROR(VLOOKUP(D133,Role_Mapping!$A$5:$D$31,4,FALSE()),"UNMAPPED") -> Consulting | Q133: =$N133*MAX(0,(MIN($G133,DATE(2026,7,31))-MAX($E133,DATE(2026,7,1))+1))/$O133 -> 34987.5 | R133: =$N133*MAX(0,(MIN($G133,DATE(2026,8,31))-MAX($E133,DATE(2026,8,1))+1))/$O133 -> 0 | S133: =$N133*MAX(0,(MIN($G133,DATE(2026,9,30))-MAX($E133,DATE(2026,9,1))+1))/$O133 -> 0 | T133: =$N133*MAX(0,(MIN($G133,DATE(2026,10,31))-MAX($E133,DATE(2026,10,1))+1))/$O133 -> 0 | U133: =$N133*MAX(0,(MIN($G133,DATE(2026,11,30))-MAX($E133,DATE(2026,11,1))+1))/$O133 -> 0 | V133: =$N133*MAX(0,(MIN($G133,DATE(2026,12,31))-MAX($E133,DATE(2026,12,1))+1))/$O133 -> 0 | W133: =$H133*MAX(0,(MIN($G133,DATE(2026,7,31))-MAX($E133,DATE(2026,7,1))+1))/30.4 -> 0.88815789 | X133: =$H133*MAX(0,(MIN($G133,DATE(2026,8,31))-MAX($E133,DATE(2026,8,1))+1))/30.4 -> 0 | Y133: =$H133*MAX(0,(MIN($G133,DATE(2026,9,30))-MAX($E133,DATE(2026,9,1))+1))/30.4 -> 0 | Z133: =$H133*MAX(0,(MIN($G133,DATE(2026,10,31))-MAX($E133,DATE(2026,10,1))+1))/30.4 -> 0 | AA133: =$H133*MAX(0,(MIN($G133,DATE(2026,11,30))-MAX($E133,DATE(2026,11,1))+1))/30.4 -> 0 | AB133: =$H133*MAX(0,(MIN($G133,DATE(2026,12,31))-MAX($E133,DATE(2026,12,1))+1))/30.4 -> 0
A134: 83 | B134: 3 | D134: PA | E134: 46195 | F134: 5 | G134: 46230 | H134: 0.125 | I134: Resourced | J134: =IFERROR(VLOOKUP(D134,Role_Mapping!$A$5:$D$31,2,FALSE()),"UNMAPPED") -> Principal Technology Architect | K134: =IFERROR(VLOOKUP(D134,Role_Mapping!$A$5:$D$31,3,FALSE()),"IN") -> IN | L134: =IFERROR(SUMPRODUCT((Rate_Card!$A$5:$A$34=J134)*(Rate_Card!$B$5:$B$34=K134)*Rate_Card!$C$5:$C$34),0) -> 845 | M134: =F134*5 -> 25 | N134: =L134*M134*H134 -> 2640.625 | O134: =(G134-E134)+1 -> 36 | P134: =IFERROR(VLOOKUP(D134,Role_Mapping!$A$5:$D$31,4,FALSE()),"UNMAPPED") -> Full Stack | Q134: =$N134*MAX(0,(MIN($G134,DATE(2026,7,31))-MAX($E134,DATE(2026,7,1))+1))/$O134 -> 1980.4688 | R134: =$N134*MAX(0,(MIN($G134,DATE(2026,8,31))-MAX($E134,DATE(2026,8,1))+1))/$O134 -> 0 | S134: =$N134*MAX(0,(MIN($G134,DATE(2026,9,30))-MAX($E134,DATE(2026,9,1))+1))/$O134 -> 0 | T134: =$N134*MAX(0,(MIN($G134,DATE(2026,10,31))-MAX($E134,DATE(2026,10,1))+1))/$O134 -> 0 | U134: =$N134*MAX(0,(MIN($G134,DATE(2026,11,30))-MAX($E134,DATE(2026,11,1))+1))/$O134 -> 0 | V134: =$N134*MAX(0,(MIN($G134,DATE(2026,12,31))-MAX($E134,DATE(2026,12,1))+1))/$O134 -> 0 | W134: =$H134*MAX(0,(MIN($G134,DATE(2026,7,31))-MAX($E134,DATE(2026,7,1))+1))/30.4 -> 0.11101974 | X134: =$H134*MAX(0,(MIN($G134,DATE(2026,8,31))-MAX($E134,DATE(2026,8,1))+1))/30.4 -> 0 | Y134: =$H134*MAX(0,(MIN($G134,DATE(2026,9,30))-MAX($E134,DATE(2026,9,1))+1))/30.4 -> 0 | Z134: =$H134*MAX(0,(MIN($G134,DATE(2026,10,31))-MAX($E134,DATE(2026,10,1))+1))/30.4 -> 0 | AA134: =$H134*MAX(0,(MIN($G134,DATE(2026,11,30))-MAX($E134,DATE(2026,11,1))+1))/30.4 -> 0 | AB134: =$H134*MAX(0,(MIN($G134,DATE(2026,12,31))-MAX($E134,DATE(2026,12,1))+1))/30.4 -> 0
A135: 84 | B135: 3 | D135: Enabler | E135: 46195 | F135: 5 | G135: 46230 | H135: 1 | I135: Resourced | J135: =IFERROR(VLOOKUP(D135,Role_Mapping!$A$5:$D$31,2,FALSE()),"UNMAPPED") -> Solutions Enabler | K135: =IFERROR(VLOOKUP(D135,Role_Mapping!$A$5:$D$31,3,FALSE()),"IN") -> IN | L135: =IFERROR(SUMPRODUCT((Rate_Card!$A$5:$A$34=J135)*(Rate_Card!$B$5:$B$34=K135)*Rate_Card!$C$5:$C$34),0) -> 683 | M135: =F135*5 -> 25 | N135: =L135*M135*H135 -> 17075 | O135: =(G135-E135)+1 -> 36 | P135: =IFERROR(VLOOKUP(D135,Role_Mapping!$A$5:$D$31,4,FALSE()),"UNMAPPED") -> Data Engineering | Q135: =$N135*MAX(0,(MIN($G135,DATE(2026,7,31))-MAX($E135,DATE(2026,7,1))+1))/$O135 -> 12806.25 | R135: =$N135*MAX(0,(MIN($G135,DATE(2026,8,31))-MAX($E135,DATE(2026,8,1))+1))/$O135 -> 0 | S135: =$N135*MAX(0,(MIN($G135,DATE(2026,9,30))-MAX($E135,DATE(2026,9,1))+1))/$O135 -> 0 | T135: =$N135*MAX(0,(MIN($G135,DATE(2026,10,31))-MAX($E135,DATE(2026,10,1))+1))/$O135 -> 0 | U135: =$N135*MAX(0,(MIN($G135,DATE(2026,11,30))-MAX($E135,DATE(2026,11,1))+1))/$O135 -> 0 | V135: =$N135*MAX(0,(MIN($G135,DATE(2026,12,31))-MAX($E135,DATE(2026,12,1))+1))/$O135 -> 0 | W135: =$H135*MAX(0,(MIN($G135,DATE(2026,7,31))-MAX($E135,DATE(2026,7,1))+1))/30.4 -> 0.88815789 | X135: =$H135*MAX(0,(MIN($G135,DATE(2026,8,31))-MAX($E135,DATE(2026,8,1))+1))/30.4 -> 0 | Y135: =$H135*MAX(0,(MIN($G135,DATE(2026,9,30))-MAX($E135,DATE(2026,9,1))+1))/30.4 -> 0 | Z135: =$H135*MAX(0,(MIN($G135,DATE(2026,10,31))-MAX($E135,DATE(2026,10,1))+1))/30.4 -> 0 | AA135: =$H135*MAX(0,(MIN($G135,DATE(2026,11,30))-MAX($E135,DATE(2026,11,1))+1))/30.4 -> 0 | AB135: =$H135*MAX(0,(MIN($G135,DATE(2026,12,31))-MAX($E135,DATE(2026,12,1))+1))/30.4 -> 0
A136: 85 | B136: 3 | D136: SSE | E136: 46195 | F136: 5 | G136: 46230 | H136: 1 | I136: Not Resourced | J136: =IFERROR(VLOOKUP(D136,Role_Mapping!$A$5:$D$31,2,FALSE()),"UNMAPPED") -> Senior Software Engineer | K136: =IFERROR(VLOOKUP(D136,Role_Mapping!$A$5:$D$31,3,FALSE()),"IN") -> IN | L136: =IFERROR(SUMPRODUCT((Rate_Card!$A$5:$A$34=J136)*(Rate_Card!$B$5:$B$34=K136)*Rate_Card!$C$5:$C$34),0) -> 585 | M136: =F136*5 -> 25 | N136: =L136*M136*H136 -> 14625 | O136: =(G136-E136)+1 -> 36 | P136: =IFERROR(VLOOKUP(D136,Role_Mapping!$A$5:$D$31,4,FALSE()),"UNMAPPED") -> Full Stack | Q136: =$N136*MAX(0,(MIN($G136,DATE(2026,7,31))-MAX($E136,DATE(2026,7,1))+1))/$O136 -> 10968.75 | R136: =$N136*MAX(0,(MIN($G136,DATE(2026,8,31))-MAX($E136,DATE(2026,8,1))+1))/$O136 -> 0 | S136: =$N136*MAX(0,(MIN($G136,DATE(2026,9,30))-MAX($E136,DATE(2026,9,1))+1))/$O136 -> 0 | T136: =$N136*MAX(0,(MIN($G136,DATE(2026,10,31))-MAX($E136,DATE(2026,10,1))+1))/$O136 -> 0 | U136: =$N136*MAX(0,(MIN($G136,DATE(2026,11,30))-MAX($E136,DATE(2026,11,1))+1))/$O136 -> 0 | V136: =$N136*MAX(0,(MIN($G136,DATE(2026,12,31))-MAX($E136,DATE(2026,12,1))+1))/$O136 -> 0 | W136: =$H136*MAX(0,(MIN($G136,DATE(2026,7,31))-MAX($E136,DATE(2026,7,1))+1))/30.4 -> 0.88815789 | X136: =$H136*MAX(0,(MIN($G136,DATE(2026,8,31))-MAX($E136,DATE(2026,8,1))+1))/30.4 -> 0 | Y136: =$H136*MAX(0,(MIN($G136,DATE(2026,9,30))-MAX($E136,DATE(2026,9,1))+1))/30.4 -> 0 | Z136: =$H136*MAX(0,(MIN($G136,DATE(2026,10,31))-MAX($E136,DATE(2026,10,1))+1))/30.4 -> 0 | AA136: =$H136*MAX(0,(MIN($G136,DATE(2026,11,30))-MAX($E136,DATE(2026,11,1))+1))/30.4 -> 0 | AB136: =$H136*MAX(0,(MIN($G136,DATE(2026,12,31))-MAX($E136,DATE(2026,12,1))+1))/30.4 -> 0
A137: 86 | B137: 1 | C137: Mini | D137: AP | E137: 46209 | F137: 5 | G137: 46244 | H137: 0.125 | I137: Not Resourced | J137: =IFERROR(VLOOKUP(D137,Role_Mapping!$A$5:$D$31,2,FALSE()),"UNMAPPED") -> Associate Partner | K137: =IFERROR(VLOOKUP(D137,Role_Mapping!$A$5:$D$31,3,FALSE()),"IN") -> UK | L137: =IFERROR(SUMPRODUCT((Rate_Card!$A$5:$A$34=J137)*(Rate_Card!$B$5:$B$34=K137)*Rate_Card!$C$5:$C$34),0) -> 3526 | M137: =F137*5 -> 25 | N137: =L137*M137*H137 -> 11018.75 | O137: =(G137-E137)+1 -> 36 | P137: =IFERROR(VLOOKUP(D137,Role_Mapping!$A$5:$D$31,4,FALSE()),"UNMAPPED") -> GTM | Q137: =$N137*MAX(0,(MIN($G137,DATE(2026,7,31))-MAX($E137,DATE(2026,7,1))+1))/$O137 -> 7957.9861 | R137: =$N137*MAX(0,(MIN($G137,DATE(2026,8,31))-MAX($E137,DATE(2026,8,1))+1))/$O137 -> 3060.7639 | S137: =$N137*MAX(0,(MIN($G137,DATE(2026,9,30))-MAX($E137,DATE(2026,9,1))+1))/$O137 -> 0 | T137: =$N137*MAX(0,(MIN($G137,DATE(2026,10,31))-MAX($E137,DATE(2026,10,1))+1))/$O137 -> 0 | U137: =$N137*MAX(0,(MIN($G137,DATE(2026,11,30))-MAX($E137,DATE(2026,11,1))+1))/$O137 -> 0 | V137: =$N137*MAX(0,(MIN($G137,DATE(2026,12,31))-MAX($E137,DATE(2026,12,1))+1))/$O137 -> 0 | W137: =$H137*MAX(0,(MIN($G137,DATE(2026,7,31))-MAX($E137,DATE(2026,7,1))+1))/30.4 -> 0.10690789 | X137: =$H137*MAX(0,(MIN($G137,DATE(2026,8,31))-MAX($E137,DATE(2026,8,1))+1))/30.4 -> 0.041118421 | Y137: =$H137*MAX(0,(MIN($G137,DATE(2026,9,30))-MAX($E137,DATE(2026,9,1))+1))/30.4 -> 0 | Z137: =$H137*MAX(0,(MIN($G137,DATE(2026,10,31))-MAX($E137,DATE(2026,10,1))+1))/30.4 -> 0 | AA137: =$H137*MAX(0,(MIN($G137,DATE(2026,11,30))-MAX($E137,DATE(2026,11,1))+1))/30.4 -> 0 | AB137: =$H137*MAX(0,(MIN($G137,DATE(2026,12,31))-MAX($E137,DATE(2026,12,1))+1))/30.4 -> 0
A138: 87 | B138: 1 | D138: M | E138: 46209 | F138: 5 | G138: 46244 | H138: 0.5 | I138: Not Resourced | J138: =IFERROR(VLOOKUP(D138,Role_Mapping!$A$5:$D$31,2,FALSE()),"UNMAPPED") -> Manager | K138: =IFERROR(VLOOKUP(D138,Role_Mapping!$A$5:$D$31,3,FALSE()),"IN") -> UK | L138: =IFERROR(SUMPRODUCT((Rate_Card!$A$5:$A$34=J138)*(Rate_Card!$B$5:$B$34=K138)*Rate_Card!$C$5:$C$34),0) -> 2984 | M138: =F138*5 -> 25 | N138: =L138*M138*H138 -> 37300 | O138: =(G138-E138)+1 -> 36 | P138: =IFERROR(VLOOKUP(D138,Role_Mapping!$A$5:$D$31,4,FALSE()),"UNMAPPED") -> Consulting | Q138: =$N138*MAX(0,(MIN($G138,DATE(2026,7,31))-MAX($E138,DATE(2026,7,1))+1))/$O138 -> 26938.889 | R138: =$N138*MAX(0,(MIN($G138,DATE(2026,8,31))-MAX($E138,DATE(2026,8,1))+1))/$O138 -> 10361.111 | S138: =$N138*MAX(0,(MIN($G138,DATE(2026,9,30))-MAX($E138,DATE(2026,9,1))+1))/$O138 -> 0 | T138: =$N138*MAX(0,(MIN($G138,DATE(2026,10,31))-MAX($E138,DATE(2026,10,1))+1))/$O138 -> 0 | U138: =$N138*MAX(0,(MIN($G138,DATE(2026,11,30))-MAX($E138,DATE(2026,11,1))+1))/$O138 -> 0 | V138: =$N138*MAX(0,(MIN($G138,DATE(2026,12,31))-MAX($E138,DATE(2026,12,1))+1))/$O138 -> 0 | W138: =$H138*MAX(0,(MIN($G138,DATE(2026,7,31))-MAX($E138,DATE(2026,7,1))+1))/30.4 -> 0.42763158 | X138: =$H138*MAX(0,(MIN($G138,DATE(2026,8,31))-MAX($E138,DATE(2026,8,1))+1))/30.4 -> 0.16447368 | Y138: =$H138*MAX(0,(MIN($G138,DATE(2026,9,30))-MAX($E138,DATE(2026,9,1))+1))/30.4 -> 0 | Z138: =$H138*MAX(0,(MIN($G138,DATE(2026,10,31))-MAX($E138,DATE(2026,10,1))+1))/30.4 -> 0 | AA138: =$H138*MAX(0,(MIN($G138,DATE(2026,11,30))-MAX($E138,DATE(2026,11,1))+1))/30.4 -> 0 | AB138: =$H138*MAX(0,(MIN($G138,DATE(2026,12,31))-MAX($E138,DATE(2026,12,1))+1))/30.4 -> 0
A139: 88 | B139: 1 | D139: C | E139: 46209 | F139: 5 | G139: 46244 | H139: 1 | I139: Not Resourced | J139: =IFERROR(VLOOKUP(D139,Role_Mapping!$A$5:$D$31,2,FALSE()),"UNMAPPED") -> Consultant | K139: =IFERROR(VLOOKUP(D139,Role_Mapping!$A$5:$D$31,3,FALSE()),"IN") -> IN | L139: =IFERROR(SUMPRODUCT((Rate_Card!$A$5:$A$34=J139)*(Rate_Card!$B$5:$B$34=K139)*Rate_Card!$C$5:$C$34),0) -> 683 | M139: =F139*5 -> 25 | N139: =L139*M139*H139 -> 17075 | O139: =(G139-E139)+1 -> 36 | P139: =IFERROR(VLOOKUP(D139,Role_Mapping!$A$5:$D$31,4,FALSE()),"UNMAPPED") -> Consulting | Q139: =$N139*MAX(0,(MIN($G139,DATE(2026,7,31))-MAX($E139,DATE(2026,7,1))+1))/$O139 -> 12331.944 | R139: =$N139*MAX(0,(MIN($G139,DATE(2026,8,31))-MAX($E139,DATE(2026,8,1))+1))/$O139 -> 4743.0556 | S139: =$N139*MAX(0,(MIN($G139,DATE(2026,9,30))-MAX($E139,DATE(2026,9,1))+1))/$O139 -> 0 | T139: =$N139*MAX(0,(MIN($G139,DATE(2026,10,31))-MAX($E139,DATE(2026,10,1))+1))/$O139 -> 0 | U139: =$N139*MAX(0,(MIN($G139,DATE(2026,11,30))-MAX($E139,DATE(2026,11,1))+1))/$O139 -> 0 | V139: =$N139*MAX(0,(MIN($G139,DATE(2026,12,31))-MAX($E139,DATE(2026,12,1))+1))/$O139 -> 0 | W139: =$H139*MAX(0,(MIN($G139,DATE(2026,7,31))-MAX($E139,DATE(2026,7,1))+1))/30.4 -> 0.85526316 | X139: =$H139*MAX(0,(MIN($G139,DATE(2026,8,31))-MAX($E139,DATE(2026,8,1))+1))/30.4 -> 0.32894737 | Y139: =$H139*MAX(0,(MIN($G139,DATE(2026,9,30))-MAX($E139,DATE(2026,9,1))+1))/30.4 -> 0 | Z139: =$H139*MAX(0,(MIN($G139,DATE(2026,10,31))-MAX($E139,DATE(2026,10,1))+1))/30.4 -> 0 | AA139: =$H139*MAX(0,(MIN($G139,DATE(2026,11,30))-MAX($E139,DATE(2026,11,1))+1))/30.4 -> 0 | AB139: =$H139*MAX(0,(MIN($G139,DATE(2026,12,31))-MAX($E139,DATE(2026,12,1))+1))/30.4 -> 0
A140: 89 | B140: 1 | D140: PA | E140: 46209 | F140: 5 | G140: 46244 | H140: 0.25 | I140: Not Resourced | J140: =IFERROR(VLOOKUP(D140,Role_Mapping!$A$5:$D$31,2,FALSE()),"UNMAPPED") -> Principal Technology Architect | K140: =IFERROR(VLOOKUP(D140,Role_Mapping!$A$5:$D$31,3,FALSE()),"IN") -> IN | L140: =IFERROR(SUMPRODUCT((Rate_Card!$A$5:$A$34=J140)*(Rate_Card!$B$5:$B$34=K140)*Rate_Card!$C$5:$C$34),0) -> 845 | M140: =F140*5 -> 25 | N140: =L140*M140*H140 -> 5281.25 | O140: =(G140-E140)+1 -> 36 | P140: =IFERROR(VLOOKUP(D140,Role_Mapping!$A$5:$D$31,4,FALSE()),"UNMAPPED") -> Full Stack | Q140: =$N140*MAX(0,(MIN($G140,DATE(2026,7,31))-MAX($E140,DATE(2026,7,1))+1))/$O140 -> 3814.2361 | R140: =$N140*MAX(0,(MIN($G140,DATE(2026,8,31))-MAX($E140,DATE(2026,8,1))+1))/$O140 -> 1467.0139 | S140: =$N140*MAX(0,(MIN($G140,DATE(2026,9,30))-MAX($E140,DATE(2026,9,1))+1))/$O140 -> 0 | T140: =$N140*MAX(0,(MIN($G140,DATE(2026,10,31))-MAX($E140,DATE(2026,10,1))+1))/$O140 -> 0 | U140: =$N140*MAX(0,(MIN($G140,DATE(2026,11,30))-MAX($E140,DATE(2026,11,1))+1))/$O140 -> 0 | V140: =$N140*MAX(0,(MIN($G140,DATE(2026,12,31))-MAX($E140,DATE(2026,12,1))+1))/$O140 -> 0 | W140: =$H140*MAX(0,(MIN($G140,DATE(2026,7,31))-MAX($E140,DATE(2026,7,1))+1))/30.4 -> 0.21381579 | X140: =$H140*MAX(0,(MIN($G140,DATE(2026,8,31))-MAX($E140,DATE(2026,8,1))+1))/30.4 -> 0.082236842 | Y140: =$H140*MAX(0,(MIN($G140,DATE(2026,9,30))-MAX($E140,DATE(2026,9,1))+1))/30.4 -> 0 | Z140: =$H140*MAX(0,(MIN($G140,DATE(2026,10,31))-MAX($E140,DATE(2026,10,1))+1))/30.4 -> 0 | AA140: =$H140*MAX(0,(MIN($G140,DATE(2026,11,30))-MAX($E140,DATE(2026,11,1))+1))/30.4 -> 0 | AB140: =$H140*MAX(0,(MIN($G140,DATE(2026,12,31))-MAX($E140,DATE(2026,12,1))+1))/30.4 -> 0
A141: 90 | B141: 1 | D141: Sol Con | E141: 46209 | F141: 5 | G141: 46244 | H141: 0.75 | I141: Not Resourced | J141: =IFERROR(VLOOKUP(D141,Role_Mapping!$A$5:$D$31,2,FALSE()),"UNMAPPED") -> Solutions Consultant | K141: =IFERROR(VLOOKUP(D141,Role_Mapping!$A$5:$D$31,3,FALSE()),"IN") -> IN | L141: =IFERROR(SUMPRODUCT((Rate_Card!$A$5:$A$34=J141)*(Rate_Card!$B$5:$B$34=K141)*Rate_Card!$C$5:$C$34),0) -> 683 | M141: =F141*5 -> 25 | N141: =L141*M141*H141 -> 12806.25 | O141: =(G141-E141)+1 -> 36 | P141: =IFERROR(VLOOKUP(D141,Role_Mapping!$A$5:$D$31,4,FALSE()),"UNMAPPED") -> Power BI & Consulting | Q141: =$N141*MAX(0,(MIN($G141,DATE(2026,7,31))-MAX($E141,DATE(2026,7,1))+1))/$O141 -> 9248.9583 | R141: =$N141*MAX(0,(MIN($G141,DATE(2026,8,31))-MAX($E141,DATE(2026,8,1))+1))/$O141 -> 3557.2917 | S141: =$N141*MAX(0,(MIN($G141,DATE(2026,9,30))-MAX($E141,DATE(2026,9,1))+1))/$O141 -> 0 | T141: =$N141*MAX(0,(MIN($G141,DATE(2026,10,31))-MAX($E141,DATE(2026,10,1))+1))/$O141 -> 0 | U141: =$N141*MAX(0,(MIN($G141,DATE(2026,11,30))-MAX($E141,DATE(2026,11,1))+1))/$O141 -> 0 | V141: =$N141*MAX(0,(MIN($G141,DATE(2026,12,31))-MAX($E141,DATE(2026,12,1))+1))/$O141 -> 0 | W141: =$H141*MAX(0,(MIN($G141,DATE(2026,7,31))-MAX($E141,DATE(2026,7,1))+1))/30.4 -> 0.64144737 | X141: =$H141*MAX(0,(MIN($G141,DATE(2026,8,31))-MAX($E141,DATE(2026,8,1))+1))/30.4 -> 0.24671053 | Y141: =$H141*MAX(0,(MIN($G141,DATE(2026,9,30))-MAX($E141,DATE(2026,9,1))+1))/30.4 -> 0 | Z141: =$H141*MAX(0,(MIN($G141,DATE(2026,10,31))-MAX($E141,DATE(2026,10,1))+1))/30.4 -> 0 | AA141: =$H141*MAX(0,(MIN($G141,DATE(2026,11,30))-MAX($E141,DATE(2026,11,1))+1))/30.4 -> 0 | AB141: =$H141*MAX(0,(MIN($G141,DATE(2026,12,31))-MAX($E141,DATE(2026,12,1))+1))/30.4 -> 0
A142: 91 | B142: 1 | D142: SSE | E142: 46209 | F142: 5 | G142: 46244 | H142: 1 | I142: Not Resourced | J142: =IFERROR(VLOOKUP(D142,Role_Mapping!$A$5:$D$31,2,FALSE()),"UNMAPPED") -> Senior Software Engineer | K142: =IFERROR(VLOOKUP(D142,Role_Mapping!$A$5:$D$31,3,FALSE()),"IN") -> IN | L142: =IFERROR(SUMPRODUCT((Rate_Card!$A$5:$A$34=J142)*(Rate_Card!$B$5:$B$34=K142)*Rate_Card!$C$5:$C$34),0) -> 585 | M142: =F142*5 -> 25 | N142: =L142*M142*H142 -> 14625 | O142: =(G142-E142)+1 -> 36 | P142: =IFERROR(VLOOKUP(D142,Role_Mapping!$A$5:$D$31,4,FALSE()),"UNMAPPED") -> Full Stack | Q142: =$N142*MAX(0,(MIN($G142,DATE(2026,7,31))-MAX($E142,DATE(2026,7,1))+1))/$O142 -> 10562.5 | R142: =$N142*MAX(0,(MIN($G142,DATE(2026,8,31))-MAX($E142,DATE(2026,8,1))+1))/$O142 -> 4062.5 | S142: =$N142*MAX(0,(MIN($G142,DATE(2026,9,30))-MAX($E142,DATE(2026,9,1))+1))/$O142 -> 0 | T142: =$N142*MAX(0,(MIN($G142,DATE(2026,10,31))-MAX($E142,DATE(2026,10,1))+1))/$O142 -> 0 | U142: =$N142*MAX(0,(MIN($G142,DATE(2026,11,30))-MAX($E142,DATE(2026,11,1))+1))/$O142 -> 0 | V142: =$N142*MAX(0,(MIN($G142,DATE(2026,12,31))-MAX($E142,DATE(2026,12,1))+1))/$O142 -> 0 | W142: =$H142*MAX(0,(MIN($G142,DATE(2026,7,31))-MAX($E142,DATE(2026,7,1))+1))/30.4 -> 0.85526316 | X142: =$H142*MAX(0,(MIN($G142,DATE(2026,8,31))-MAX($E142,DATE(2026,8,1))+1))/30.4 -> 0.32894737 | Y142: =$H142*MAX(0,(MIN($G142,DATE(2026,9,30))-MAX($E142,DATE(2026,9,1))+1))/30.4 -> 0 | Z142: =$H142*MAX(0,(MIN($G142,DATE(2026,10,31))-MAX($E142,DATE(2026,10,1))+1))/30.4 -> 0 | AA142: =$H142*MAX(0,(MIN($G142,DATE(2026,11,30))-MAX($E142,DATE(2026,11,1))+1))/30.4 -> 0 | AB142: =$H142*MAX(0,(MIN($G142,DATE(2026,12,31))-MAX($E142,DATE(2026,12,1))+1))/30.4 -> 0
A143: 92 | B143: 4 | C143: Mercedes | D143: P | E143: 46188 | F143: 5 | G143: 46223 | H143: 0.125 | I143: Resourced | J143: =IFERROR(VLOOKUP(D143,Role_Mapping!$A$5:$D$31,2,FALSE()),"UNMAPPED") -> Associate Partner | K143: =IFERROR(VLOOKUP(D143,Role_Mapping!$A$5:$D$31,3,FALSE()),"IN") -> UK | L143: =IFERROR(SUMPRODUCT((Rate_Card!$A$5:$A$34=J143)*(Rate_Card!$B$5:$B$34=K143)*Rate_Card!$C$5:$C$34),0) -> 3526 | M143: =F143*5 -> 25 | N143: =L143*M143*H143 -> 11018.75 | O143: =(G143-E143)+1 -> 36 | P143: =IFERROR(VLOOKUP(D143,Role_Mapping!$A$5:$D$31,4,FALSE()),"UNMAPPED") -> GTM | Q143: =$N143*MAX(0,(MIN($G143,DATE(2026,7,31))-MAX($E143,DATE(2026,7,1))+1))/$O143 -> 6121.5278 | R143: =$N143*MAX(0,(MIN($G143,DATE(2026,8,31))-MAX($E143,DATE(2026,8,1))+1))/$O143 -> 0 | S143: =$N143*MAX(0,(MIN($G143,DATE(2026,9,30))-MAX($E143,DATE(2026,9,1))+1))/$O143 -> 0 | T143: =$N143*MAX(0,(MIN($G143,DATE(2026,10,31))-MAX($E143,DATE(2026,10,1))+1))/$O143 -> 0 | U143: =$N143*MAX(0,(MIN($G143,DATE(2026,11,30))-MAX($E143,DATE(2026,11,1))+1))/$O143 -> 0 | V143: =$N143*MAX(0,(MIN($G143,DATE(2026,12,31))-MAX($E143,DATE(2026,12,1))+1))/$O143 -> 0 | W143: =$H143*MAX(0,(MIN($G143,DATE(2026,7,31))-MAX($E143,DATE(2026,7,1))+1))/30.4 -> 0.082236842 | X143: =$H143*MAX(0,(MIN($G143,DATE(2026,8,31))-MAX($E143,DATE(2026,8,1))+1))/30.4 -> 0 | Y143: =$H143*MAX(0,(MIN($G143,DATE(2026,9,30))-MAX($E143,DATE(2026,9,1))+1))/30.4 -> 0 | Z143: =$H143*MAX(0,(MIN($G143,DATE(2026,10,31))-MAX($E143,DATE(2026,10,1))+1))/30.4 -> 0 | AA143: =$H143*MAX(0,(MIN($G143,DATE(2026,11,30))-MAX($E143,DATE(2026,11,1))+1))/30.4 -> 0 | AB143: =$H143*MAX(0,(MIN($G143,DATE(2026,12,31))-MAX($E143,DATE(2026,12,1))+1))/30.4 -> 0
A144: 93 | B144: 4 | D144: M | E144: 46188 | F144: 5 | G144: 46223 | H144: 0.25 | I144: Resourced | J144: =IFERROR(VLOOKUP(D144,Role_Mapping!$A$5:$D$31,2,FALSE()),"UNMAPPED") -> Manager | K144: =IFERROR(VLOOKUP(D144,Role_Mapping!$A$5:$D$31,3,FALSE()),"IN") -> UK | L144: =IFERROR(SUMPRODUCT((Rate_Card!$A$5:$A$34=J144)*(Rate_Card!$B$5:$B$34=K144)*Rate_Card!$C$5:$C$34),0) -> 2984 | M144: =F144*5 -> 25 | N144: =L144*M144*H144 -> 18650 | O144: =(G144-E144)+1 -> 36 | P144: =IFERROR(VLOOKUP(D144,Role_Mapping!$A$5:$D$31,4,FALSE()),"UNMAPPED") -> Consulting | Q144: =$N144*MAX(0,(MIN($G144,DATE(2026,7,31))-MAX($E144,DATE(2026,7,1))+1))/$O144 -> 10361.111 | R144: =$N144*MAX(0,(MIN($G144,DATE(2026,8,31))-MAX($E144,DATE(2026,8,1))+1))/$O144 -> 0 | S144: =$N144*MAX(0,(MIN($G144,DATE(2026,9,30))-MAX($E144,DATE(2026,9,1))+1))/$O144 -> 0 | T144: =$N144*MAX(0,(MIN($G144,DATE(2026,10,31))-MAX($E144,DATE(2026,10,1))+1))/$O144 -> 0 | U144: =$N144*MAX(0,(MIN($G144,DATE(2026,11,30))-MAX($E144,DATE(2026,11,1))+1))/$O144 -> 0 | V144: =$N144*MAX(0,(MIN($G144,DATE(2026,12,31))-MAX($E144,DATE(2026,12,1))+1))/$O144 -> 0 | W144: =$H144*MAX(0,(MIN($G144,DATE(2026,7,31))-MAX($E144,DATE(2026,7,1))+1))/30.4 -> 0.16447368 | X144: =$H144*MAX(0,(MIN($G144,DATE(2026,8,31))-MAX($E144,DATE(2026,8,1))+1))/30.4 -> 0 | Y144: =$H144*MAX(0,(MIN($G144,DATE(2026,9,30))-MAX($E144,DATE(2026,9,1))+1))/30.4 -> 0 | Z144: =$H144*MAX(0,(MIN($G144,DATE(2026,10,31))-MAX($E144,DATE(2026,10,1))+1))/30.4 -> 0 | AA144: =$H144*MAX(0,(MIN($G144,DATE(2026,11,30))-MAX($E144,DATE(2026,11,1))+1))/30.4 -> 0 | AB144: =$H144*MAX(0,(MIN($G144,DATE(2026,12,31))-MAX($E144,DATE(2026,12,1))+1))/30.4 -> 0
A145: 94 | B145: 4 | D145: C | E145: 46188 | F145: 5 | G145: 46223 | H145: 0.5 | I145: Resourced | J145: =IFERROR(VLOOKUP(D145,Role_Mapping!$A$5:$D$31,2,FALSE()),"UNMAPPED") -> Consultant | K145: =IFERROR(VLOOKUP(D145,Role_Mapping!$A$5:$D$31,3,FALSE()),"IN") -> IN | L145: =IFERROR(SUMPRODUCT((Rate_Card!$A$5:$A$34=J145)*(Rate_Card!$B$5:$B$34=K145)*Rate_Card!$C$5:$C$34),0) -> 683 | M145: =F145*5 -> 25 | N145: =L145*M145*H145 -> 8537.5 | O145: =(G145-E145)+1 -> 36 | P145: =IFERROR(VLOOKUP(D145,Role_Mapping!$A$5:$D$31,4,FALSE()),"UNMAPPED") -> Consulting | Q145: =$N145*MAX(0,(MIN($G145,DATE(2026,7,31))-MAX($E145,DATE(2026,7,1))+1))/$O145 -> 4743.0556 | R145: =$N145*MAX(0,(MIN($G145,DATE(2026,8,31))-MAX($E145,DATE(2026,8,1))+1))/$O145 -> 0 | S145: =$N145*MAX(0,(MIN($G145,DATE(2026,9,30))-MAX($E145,DATE(2026,9,1))+1))/$O145 -> 0 | T145: =$N145*MAX(0,(MIN($G145,DATE(2026,10,31))-MAX($E145,DATE(2026,10,1))+1))/$O145 -> 0 | U145: =$N145*MAX(0,(MIN($G145,DATE(2026,11,30))-MAX($E145,DATE(2026,11,1))+1))/$O145 -> 0 | V145: =$N145*MAX(0,(MIN($G145,DATE(2026,12,31))-MAX($E145,DATE(2026,12,1))+1))/$O145 -> 0 | W145: =$H145*MAX(0,(MIN($G145,DATE(2026,7,31))-MAX($E145,DATE(2026,7,1))+1))/30.4 -> 0.32894737 | X145: =$H145*MAX(0,(MIN($G145,DATE(2026,8,31))-MAX($E145,DATE(2026,8,1))+1))/30.4 -> 0 | Y145: =$H145*MAX(0,(MIN($G145,DATE(2026,9,30))-MAX($E145,DATE(2026,9,1))+1))/30.4 -> 0 | Z145: =$H145*MAX(0,(MIN($G145,DATE(2026,10,31))-MAX($E145,DATE(2026,10,1))+1))/30.4 -> 0 | AA145: =$H145*MAX(0,(MIN($G145,DATE(2026,11,30))-MAX($E145,DATE(2026,11,1))+1))/30.4 -> 0 | AB145: =$H145*MAX(0,(MIN($G145,DATE(2026,12,31))-MAX($E145,DATE(2026,12,1))+1))/30.4 -> 0
...

Sheet Revenue_Trend
A1: Top-Down Total Revenue Trend (Company-wide, all clusters combined)
A2: Actuals (Jan-Jun 2026) are from Pipeline Details > '6 Months Revenue' tab. Jul-Dec 2026 = FORECAST.LINEAR trend. Yellow = forecast.
A4: Month | B4: Month Index | C4: Actual Revenue (USD) | D4: Forecast Revenue (USD)
A5: Jan-2026 | B5: 1 | C5: 3801000
A6: Feb-2026 | B6: 2 | C6: 4139000
A7: Mar-2026 | B7: 3 | C7: 4153000
A8: Apr-2026 | B8: 4 | C8: 4177000
A9: May-2026 | B9: 5 | C9: 4290000
A10: Jun-2026 | B10: 6 | C10: 4355000
A11: Jul-2026 | B11: 7 | D11: =_xlfn.FORECAST.LINEAR(B11,$C$5:$C$10,$B$5:$B$10) -> 4477200
A12: Aug-2026 | B12: 8 | D12: =_xlfn.FORECAST.LINEAR(B12,$C$5:$C$10,$B$5:$B$10) -> 4569971.4
A13: Sep-2026 | B13: 9 | D13: =_xlfn.FORECAST.LINEAR(B13,$C$5:$C$10,$B$5:$B$10) -> 4662742.9
A14: Oct-2026 | B14: 10 | D14: =_xlfn.FORECAST.LINEAR(B14,$C$5:$C$10,$B$5:$B$10) -> 4755514.3
A15: Nov-2026 | B15: 11 | D15: =_xlfn.FORECAST.LINEAR(B15,$C$5:$C$10,$B$5:$B$10) -> 4848285.7
A16: Dec-2026 | B16: 12 | D16: =_xlfn.FORECAST.LINEAR(B16,$C$5:$C$10,$B$5:$B$10) -> 4941057.1

Sheet Cluster_Forecast
A1: Cluster Revenue Forecast - Next 6 Months (Jul-Dec 2026)
A2: Method: Forecast Revenue[Cluster,Month] = Total Revenue Trend[Month] (Revenue_Trend tab) x Cluster Weight[Cluster,Month] (this cluster's share of bottom-up pipeline revenue that month, from Pipeline_Data).
A4: 1) Bottom-Up Pipeline Revenue by Cluster (from Pipeline_Data)
A5: Cluster | B5: Jul-2026 | C5: Aug-2026 | D5: Sep-2026 | E5: Oct-2026 | F5: Nov-2026 | G5: Dec-2026
A6: Cluster 1 | B6: =SUMIFS(Pipeline_Data!$Q$5:$Q$297,Pipeline_Data!$B$5:$B$297,1) -> 516603.04 | C6: =SUMIFS(Pipeline_Data!$R$5:$R$297,Pipeline_Data!$B$5:$B$297,1) -> 247146.06 | D6: =SUMIFS(Pipeline_Data!$S$5:$S$297,Pipeline_Data!$B$5:$B$297,1) -> 82604.167 | E6: =SUMIFS(Pipeline_Data!$T$5:$T$297,Pipeline_Data!$B$5:$B$297,1) -> 13767.361 | F6: =SUMIFS(Pipeline_Data!$U$5:$U$297,Pipeline_Data!$B$5:$B$297,1) -> 0 | G6: =SUMIFS(Pipeline_Data!$V$5:$V$297,Pipeline_Data!$B$5:$B$297,1) -> 0
A7: Cluster 2 | B7: =SUMIFS(Pipeline_Data!$Q$5:$Q$297,Pipeline_Data!$B$5:$B$297,2) -> 415677.07 | C7: =SUMIFS(Pipeline_Data!$R$5:$R$297,Pipeline_Data!$B$5:$B$297,2) -> 280543.19 | D7: =SUMIFS(Pipeline_Data!$S$5:$S$297,Pipeline_Data!$B$5:$B$297,2) -> 75233.721 | E7: =SUMIFS(Pipeline_Data!$T$5:$T$297,Pipeline_Data!$B$5:$B$297,2) -> 0 | F7: =SUMIFS(Pipeline_Data!$U$5:$U$297,Pipeline_Data!$B$5:$B$297,2) -> 0 | G7: =SUMIFS(Pipeline_Data!$V$5:$V$297,Pipeline_Data!$B$5:$B$297,2) -> 0
A8: Cluster 3 | B8: =SUMIFS(Pipeline_Data!$Q$5:$Q$297,Pipeline_Data!$B$5:$B$297,3) -> 625644.29 | C8: =SUMIFS(Pipeline_Data!$R$5:$R$297,Pipeline_Data!$B$5:$B$297,3) -> 325529.11 | D8: =SUMIFS(Pipeline_Data!$S$5:$S$297,Pipeline_Data!$B$5:$B$297,3) -> 309966.98 | E8: =SUMIFS(Pipeline_Data!$T$5:$T$297,Pipeline_Data!$B$5:$B$297,3) -> 48311.751 | F8: =SUMIFS(Pipeline_Data!$U$5:$U$297,Pipeline_Data!$B$5:$B$297,3) -> 0 | G8: =SUMIFS(Pipeline_Data!$V$5:$V$297,Pipeline_Data!$B$5:$B$297,3) -> 0
A9: Cluster 4 | B9: =SUMIFS(Pipeline_Data!$Q$5:$Q$297,Pipeline_Data!$B$5:$B$297,4) -> 336604.23 | C9: =SUMIFS(Pipeline_Data!$R$5:$R$297,Pipeline_Data!$B$5:$B$297,4) -> 114859.43 | D9: =SUMIFS(Pipeline_Data!$S$5:$S$297,Pipeline_Data!$B$5:$B$297,4) -> 19553.836 | E9: =SUMIFS(Pipeline_Data!$T$5:$T$297,Pipeline_Data!$B$5:$B$297,4) -> 0 | F9: =SUMIFS(Pipeline_Data!$U$5:$U$297,Pipeline_Data!$B$5:$B$297,4) -> 0 | G9: =SUMIFS(Pipeline_Data!$V$5:$V$297,Pipeline_Data!$B$5:$B$297,4) -> 0
A10: Cluster 5 | B10: =SUMIFS(Pipeline_Data!$Q$5:$Q$297,Pipeline_Data!$B$5:$B$297,5) -> 400656.93 | C10: =SUMIFS(Pipeline_Data!$R$5:$R$297,Pipeline_Data!$B$5:$B$297,5) -> 444820.25 | D10: =SUMIFS(Pipeline_Data!$S$5:$S$297,Pipeline_Data!$B$5:$B$297,5) -> 517607.45 | E10: =SUMIFS(Pipeline_Data!$T$5:$T$297,Pipeline_Data!$B$5:$B$297,5) -> 228227.07 | F10: =SUMIFS(Pipeline_Data!$U$5:$U$297,Pipeline_Data!$B$5:$B$297,5) -> 83796.485 | G10: =SUMIFS(Pipeline_Data!$V$5:$V$297,Pipeline_Data!$B$5:$B$297,5) -> 0
A11: Column Total | B11: =SUM(B6:B10) -> 2295185.6 | C11: =SUM(C6:C10) -> 1412898 | D11: =SUM(D6:D10) -> 1004966.2 | E11: =SUM(E6:E10) -> 290306.18 | F11: =SUM(F6:F10) -> 83796.485 | G11: =SUM(G6:G10) -> 0
A13: 2) Cluster Weight % (this cluster's share of bottom-up pipeline that month)
A14: Cluster | B14: Jul-2026 | C14: Aug-2026 | D14: Sep-2026 | E14: Oct-2026 | F14: Nov-2026 | G14: Dec-2026 | H14: Avg Weight (6-mo)
A15: Cluster 1 | B15: =IF(B11>0,B6/B11,$H15) -> 0.22508117 | C15: =IF(C11>0,C6/C11,$H15) -> 0.17492137 | D15: =IF(D11>0,D6/D11,$H15) -> 0.082195969 | E15: =IF(E11>0,E6/E11,$H15) -> 0.047423589 | F15: =IF(F11>0,F6/F11,$H15) -> 0 | G15: =IF(G11>0,G6/G11,$H15) -> 0.16907703 | H15: =SUM(B6:G6)/SUM(B11:G11) -> 0.16907703
A16: Cluster 2 | B16: =IF(B11>0,B7/B11,$H16) -> 0.18110826 | C16: =IF(C11>0,C7/C11,$H16) -> 0.1985587 | D16: =IF(D11>0,D7/D11,$H16) -> 0.074861945 | E16: =IF(E11>0,E7/E11,$H16) -> 0 | F16: =IF(F11>0,F7/F11,$H16) -> 0 | G16: =IF(G11>0,G7/G11,$H16) -> 0.15164751 | H16: =SUM(B7:G7)/SUM(B11:G11) -> 0.15164751
A17: Cluster 3 | B17: =IF(B11>0,B8/B11,$H17) -> 0.27258985 | C17: =IF(C11>0,C8/C11,$H17) -> 0.23039816 | D17: =IF(D11>0,D8/D11,$H17) -> 0.30843524 | E17: =IF(E11>0,E8/E11,$H17) -> 0.16641654 | F17: =IF(F11>0,F8/F11,$H17) -> 0 | G17: =IF(G11>0,G8/G11,$H17) -> 0.25740375 | H17: =SUM(B8:G8)/SUM(B11:G11) -> 0.25740375
A18: Cluster 4 | B18: =IF(B11>0,B9/B11,$H18) -> 0.14665665 | C18: =IF(C11>0,C9/C11,$H18) -> 0.081293505 | D18: =IF(D11>0,D9/D11,$H18) -> 0.019457209 | E18: =IF(E11>0,E9/E11,$H18) -> 0 | F18: =IF(F11>0,F9/F11,$H18) -> 0 | G18: =IF(G11>0,G9/G11,$H18) -> 0.092589618 | H18: =SUM(B9:G9)/SUM(B11:G11) -> 0.092589618
A19: Cluster 5 | B19: =IF(B11>0,B10/B11,$H19) -> 0.17456407 | C19: =IF(C11>0,C10/C11,$H19) -> 0.31482827 | D19: =IF(D11>0,D10/D11,$H19) -> 0.51504964 | E19: =IF(E11>0,E10/E11,$H19) -> 0.78615987 | F19: =IF(F11>0,F10/F11,$H19) -> 1 | G19: =IF(G11>0,G10/G11,$H19) -> 0.32928209 | H19: =SUM(B10:G10)/SUM(B11:G11) -> 0.32928209
A21: 3) Top-Down Total Revenue Forecast (from Revenue_Trend tab)
B22: Jul-2026 | C22: Aug-2026 | D22: Sep-2026 | E22: Oct-2026 | F22: Nov-2026 | G22: Dec-2026
A23: Total Forecast Revenue (USD) | B23: =Revenue_Trend!$D$11 -> 4477200 | C23: =Revenue_Trend!$D$12 -> 4569971.4 | D23: =Revenue_Trend!$D$13 -> 4662742.9 | E23: =Revenue_Trend!$D$14 -> 4755514.3 | F23: =Revenue_Trend!$D$15 -> 4848285.7 | G23: =Revenue_Trend!$D$16 -> 4941057.1
A25: 4) FINAL: Forecast Revenue by Cluster by Month (Total Trend x Cluster Weight)
A26: Cluster | B26: Jul-2026 | C26: Aug-2026 | D26: Sep-2026 | E26: Oct-2026 | F26: Nov-2026 | G26: Dec-2026 | H26: 6-Month Total
A27: Cluster 1 | B27: =B23*B15 -> 1007733.4 | C27: =C23*C15 -> 799385.66 | D27: =D23*D15 -> 383258.67 | E27: =E23*E15 -> 225523.56 | F27: =F23*F15 -> 0 | G27: =G23*G15 -> 835419.27 | H27: =SUM(B27:G27) -> 3251320.6
A28: Cluster 2 | B28: =B23*B16 -> 810857.92 | C28: =C23*C16 -> 907407.57 | D28: =D23*D16 -> 349062 | E28: =E23*E16 -> 0 | F28: =F23*F16 -> 0 | G28: =G23*G16 -> 749299 | H28: =SUM(B28:G28) -> 2816626.5
A29: Cluster 3 | B29: =B23*B17 -> 1220439.3 | C29: =C23*C17 -> 1052913 | D29: =D23*D17 -> 1438154.2 | E29: =E23*E17 -> 791396.24 | F29: =F23*F17 -> 0 | G29: =G23*G17 -> 1271846.7 | H29: =SUM(B29:G29) -> 5774749.4
A30: Cluster 4 | B30: =B23*B18 -> 656611.16 | C30: =C23*C18 -> 371509 | D30: =D23*D18 -> 90723.961 | E30: =E23*E18 -> 0 | F30: =F23*F18 -> 0 | G30: =G23*G18 -> 457490.59 | H30: =SUM(B30:G30) -> 1576334.7
A31: Cluster 5 | B31: =B23*B19 -> 781558.25 | C31: =C23*C19 -> 1438756.2 | D31: =D23*D19 -> 2401544 | E31: =E23*E19 -> 3738594.5 | F31: =F23*F19 -> 4848285.7 | G31: =G23*G19 -> 1627001.6 | H31: =SUM(B31:G31) -> 14835740
A32: TOTAL (all clusters) | B32: =SUM(B27:B31) -> 4477200 | C32: =SUM(C27:C31) -> 4569971.4 | D32: =SUM(D27:D31) -> 4662742.9 | E32: =SUM(E27:E31) -> 4755514.3 | F32: =SUM(F27:F31) -> 4848285.7 | G32: =SUM(G27:G31) -> 4941057.1 | H32: =SUM(H27:H31) -> 28254771

Sheet COE_Supply_Demand
A1: COE Supply vs Demand - Next 6 Months (Jul-Dec 2026)
A2: Demand = pipeline role requests mapped to COE (Pipeline_Data 'Demand FTE' columns). Supply = active headcount by COE (Skill Data + Employee Details) minus employees already billable on confirmed projects (Project Allocation Details). Only 286 of 665 active employees have a recorded COE tag in Skill Data - Active/Busy headcount below reflect only that mapped population.
A4: 1) Active Headcount by COE (Skill Data primary COE x Employee Details active status)
A5: COE | B5: Active Headcount (all mapped)
A6: Data Engineering | B6: 91
A7: Techops & Automation | B7: 65
A8: Data Science & AI | B8: 54
A9: Full Stack | B9: 32
A10: Power BI & Consulting | B10: 40
A11: Consulting | B11: 3
A12: GTM | B12: 1
A14: 2) Already-Billable Headcount by COE by Month (Project Allocation Details, resourcing_status=BILLABLE)
A15: COE | B15: Jul-2026 | C15: Aug-2026 | D15: Sep-2026 | E15: Oct-2026 | F15: Nov-2026 | G15: Dec-2026
A16: Data Engineering | B16: 90 | C16: 90 | D16: 90 | E16: 90 | F16: 90 | G16: 90
A17: Techops & Automation | B17: 65 | C17: 65 | D17: 65 | E17: 65 | F17: 65 | G17: 65
A18: Data Science & AI | B18: 54 | C18: 54 | D18: 54 | E18: 54 | F18: 54 | G18: 54
A19: Full Stack | B19: 32 | C19: 32 | D19: 32 | E19: 32 | F19: 32 | G19: 32
A20: Power BI & Consulting | B20: 40 | C20: 40 | D20: 40 | E20: 40 | F20: 40 | G20: 40
A21: Consulting | B21: 3 | C21: 3 | D21: 3 | E21: 3 | F21: 3 | G21: 3
A22: GTM | B22: 1 | C22: 1 | D22: 1 | E22: 1 | F22: 1 | G22: 1
A24: 3) Available Supply by COE by Month (=Active Headcount − Already-Billable)
A25: COE | B25: Jul-2026 | C25: Aug-2026 | D25: Sep-2026 | E25: Oct-2026 | F25: Nov-2026 | G25: Dec-2026
A26: Data Engineering | B26: =$B6-B16 -> 1 | C26: =$B6-C16 -> 1 | D26: =$B6-D16 -> 1 | E26: =$B6-E16 -> 1 | F26: =$B6-F16 -> 1 | G26: =$B6-G16 -> 1
A27: Techops & Automation | B27: =$B7-B17 -> 0 | C27: =$B7-C17 -> 0 | D27: =$B7-D17 -> 0 | E27: =$B7-E17 -> 0 | F27: =$B7-F17 -> 0 | G27: =$B7-G17 -> 0
A28: Data Science & AI | B28: =$B8-B18 -> 0 | C28: =$B8-C18 -> 0 | D28: =$B8-D18 -> 0 | E28: =$B8-E18 -> 0 | F28: =$B8-F18 -> 0 | G28: =$B8-G18 -> 0
A29: Full Stack | B29: =$B9-B19 -> 0 | C29: =$B9-C19 -> 0 | D29: =$B9-D19 -> 0 | E29: =$B9-E19 -> 0 | F29: =$B9-F19 -> 0 | G29: =$B9-G19 -> 0
A30: Power BI & Consulting | B30: =$B10-B20 -> 0 | C30: =$B10-C20 -> 0 | D30: =$B10-D20 -> 0 | E30: =$B10-E20 -> 0 | F30: =$B10-F20 -> 0 | G30: =$B10-G20 -> 0
A31: Consulting | B31: =$B11-B21 -> 0 | C31: =$B11-C21 -> 0 | D31: =$B11-D21 -> 0 | E31: =$B11-E21 -> 0 | F31: =$B11-F21 -> 0 | G31: =$B11-G21 -> 0
A32: GTM | B32: =$B12-B22 -> 0 | C32: =$B12-C22 -> 0 | D32: =$B12-D22 -> 0 | E32: =$B12-E22 -> 0 | F32: =$B12-F22 -> 0 | G32: =$B12-G22 -> 0
A34: 4) Demand FTE by COE by Month (from Pipeline_Data, mapped via Role_Mapping)
A35: COE | B35: Jul-2026 | C35: Aug-2026 | D35: Sep-2026 | E35: Oct-2026 | F35: Nov-2026 | G35: Dec-2026
A36: Data Engineering | B36: =SUMIFS(Pipeline_Data!$W$5:$W$297,Pipeline_Data!$P$5:$P$297,$A36) -> 12.430099 | C36: =SUMIFS(Pipeline_Data!$X$5:$X$297,Pipeline_Data!$P$5:$P$297,$A36) -> 9.6669408 | D36: =SUMIFS(Pipeline_Data!$Y$5:$Y$297,Pipeline_Data!$P$5:$P$297,$A36) -> 5.7894737 | E36: =SUMIFS(Pipeline_Data!$Z$5:$Z$297,Pipeline_Data!$P$5:$P$297,$A36) -> 2.3684211 | F36: =SUMIFS(Pipeline_Data!$AA$5:$AA$297,Pipeline_Data!$P$5:$P$297,$A36) -> 0.82236842 | G36: =SUMIFS(Pipeline_Data!$AB$5:$AB$297,Pipeline_Data!$P$5:$P$297,$A36) -> 0
A37: Techops & Automation | B37: =SUMIFS(Pipeline_Data!$W$5:$W$297,Pipeline_Data!$P$5:$P$297,$A37) -> 0 | C37: =SUMIFS(Pipeline_Data!$X$5:$X$297,Pipeline_Data!$P$5:$P$297,$A37) -> 0 | D37: =SUMIFS(Pipeline_Data!$Y$5:$Y$297,Pipeline_Data!$P$5:$P$297,$A37) -> 0 | E37: =SUMIFS(Pipeline_Data!$Z$5:$Z$297,Pipeline_Data!$P$5:$P$297,$A37) -> 0 | F37: =SUMIFS(Pipeline_Data!$AA$5:$AA$297,Pipeline_Data!$P$5:$P$297,$A37) -> 0 | G37: =SUMIFS(Pipeline_Data!$AB$5:$AB$297,Pipeline_Data!$P$5:$P$297,$A37) -> 0
A38: Data Science & AI | B38: =SUMIFS(Pipeline_Data!$W$5:$W$297,Pipeline_Data!$P$5:$P$297,$A38) -> 0.12746711 | C38: =SUMIFS(Pipeline_Data!$X$5:$X$297,Pipeline_Data!$P$5:$P$297,$A38) -> 0.012335526 | D38: =SUMIFS(Pipeline_Data!$Y$5:$Y$297,Pipeline_Data!$P$5:$P$297,$A38) -> 0 | E38: =SUMIFS(Pipeline_Data!$Z$5:$Z$297,Pipeline_Data!$P$5:$P$297,$A38) -> 0 | F38: =SUMIFS(Pipeline_Data!$AA$5:$AA$297,Pipeline_Data!$P$5:$P$297,$A38) -> 0 | G38: =SUMIFS(Pipeline_Data!$AB$5:$AB$297,Pipeline_Data!$P$5:$P$297,$A38) -> 0
A39: Full Stack | B39: =SUMIFS(Pipeline_Data!$W$5:$W$297,Pipeline_Data!$P$5:$P$297,$A39) -> 50.509868 | C39: =SUMIFS(Pipeline_Data!$X$5:$X$297,Pipeline_Data!$P$5:$P$297,$A39) -> 28.889803 | D39: =SUMIFS(Pipeline_Data!$Y$5:$Y$297,Pipeline_Data!$P$5:$P$297,$A39) -> 21.299342 | E39: =SUMIFS(Pipeline_Data!$Z$5:$Z$297,Pipeline_Data!$P$5:$P$297,$A39) -> 6.2746711 | F39: =SUMIFS(Pipeline_Data!$AA$5:$AA$297,Pipeline_Data!$P$5:$P$297,$A39) -> 1.8503289 | G39: =SUMIFS(Pipeline_Data!$AB$5:$AB$297,Pipeline_Data!$P$5:$P$297,$A39) -> 0
A40: Power BI & Consulting | B40: =SUMIFS(Pipeline_Data!$W$5:$W$297,Pipeline_Data!$P$5:$P$297,$A40) -> 13.063322 | C40: =SUMIFS(Pipeline_Data!$X$5:$X$297,Pipeline_Data!$P$5:$P$297,$A40) -> 7.5246711 | D40: =SUMIFS(Pipeline_Data!$Y$5:$Y$297,Pipeline_Data!$P$5:$P$297,$A40) -> 7.5205592 | E40: =SUMIFS(Pipeline_Data!$Z$5:$Z$297,Pipeline_Data!$P$5:$P$297,$A40) -> 2.5493421 | F40: =SUMIFS(Pipeline_Data!$AA$5:$AA$297,Pipeline_Data!$P$5:$P$297,$A40) -> 0.41118421 | G40: =SUMIFS(Pipeline_Data!$AB$5:$AB$297,Pipeline_Data!$P$5:$P$297,$A40) -> 0
A41: Consulting | B41: =SUMIFS(Pipeline_Data!$W$5:$W$297,Pipeline_Data!$P$5:$P$297,$A41) -> 39.333882 | C41: =SUMIFS(Pipeline_Data!$X$5:$X$297,Pipeline_Data!$P$5:$P$297,$A41) -> 23.601974 | D41: =SUMIFS(Pipeline_Data!$Y$5:$Y$297,Pipeline_Data!$P$5:$P$297,$A41) -> 15.637336 | E41: =SUMIFS(Pipeline_Data!$Z$5:$Z$297,Pipeline_Data!$P$5:$P$297,$A41) -> 3.6266447 | F41: =SUMIFS(Pipeline_Data!$AA$5:$AA$297,Pipeline_Data!$P$5:$P$297,$A41) -> 1.0279605 | G41: =SUMIFS(Pipeline_Data!$AB$5:$AB$297,Pipeline_Data!$P$5:$P$297,$A41) -> 0
A42: GTM | B42: =SUMIFS(Pipeline_Data!$W$5:$W$297,Pipeline_Data!$P$5:$P$297,$A42) -> 3.6636513 | C42: =SUMIFS(Pipeline_Data!$X$5:$X$297,Pipeline_Data!$P$5:$P$297,$A42) -> 2.7837171 | D42: =SUMIFS(Pipeline_Data!$Y$5:$Y$297,Pipeline_Data!$P$5:$P$297,$A42) -> 2.109375 | E42: =SUMIFS(Pipeline_Data!$Z$5:$Z$297,Pipeline_Data!$P$5:$P$297,$A42) -> 0.67434211 | F42: =SUMIFS(Pipeline_Data!$AA$5:$AA$297,Pipeline_Data!$P$5:$P$297,$A42) -> 0.26315789 | G42: =SUMIFS(Pipeline_Data!$AB$5:$AB$297,Pipeline_Data!$P$5:$P$297,$A42) -> 0
A44: 5) FINAL: Capacity Gap by COE by Month (Supply − Demand; negative = shortfall, hire/reallocate)
A45: COE | B45: Jul-2026 | C45: Aug-2026 | D45: Sep-2026 | E45: Oct-2026 | F45: Nov-2026 | G45: Dec-2026
A46: Data Engineering | B46: =B26-B36 -> -11.430099 | C46: =C26-C36 -> -8.6669408 | D46: =D26-D36 -> -4.7894737 | E46: =E26-E36 -> -1.3684211 | F46: =F26-F36 -> 0.17763158 | G46: =G26-G36 -> 1
A47: Techops & Automation | B47: =B27-B37 -> 0 | C47: =C27-C37 -> 0 | D47: =D27-D37 -> 0 | E47: =E27-E37 -> 0 | F47: =F27-F37 -> 0 | G47: =G27-G37 -> 0
A48: Data Science & AI | B48: =B28-B38 -> -0.12746711 | C48: =C28-C38 -> -0.012335526 | D48: =D28-D38 -> 0 | E48: =E28-E38 -> 0 | F48: =F28-F38 -> 0 | G48: =G28-G38 -> 0
A49: Full Stack | B49: =B29-B39 -> -50.509868 | C49: =C29-C39 -> -28.889803 | D49: =D29-D39 -> -21.299342 | E49: =E29-E39 -> -6.2746711 | F49: =F29-F39 -> -1.8503289 | G49: =G29-G39 -> 0
A50: Power BI & Consulting | B50: =B30-B40 -> -13.063322 | C50: =C30-C40 -> -7.5246711 | D50: =D30-D40 -> -7.5205592 | E50: =E30-E40 -> -2.5493421 | F50: =F30-F40 -> -0.41118421 | G50: =G30-G40 -> 0
A51: Consulting | B51: =B31-B41 -> -39.333882 | C51: =C31-C41 -> -23.601974 | D51: =D31-D41 -> -15.637336 | E51: =E31-E41 -> -3.6266447 | F51: =F31-F41 -> -1.0279605 | G51: =G31-G41 -> 0
A52: GTM | B52: =B32-B42 -> -3.6636513 | C52: =C32-C42 -> -2.7837171 | D52: =D32-D42 -> -2.109375 | E52: =E32-E42 -> -0.67434211 | F52: =F32-F42 -> -0.26315789 | G52: =G32-G42 -> 0
